Workbook
Name hh: #REF!
Name hh: #REF!
Name hh: #REF!
Name riesgopais: #REF!
Name riesgopais: #REF!
Name Tabla3_RFFRFR: Tabla3[]
Name Tabla3_RFFRFRcustom: Tabla3[]
Name Tabla3_RFFRFRustom: Tabla3[]

Sheet Plantilla Usuario
B2: Fecha | C2: 45838
B3: País | C3: Peru
B4: Moneda | C4: Dólares
B5: Acciones | C5: 847191.73
B7: Primer año de información histórica (Anual) | C7: 2017
B8: Último año de información histórica (Anual) | C8: 2021
B9: Entrada EE.FF. | C9: 3289719;;;;3289719;3826276;;1865624;1198090;;;3826276;7115995;;;;2823965;;;;1391745;4215710;2900285;;;;2900285;7115995 | D9: 4103986;;;;4103986;4955240;;2537852;1361126;;;4955240;9059226;;;;3084554;;;;2729104;5813658;3245568;;;;3245568;9059226 | E9: 4490817;;;;4490817;6751464;;3323015;1540298;;;6751464;11242281;;;;3462553;;;;4321222;7783775;3458506;;;;3458506;11242281 | F9: 4618768;;;;4618768;7031343;;3410774;1801309;;;7031343;11650111;558545;;;3604331;3515304;;;4364956;7969287;3680824;;;;3680824;11650111 | G9: 6509850;;;;6509850;6898453;;3343589;1973854;;;6898453;13408303;639174;;;4645551;4676131;;;5437375;10082926;3325377;;;;3325377;13408303 | K9: 2017;3289719;;;;3289719;3826276;;1865624;1198090;;;3826276;7115995;;;;2823965;;;;1391745;4215710;2900285;;;;2900285;7115995;;;2017;6949265;-5042402;1906863;-633605;164314;-487579;-42607;743072;;;;;;;;;;;;;;;;;;;;;;;;;;;;;;;;;;;;;;;;
B10: BALANCE GENERAL | C10: =C7 -> 2017 | D10: =IF(C10<YEAR($C$2)-1,C10+1,"") -> 2018 | E10: =IF(D10<$C$8,D10+1,"") -> 2019 | F10: =IF(E10<$C$8,E10+1,"") -> 2020 | G10: =IF(F10<$C$8,F10+1,"") -> 2021 | H10: =IF(G10<$C$8,G10+1,"") | I10: =IF(H10<$C$8,H10+1,"") -> #VALUE! | J10: =IF(I10<$C$8,I10+1,"") -> #VALUE!
B11: Efectivo y Equivalentes al Efectivo | C11: {=IF(ISBLANK(C9), "", TRANSPOSE(IFERROR(VALUE(_xlfn.TEXTSPLIT(C9,";")),0)))} | D11: {=IF(ISBLANK(D9), "", TRANSPOSE(IFERROR(VALUE(_xlfn.TEXTSPLIT(D9,";")),0)))} | E11: {=IF(ISBLANK(E9), "", TRANSPOSE(IFERROR(VALUE(_xlfn.TEXTSPLIT(E9,";")),0)))} | F11: {=IF(ISBLANK(F9), "", TRANSPOSE(IFERROR(VALUE(_xlfn.TEXTSPLIT(F9,";")),0)))} | G11: {=IF(ISBLANK(G9), "", TRANSPOSE(IFERROR(VALUE(_xlfn.TEXTSPLIT(G9,";")),0)))}
B12: Cuentas por Cobrar Comerciales y Otras Cuentas por Cobrar | C12: 0 | D12: 0 | E12: 0 | F12: 0 | G12: 0
B13: Inventarios | C13: 0 | D13: 0 | E13: 0 | F13: 0 | G13: 0
B14: Otros activos no financieros | C14: 0 | D14: 0 | E14: 0 | F14: 0 | G14: 0
B15: Total Activos Corrientes | C15: 3289719 | D15: 4103986 | E15: 4490817 | F15: 4618768 | G15: 6509850
B16: Cuentas por Cobrar Comerciales y Otras Cuentas por Cobrar | C16: 3826276 | D16: 4955240 | E16: 6751464 | F16: 7031343 | G16: 6898453
B17: Inversiones Financieras e inmobiliarias | C17: 0 | D17: 0 | E17: 0 | F17: 0 | G17: 0
B18: Propiedades, Planta y Equipo | C18: 1865624 | D18: 2537852 | E18: 3323015 | F18: 3410774 | G18: 3343589
B19: Depreciación Acumulada* | C19: 1198090 | D19: 1361126 | E19: 1540298 | F19: 1801309 | G19: 1973854
B20: Activos Intangibles | C20: 0 | D20: 0 | E20: 0 | F20: 0 | G20: 0
B21: Otros activos no financieros | C21: 0 | D21: 0 | E21: 0 | F21: 0 | G21: 0
B22: Total Activos No Corrientes | C22: 3826276 | D22: 4955240 | E22: 6751464 | F22: 7031343 | G22: 6898453
B23: TOTAL ACTIVOS | C23: 7115995 | D23: 9059226 | E23: 11242281 | F23: 11650111 | G23: 13408303
... B38: TOTAL PASIVOS Y PATRIMONIO | C38: 7115995 | D38: 9059226 | E38: 11242281 | F38: 11650111 | G38: 13408303
B40: Entrada EE.RR. | C40: 6949265;-5042402;1906863;-633605;164314;-487579;-42607;743072;;;;;; | D40: 8288702;-6244012;2044690;-681336;202775;-603139;26059;786274;;;;;; | E40: 9872187;-7420013;2452174;-801905;298028;-651838;-49856;948575;;;;;; | F40: 10131767;-7712254;2419513;-862157;286071;-688428;-75085;793843;;;;;; | G40: 12227663;-9831454;2396209;-786246;232476;-732928;39531;916566;;-337756;;;;
B41: ESTADO DE RESULTADOS | C41: =C10 -> 2017 | D41: =D10 -> 2018 | E41: =E10 -> 2019 | F41: =F10 -> 2020 | G41: =G10 -> 2021 | H41: =H10
B42: Ingresos de Actividades Ordinarias | C42: {=IF(ISBLANK(C40), "", TRANSPOSE(IFERROR(VALUE(_xlfn.TEXTSPLIT(C40,";")),0)))} | D42: {=IF(ISBLANK(D40), "", TRANSPOSE(IFERROR(VALUE(_xlfn.TEXTSPLIT(D40,";")),0)))} | E42: {=IF(ISBLANK(E40), "", TRANSPOSE(IFERROR(VALUE(_xlfn.TEXTSPLIT(E40,";")),0)))} | F42: {=IF(ISBLANK(F40), "", TRANSPOSE(IFERROR(VALUE(_xlfn.TEXTSPLIT(F40,";")),0)))} | G42: {=IF(ISBLANK(G40), "", TRANSPOSE(IFERROR(VALUE(_xlfn.TEXTSPLIT(G40,";")),0)))}
B43: Costo de Ventas | C43: -5042402 | D43: -6244012 | E43: -7420013 | F43: -7712254 | G43: -9831454
B44: Utilidad Bruta | C44: 1906863 | D44: 2044690 | E44: 2452174 | F44: 2419513 | G44: 2396209
B45: Gastos de Ventas y Distribución | C45: -633605 | D45: -681336 | E45: -801905 | F45: -862157 | G45: -786246
B46: Depreciación* | C46: 164314 | D46: 202775 | E46: 298028 | F46: 286071 | G46: 232476
B47: Gastos de Administración | C47: -487579 | D47: -603139 | E47: -651838 | F47: -688428 | G47: -732928
B48: Otros ingresos (gastos) netos | C48: -42607 | D48: 26059 | E48: -49856 | F48: -75085 | G48: 39531
B49: Utilidad Operativa | C49: 743072 | D49: 786274 | E49: 948575 | F49: 793843 | G49: 916566
B50: Ingresos financieros | C50: 0 | D50: 0 | E50: 0 | F50: 0 | G50: 0
B51: Gastos financieros | C51: 0 | D51: 0 | E51: 0 | F51: 0 | G51: -337756
B52: Diferencia en cambio, neta | C52: 0 | D52: 0 | E52: 0 | F52: 0 | G52: 0
B53: Utilidad antes de impuesto a la renta | C53: 0 | D53: 0 | E53: 0 | F53: 0 | G53: 0
B54: Impuesto a la renta | C54: 0 | D54: 0 | E54: 0 | F54: 0 | G54: 0
B55: Utilidad neta | C55: 0 | D55: 0 | E55: 0 | F55: 0 | G55: 0
B70: Columna1 | C70: Columna2 | E70: Columna1 | F70: Columna2 | G70: Columna3 | H70: Columna4
B71: Empresa concepto | C71: ='M. por conceptos'!L195 -> 0 | E71: $$FVBGH$$ | F71: Fecha | G71: =C2 -> 45838
B72: Patrimonio concepto | C72: ='M. por conceptos'!L197 -> -5437375 | E72: $$SWXSD$$ | F72: Moneda | G72: =C4 -> Dólares
B73: Acciones concepto | C73: ='M. por conceptos'!L198 -> -6.4181162 | E73: $$KIJUN$$ | G73: Metodo por conceptos | H73: Metodo Integrado
B74: Empresa integrado | C74: ='M. Integrado'!L49 -> 0 | E74: $$KIJUG$$ | F74: Valor de la empresa | G74: ='M. por conceptos'!L195 -> 0 | H74: ='M. Integrado'!L49 -> 0
B75: Patrimonio integrado | C75: ='M. Integrado'!L51 -> -5437375 | E75: $$KIJUJ$$ | F75: Valor de la deuda | G75: ='M. por conceptos'!L196 -> 5437375 | H75: ='M. Integrado'!L50 -> 5437375
B76: Acciones integrado | C76: ='M. Integrado'!L52 -> -6.4181162 | E76: $$KIJUY$$ | F76: Valor del patrimonio | G76: ='M. por conceptos'!L197 -> -5437375 | H76: ='M. Integrado'!L51 -> -5437375
B77: Primer año historico | C77: =C7 -> 2017 | E77: $$KIJUT$$ | F77: Precio por acción | G77: ='M. por conceptos'!L198 -> -6.4181162 | H77: ='M. Integrado'!L52 -> -6.4181162
B78: Ultimo año historico | C78: =C8 -> 2021 | E78: $$PQOSJ$$ | F78: Gastos por venta | G78: ='M. por conceptos'!H48 -> #REF!
B79: Valor financiero concepto | C79: ='M. por conceptos'!L197 -> -5437375 | E79: $$LOKIH$$ | F79: Gastos administrativos | G79: ='M. por conceptos'!H66 -> #REF!
B80: Valor financiero integrado | C80: ='M. Integrado'!L51 -> -5437375 | E80: $$NHGTF$$ | F80: CAPEX | G80: ='M. por conceptos'!H117 -> #REF!
B81: Valor financiero concepto sensibilidad | C81: =Sensibilidad!H100 -> 0 | E81: $$NHGTC$$ | F81: Capital de trabajo | G81: ='M. por conceptos'!H143 -> #REF!
B82: Valor financiero integrado sensibilidad | C82: =Sensibilidad!H130 -> 0 | G82: Metodo Integrado
B83: Tasa de crecimiento de largo plazo | C83: =Sensibilidad!G14 -> 0.015 | E83: $$TEST3$$ | F83: Valor de la empresa | G83: ='M. Integrado'!L49 -> 0
B84: Costo de Capital CPPC/WACC | C84: =Sensibilidad!M100 -> 0.091 | E84: $$TEST4$$ | F84: Valor de la deuda | G84: ='M. Integrado'!L50 -> 5437375
B85: Tasa de crecimiento de los ingresos | C85: =Sensibilidad!D10 -> #REF! | E85: $$TEST5$$ | F85: Valor del patrimonio | G85: ='M. Integrado'!L51 -> -5437375
B86: Valor del patrimonio concepto sensibilidad | C86: =Sensibilidad!H102 -> -5437375 | E86: $$TEST6$$ | F86: Precio por acción | G86: ='M. Integrado'!L52 -> -6.4181162
B87: Valor por acción concepto sensibilidad | C87: =Sensibilidad!H103 -> -6.4181162
B88: Valor del patrimonio integrado sensibilidad | C88: =Sensibilidad!H132 -> -5437375
B89: Valor por acción concepto sensibilidad | C89: =Sensibilidad!H133 -> -6.4181162
B92: Conceptos
B220: Integrado

Sheet WACC
B3: Tratamiento del Rf | C3: Bono EE.UU | E3: Fecha | F3: ='Plantilla Usuario'!C2 -> 45838 | H3: Costo de deuda (Kd) | I3: =ROUND(-HLOOKUP('Plantilla Usuario'!$C$8,'Plantilla Usuario'!B10:Q55,42)/(HLOOKUP('Plantilla Usuario'!$C$8-1,'Plantilla Usuario'!B10:G38,15)+HLOOKUP('Plantilla Usuario'!$C$8-1,'Plantilla Usuario'!B10:G38,19)),4) -> 0.0829 | J3: =+'Plantilla Usuario'!C4 -> Dólares | N3: 1. Evolución del Be
A5: I. | B5: Parametros generales | D5: VI. | E5: Parámetros para el mercado emergente | G5: VI. | H5: Parámetros para la empresa | O5: Rm Promedio | P5: Rf Promedio | Q5: Rf Spot
B6: Bono EE.UU seleccionado | C6: 1 | D6: años | E6: País | F6: ='Plantilla Usuario'!C3 -> Peru | I6: Dólares | J6: Dev. esperada | K6: Moneda Nac | N6: Mercado Desarrollado | O6: ='Prima de mercado'!C$3 -> 0.11821279 | P6: ='Prima de mercado'!$D$3 -> 0.051104658 | Q6: =$C$10 -> 0.0416
B7: Bono del Rf ajustado | C7: ='Rf Ajustado'!E11 -> 2.8477432 | D7: años | E7: Devaluación Esperada | F7: 0.0164 | I7: =IF($K$7=0,0,(1+$K$7)/(1+$J$7)-1) -> 0 | J7: =$F$7 -> 0.0164 | K7: =IF($J$3="Soles",I3,0) -> 0 | N7: Mercado Emergente | O7: ='Prima de mercado'!C$3 -> 0.11821279 | P7: ='Prima de mercado'!$D$3 -> 0.051104658 | Q7: =$C$10 -> 0.0416
H8: Costo de deuda (Kd) | I8: =IF($J$3="Dólares",$I$3,0) -> 0.0829 | J8: =$F$7 -> 0.0164 | K8: =IF(I8=0,0,(1+$I$8)*(1+$J$8)-1) -> 0.10065956 | N8: Empresa | O8: ='Prima de mercado'!C$3 -> 0.11821279 | P8: ='Prima de mercado'!$D$3 -> 0.051104658 | Q8: =$C$10 -> 0.0416
B9: Prima de Mercado (Rm -Rf) | C9: =VLOOKUP(YEAR($F$3),'Prima de mercado'!A2:D7,2) -> 0.066379627 | E9: Riesgo país | F9: =VLOOKUP($F$6,Embi!$L$2:$M$11,2,FALSE)/10000 -> 0.015438095
B10: Tasa libre de Riesgo (Rf) | C10: =IF($C$3="Bono EE.UU",VLOOKUP($C$6,'Rf Ajustado'!$A$14:$B$25,2,FALSE),'Rf Ajustado'!$E$12) -> 0.0416 | H10: Prima empresa | I10: =IF(J3="Dólares",I3-F33,I7-F33) -> 0.0058619048
N11: 2. Formación de las tasas
A12: II. | B12: Parámetros del sector de referencia
B13: Sector | C13: Publicidad | N13: Mercado desarrollado | AN13: WACC (Capitalización de Mercado) - Método por conceptos
O14: Ke | P14: Koa | Q14: Kd
B15: MERCADO DESARROLLADO | E15: MERCADO EMERGENTE | H15: EMPRESA | N15: Rf | O15: =$C$10 -> 0.0416 | P15: =$C$10 -> 0.0416 | Q15: =$C$10 -> 0.0416 | AN15: Porcentaje de deuda (%D) | AO15: =('EE.FF Económicos'!$H$17+'EE.FF Económicos'!$H$21)/('EE.FF Económicos'!$H$17+'EE.FF Económicos'!$H$21+'M. por conceptos'!$L$184) -> -43.54309
N16: Riesgo de negocio | O16: =C9*C21 -> 0.04971834 | AN16: Porcentaje de Capital (%C) | AO16: =1-AO15 -> 44.54309
B17: Porcentaje de deuda (%D) | C17: =IF(AND(WACC!$F$3>Tablas!$I$3,WACC!$F$3<=Tablas!$J$6), VLOOKUP(WACC!$C$13,'Damondaran Industries'!$A$1:$AE$95,2 + 6 * ROUNDDOWN((WACC!$F$3 - Tablas!$I$3) / (Tablas!$J$6 - Tablas!$I$3) * 3, 0), FALSE), VLOOKUP(WACC!$C$13,'Damondaran Industries'!$A$1:$AE$95,7,FALSE) ) -> 0.31029224 | E17: Porcentaje de deuda (%D) | F17: =IF(G17,G17,C17) -> 0.31029224 | H17: Porcentaje de deuda (%D) | I17: =ROUND(('EE.FF Económicos'!H17+'EE.FF Económicos'!H21)/('EE.FF Económicos'!H17+'EE.FF Económicos'!H21+'EE.FF Económicos'!H26),4) -> 0.6151 | N17: Riesgo económico de negocio | P17: =C27*C9 -> 0.037768475 | AN17: Ratio D/C | AO17: =AO15/AO16 -> -0.97754983
B18: Porcentaje de Capital (%C) | C18: =IF(AND(WACC!$F$3>Tablas!$I$3,WACC!$F$3<=Tablas!$J$6), VLOOKUP(WACC!$C$13,'Damondaran Industries'!$A$1:$AE$95,3 + 6 * ROUNDDOWN((WACC!$F$3 - Tablas!$I$3) / (Tablas!$J$6 - Tablas!$I$3) * 3, 0), FALSE), VLOOKUP(WACC!$C$13,'Damondaran Industries'!$A$1:$AE$95,7,FALSE) ) -> 0.68970776 | E18: Porcentaje de Capital (%C) | F18: =1-F17 -> 0.68970776 | H18: Porcentaje de Capital (%C) | I18: =1-I17 -> 0.3849 | N18: Spread de la deuda | Q18: =C32 -> 0.02 | AN18: Tasa de Impuesto (T) | AO18: =+I20 -> 0.295
B19: Ratio D/C | C19: 0.5186 | E19: Ratio D/C | F19: =F17/F18 -> 0.44988945 | H19: Ratio D/C | I19: =I17/I18 -> 1.5980774 | O19: =SUM(O15:O18) -> 0.09131834 | P19: =SUM(P15:P18) -> 0.079368475 | Q19: =SUM(Q15:Q18) -> 0.0616 | AN19: Beta apalancado (Be) | AO19: =$C$27*(1+(1-$AO$18)*$AO$17) -> 0.1768536
B20: Tasa de Impuesto (T) | C20: 0.3899 | E20: Tasa de Impuesto (T) | F20: 0.295 | H20: Tasa de Impuesto (T) | I20: =+F20 -> 0.295 | Q20: =Q19*(1-C20) -> 0.03758216
B21: Beta apalancado (Be) | C21: 0.749 | E21: Beta apalancado (Be) | F21: =$C$27*(1+(1-$F$20)*$F$19) -> 0.7494405 | H21: Beta apalancado (Be) | I21: =$C$27*(1+(1-$I$20)*$I$19) -> 1.2100117 | AO21: Dólares | AP21: Moneda Nacional
AN22: Costo de Capital Financiero (Ke) | AO22: =$C$10+$AO$19*$C$9+$F$9+$I$10 -> 0.074639476 | AP22: =(1+$AO$22)*(1+$J$7)-1 -> 0.092263563
A23: III. | B23: Determinación del Costo de Capital Financiero | I23: Dólares | J23: Moneda Nacional | N23: Mercado emergente
A24: Ke = rf + Be (Rm-rf) | B24: Costo de Capital Financiero (Ke) | C24: =$C$10+$C$21*$C$9 -> 0.09131834 | E24: Costo de Capital Financiero (Ke) | F24: =$C$10+$F$21*$C$9+$F$9 -> 0.10678568 | H24: Costo de Capital Financiero (Ke) | I24: =ROUND($C$10+$I$21*$C$9+$F$9+$I$10,4) -> 0.1432 | J24: =ROUND((1+$I$24)*(1+$J$7)-1,4) -> 0.1619 | O24: Ke | P24: Koa | Q24: Kd
N25: Rf | O25: =O15 -> 0.0416 | P25: =P15 -> 0.0416 | Q25: =Q15 -> 0.0416 | AO25: Dólares | AP25: Moneda Nacional
A26: IV. | B26: Determinación del Costo de Capital Económico | N26: Riesgo de negocio | O26: =F21*C9 -> 0.049747581 | AN26: Costo de Capital Económico (Koa) | AO26: =$F$28+$I$10 -> 0.10066848 | AP26: =(1+$AO$26)*(1+$J$7)-1 -> 0.11871944
A27: Koa = rf + Boa (Rm-rf) | B27: Beta desapalancado (Boa) | C27: =$C$21/(1+(1-$C$20)*$C$19) -> 0.56897692 | E27: Beta desapalancado (Boa) | F27: =$F$21/(1+(1-$F$20)*$F$19) -> 0.56897692 | I27: Dólares | J27: Moneda Nacional | N27: Riesgo económico de negocio | P27: =F27*C9 -> 0.037768475
B28: Costo de Capital Económico (Koa) | C28: =$C$10+$C$27*$C$9 -> 0.079368475 | E28: Costo de Capital Económico (Koa) | F28: =$C$10+$F$27*$C$9+$F$9 -> 0.094806571 | H28: Costo de Capital Económico (Koa) | I28: =ROUND($F$28+$I$10,4) -> 0.1007 | J28: =ROUND((1+$I$28)*(1+$J$7)-1,4) -> 0.1188 | N28: Spread de la deuda | Q28: =C32 -> 0.02
N29: Riesgo país | O29: =$F$9 -> 0.015438095 | P29: =$F$9 -> 0.015438095 | Q29: =$F$9 -> 0.015438095
A30: V. | B30: Determinación de la Prima de Riesgo sobre la Deuda | O30: =SUM(O25:O29) -> 0.10678568 | P30: =SUM(P25:P29) -> 0.094806571 | Q30: =SUM(Q25:Q29) -> 0.077038095 | AO30: Dólares | AP30: Moneda Nacional
B31: Desviación estandar | C31: =IF(AND(WACC!$F$3>Tablas!$I$3,WACC!$F$3<=Tablas!$J$6), VLOOKUP(WACC!$C$13,'Damondaran Industries'!$A$1:$AE$95,6 + 6 * ROUNDDOWN((WACC!$F$3 - Tablas!$I$3) / (Tablas!$J$6 - Tablas!$I$3) * 3, 0), FALSE), VLOOKUP(WACC!$C$13,'Damondaran Industries'!$A$1:$AE$95,7,FALSE) ) -> 0.52722114 | Q31: =Q30*(1-F20) -> 0.054311857 | AN31: Costo de deuda (Kd) | AO31: =IF($I$7="",$I$8,$I$7) -> 0 | AP31: =(1+$AO$31)*(1+$J$7)-1 -> 0.0164
B32: Spread de la deuda | C32: =IF(AND(WACC!$F$3>Tablas!$I$3,WACC!$F$3<=Tablas!$J$6), VLOOKUP(WACC!$C$13,'Damondaran Industries'!$A$1:$AE$95,7 + 6 * ROUNDDOWN((WACC!$F$3 - Tablas!$I$3) / (Tablas!$J$6 - Tablas!$I$3) * 3, 0), FALSE), VLOOKUP(WACC!$C$13,'Damondaran Industries'!$A$1:$AE$95,7,FALSE) ) -> 0.02 | I32: DÓLARES | J32: Moneda Nacional | AN32: Costo de deuda despúes de impuestos (Kd(1-T)) | AO32: =AO31*(1-$AO$18) -> 0 | AP32: =$AP$31*(1-$I$20) -> 0.011562
A33: Kd = rf + Spread de la deuda | B33: Costo de deuda (Kd) | C33: =$C$10+C32 -> 0.0616 | E33: Costo de deuda (Kd) | F33: =$C$33+$F$9 -> 0.077038095 | H33: Costo de deuda (Kd) | I33: =ROUND(IF($J$3="DÓLARES",$I$8,$I$7),4) -> 0.0829 | J33: =ROUND((1+$I$33)*(1+$J$7)-1,4) -> 0.1007 | N33: Empresa
B34: Costo de deuda despúes de impuestos (Kd(1-T)) | C34: =$C$33*(1-$C$20) -> 0.03758216 | E34: Costo de deuda despúes de impuestos (Kd(1-T)) | F34: =$F$33*(1-$F$20) -> 0.054311857 | H34: Costo de deuda despúes de impuestos (Kd(1-T)) | I34: =ROUND(I33*(1-$I$20),4) -> 0.0584 | J34: =ROUND($J$33*(1-$I$20),4) -> 0.071 | O34: Ke | P34: Koa | Q34: Kd | AO34: Dólares | AP34: Moneda Nacional
N35: Rf | O35: =$O$25 -> 0.0416 | P35: =$O$25 -> 0.0416 | Q35: =$O$25 -> 0.0416 | AN35: Costo Promedio Ponderado de Capital (CPPC) | AO35: =$AO$22*$AO$16+$AO$32*$AO$15 -> 3.3246729 | AP35: =(1+$AO$35)*(1+$J$7)-1 -> 3.3955975
A36: VI. | B36: Determinación del CPPC | I36: Dólares | J36: Moneda Nacional | N36: Riesgo de negocio | O36: =I21*C9 -> 0.080320124
B37: Costo Promedio Ponderado de Capital (CPPC) | C37: =$C$24*$C$18+$C$34*$C$17 -> 0.07464442 | E37: Costo Promedio Ponderado de Capital (CPPC) | F37: =$F$24*$F$18+$F$34*$F$17 -> 0.090503457 | H37: Costo Promedio Ponderado de Capital (CPPC) | I37: =ROUND($I$24*$I$18+$I$34*$I$17,4) -> 0.091 | J37: =ROUND((1+$I$37)*(1+$J$7)-1,4) -> 0.1089 | N37: Riesgo económico de negocio | P37: =C27*C9 -> 0.037768475
N38: Spread de la deuda | Q38: =$C$32 -> 0.02 | AN38: CPPC | AO38: =IF('EE.FF Económicos'!$D$54="Soles",AP35,AO35) -> 3.3955975
A39: VII. | B39: Riesgos de negocio | N39: Riesgo país | O39: =$F$9 -> 0.015438095 | P39: =$F$9 -> 0.015438095 | Q39: =$F$9 -> 0.015438095
B40: Riesgo de negocio financiero (φf) | C40: =C24-C10 -> 0.04971834 | E40: Riesgo de negocio financiero (φf) | F40: =F24-C10-F9 -> 0.049747581 | H40: Riesgo de negocio financiero (φf) | I40: =ROUND(I24-C10-F9-I10,4) -> 0.0803 | N40: Prima empresa | O40: =$I$10 -> 0.0058619048 | P40: =$I$10 -> 0.0058619048 | Q40: =$I$10 -> 0.0058619048
B41: Riesgo de negocio económico (φe) | C41: =C28-C10 -> 0.037768475 | E41: Riesgo de negocio económico (φe) | F41: =F28-C10-F9 -> 0.037768475 | H41: Riesgo de negocio económico (φe) | I41: =ROUND(I28-C10-F9-I10,4) -> 0.0378 | O41: =SUM(O35:O40) -> 0.14322012 | P41: =SUM(P35:P40) -> 0.10066848 | Q41: =SUM(Q35:Q40) -> 0.0829
Q42: =Q41*(1-I20) -> 0.0584445
H44: CPPC | I44: =ROUND(IF('Plantilla Usuario'!C4="Soles",J37,I37),4) -> 0.091
AN45: WACC (Capitalización de Mercado) - Método integrado
N46: 3. Formación del CPPC
B47: Tabla3 | J47: Tabla7 | AN47: Porcentaje de deuda (%D) | AO47: =('EE.FF Económicos'!$H$17+'EE.FF Económicos'!$H$21)/('EE.FF Económicos'!$H$17+'EE.FF Económicos'!$H$21+'M. Integrado'!L39) -> -43.54309
AN48: Porcentaje de Capital (%C) | AO48: =1-AO47 -> 44.54309
B49: Columna1 | C49: Columna2 | D49: Columna3 | E49: Columna4 | F49: Columna5 | J49: Columna1 | K49: Columna2 | Q49: Mercado Desarrollado | Y49: Mercado Emergente | AH49: Empresa - Dólares | AQ49: Ratio D/C | AR49: =AO47/AO48 -> -0.97754983
C50: Mercado Desarrollado | D50: Mercado Emergente | E50: Empresa Dolares | F50: Empresa Soles | J50: Fecha | K50: =F3 -> 45838 | AQ50: Tasa de Impuesto (T) | AR50: =AO18 -> 0.295
B51: Ke | C51: =C24 -> 0.09131834 | D51: =F24 -> 0.10678568 | E51: =I24 -> 0.1432 | F51: =J24 -> 0.1619 | J51: Industria | K51: =C13 -> Publicidad | Q51: Var D/C | R51: =W55/5 -> 0.10372 | Y51: Var D/C | Z51: =AE55/5 -> 0.08997789 | AH51: Var D/C | AI51: =AN55/5 -> 0.31961548 | AQ51: Beta apalancado (Be) | AR51: =$C$27*(1+(1-$AR$50)*$AR$49) -> 0.1768536
B52: Koa | C52: =C28 -> 0.079368475 | D52: =F28 -> 0.094806571 | E52: =I28 -> 0.1007 | F52: =J28 -> 0.1188 | J52: Tasa libre | K52: =C3 -> Bono EE.UU
B53: Kd | C53: =C33 -> 0.0616 | D53: =F33 -> 0.077038095 | E53: =I33 -> 0.0829 | F53: =J33 -> 0.1007 | J53: Año del bono | K53: =C6 -> 1 | Q53: %D | R53: 0 | S53: =S55/(1+S55) -> 0.093973109 | T53: =T55/(1+T55) -> 0.1718015 | U53: =U55/(1+U55) -> 0.23731657 | V53: =V55/(1+V55) -> 0.29322628 | W53: =W55/(1+W55) -> 0.34149875 | Y53: %D | Z53: 0 | AA53: =AA55/(1+AA55) -> 0.082550197 | AB53: =AB55/(1+AB55) -> 0.15251061 | AC53: =AC55/(1+AC55) -> 0.2125573 | AD53: =AD55/(1+AD55) -> 0.26465806 | AE53: =AE55/(1+AE55) -> 0.31029224 | AH53: %D | AI53: 0 | AJ53: =AJ55/(1+AJ55) -> 0.2422035 | AK53: =AK55/(1+AK55) -> 0.38995784 | AL53: =AL55/(1+AL55) -> 0.48949546 | AM53: =AM55/(1+AM55) -> 0.56110744 | AN53: =AN55/(1+AN55) -> 0.6151 | AR53: Dólares | AS53: Moneda Nacional
B54: CPPC | C54: =C37 -> 0.07464442 | D54: =F37 -> 0.090503457 | E54: =I37 -> 0.091 | F54: =J37 -> 0.1089 | J54: Pais | K54: =F6 -> Peru | Q54: %C | R54: 1 | S54: =1-S53 -> 0.90602689 | T54: =1-T53 -> 0.8281985 | U54: =1-U53 -> 0.76268343 | V54: =1-V53 -> 0.70677372 | W54: =1-W53 -> 0.65850125 | Y54: %C | Z54: 1 | AA54: =1-AA53 -> 0.9174498 | AB54: =1-AB53 -> 0.84748939 | AC54: =1-AC53 -> 0.7874427 | AD54: =1-AD53 -> 0.73534194 | AE54: =1-AE53 -> 0.68970776 | AH54: %C | AI54: 1 | AJ54: =1-AJ53 -> 0.7577965 | AK54: =1-AK53 -> 0.61004216 | AL54: =1-AL53 -> 0.51050454 | AM54: =1-AM53 -> 0.43889256 | AN54: =1-AN53 -> 0.3849 | AQ54: Costo de Capital Financiero (Ke) | AR54: =$C$10+$AR$51*$C$9+$F$9+$I$10 -> 0.074639476 | AS54: =(1+$AR$54)*(1+$J$7)-1 -> 0.092263563
B55: Kd(1-T) | C55: =C34 -> 0.03758216 | D55: =F34 -> 0.054311857 | E55: =I34 -> 0.0584 | F55: =J34 -> 0.071 | J55: Devaluación | K55: =F7 -> 0.0164 | Q55: Ratio D/C | R55: =S55-$R$51 -> 2.7755576e-17 | S55: =T55-$R$51 -> 0.10372 | T55: =U55-$R$51 -> 0.20744 | U55: =V55-$R$51 -> 0.31116 | V55: =W55-$R$51 -> 0.41488 | W55: =C19 -> 0.5186 | Y55: Ratio D/C | Z55: =AA55-$Z$51 -> -2.7755576e-17 | AA55: =AB55-$Z$51 -> 0.08997789 | AB55: =AC55-$Z$51 -> 0.17995578 | AC55: =AD55-$Z$51 -> 0.26993367 | AD55: =AE55-$Z$51 -> 0.35991156 | AE55: =F19 -> 0.44988945 | AH55: Ratio D/C | AI55: =AJ55-$AI$51 -> 0 | AJ55: =AK55-$AI$51 -> 0.31961548 | AK55: =AL55-$AI$51 -> 0.63923097 | AL55: =AM55-$AI$51 -> 0.95884645 | AM55: =AN55-$AI$51 -> 1.2784619 | AN55: =I19 -> 1.5980774
J56: Tasa | K56: =F20 -> 0.295 | Q56: Be | R56: =$C$27*(1+(1-$I$20)*R$55) -> 0.56897692 | S56: =$C$27*(1+(1-$I$20)*S$55) -> 0.61058199 | T56: =$C$27*(1+(1-$I$20)*T$55) -> 0.65218706 | U56: =$C$27*(1+(1-$I$20)*U$55) -> 0.69379214 | V56: =$C$27*(1+(1-$I$20)*V$55) -> 0.73539721 | W56: =$C$27*(1+(1-$C$20)*W$55) -> 0.749 | Y56: Be | Z56: =$C$27*(1+(1-$F$20)*Z$55) -> 0.56897692 | AA56: =$C$27*(1+(1-$F$20)*AA$55) -> 0.60506964 | AB56: =$C$27*(1+(1-$F$20)*AB$55) -> 0.64116235 | AC56: =$C$27*(1+(1-$F$20)*AC$55) -> 0.67725507 | AD56: =$C$27*(1+(1-$F$20)*AD$55) -> 0.71334779 | AE56: =$C$27*(1+(1-$F$20)*AE$55) -> 0.7494405 | AH56: Be | AI56: =$C$27*(1+(1-$I$20)*AI$55) -> 0.56897692 | AJ56: =$C$27*(1+(1-$I$20)*AJ$55) -> 0.69718387 | AK56: =$C$27*(1+(1-$I$20)*AK$55) -> 0.82539083 | AL56: =$C$27*(1+(1-$I$20)*AL$55) -> 0.95359778 | AM56: =$C$27*(1+(1-$I$20)*AM$55) -> 1.0818047 | AN56: =$C$27*(1+(1-$I$20)*AN$55) -> 1.2100117
C57: Mercado Emergente | D57: Empresa | J57: Moneda | K57: =J3 -> Dólares | Q57: Ke | R57: =$C$10+R$56*$C$9 -> 0.079368475 | S57: =$C$10+S$56*$C$9 -> 0.082130205 | T57: =$C$10+T$56*$C$9 -> 0.084891934 | U57: =$C$10+U$56*$C$9 -> 0.087653663 | V57: =$C$10+V$56*$C$9 -> 0.090415392 | W57: =$C$10+W$56*$C$9 -> 0.09131834 | Y57: Ke | Z57: =$C$10+Z$56*$C$9+$F$9 -> 0.094806571 | AA57: =$C$10+AA$56*$C$9+$F$9 -> 0.097202392 | AB57: =$C$10+AB$56*$C$9+$F$9 -> 0.099598213 | AC57: =$C$10+AC$56*$C$9+$F$9 -> 0.10199403 | AD57: =$C$10+AD$56*$C$9+$F$9 -> 0.10438985 | AE57: =$C$10+AE$56*$C$9+$F$9 -> 0.10678568 | AH57: Ke | AI57: =$C$10+AI$56*$C$9+$F$9+$I$10 -> 0.10066848 | AJ57: =$C$10+AJ$56*$C$9+$F$9+$I$10 -> 0.10917881 | AK57: =$C$10+AK$56*$C$9+$F$9+$I$10 -> 0.11768913 | AL57: =$C$10+AL$56*$C$9+$F$9+$I$10 -> 0.12619946 | AM57: =$C$10+AM$56*$C$9+$F$9+$I$10 -> 0.13470979 | AN57: =$C$10+AN$56*$C$9+$F$9+$I$10 -> 0.14322012 | AR57: Dólares | AS57: Moneda Nacional
B58: D/C | C58: =F19 -> 0.44988945 | D58: =I19 -> 1.5980774 | J58: Deuda | K58: =I3 -> 0.0829 | Q58: Koa | R58: =$C$28 -> 0.079368475 | S58: =$C$28 -> 0.079368475 | T58: =$C$28 -> 0.079368475 | U58: =$C$28 -> 0.079368475 | V58: =$C$28 -> 0.079368475 | W58: =$C$28 -> 0.079368475 | Y58: Koa | Z58: =$C$28+$F$9 -> 0.094806571 | AA58: =$C$28+$F$9 -> 0.094806571 | AB58: =$C$28+$F$9 -> 0.094806571 | AC58: =$C$28+$F$9 -> 0.094806571 | AD58: =$C$28+$F$9 -> 0.094806571 | AE58: =$C$28+$F$9 -> 0.094806571 | AH58: Koa | AI58: =$F$28+$I$10 -> 0.10066848 | AJ58: =$F$28+$I$10 -> 0.10066848 | AK58: =$F$28+$I$10 -> 0.10066848 | AL58: =$F$28+$I$10 -> 0.10066848 | AM58: =$F$28+$I$10 -> 0.10066848 | AN58: =$F$28+$I$10 -> 0.10066848 | AQ58: Costo de Capital Económico (Koa) | AR58: =$F$28+$I$10 -> 0.10066848 | AS58: =(1+$AR$58)*(1+$J$7)-1 -> 0.11871944
B59: CPPC | D59: =I44 -> 0.091 | J59: Porcentaje deuda | K59: =I17 -> 0.6151 | Q59: Kd | R59: =$C$33 -> 0.0616 | S59: =$C$33 -> 0.0616 | T59: =$C$33 -> 0.0616 | U59: =$C$33 -> 0.0616 | V59: =$C$33 -> 0.0616 | W59: =$C$33 -> 0.0616 | Y59: Kd | Z59: =$F$33 -> 0.077038095 | AA59: =$F$33 -> 0.077038095 | AB59: =$F$33 -> 0.077038095 | AC59: =$F$33 -> 0.077038095 | AD59: =$F$33 -> 0.077038095 | AE59: =$F$33 -> 0.077038095 | AH59: Kd | AI59: =IF($I$7="",$I$8,$I$7) -> 0 | AJ59: =IF($I$7="",$I$8,$I$7) -> 0 | AK59: =IF($I$7="",$I$8,$I$7) -> 0 | AL59: =IF($I$7="",$I$8,$I$7) -> 0 | AM59: =IF($I$7="",$I$8,$I$7) -> 0 | AN59: =IF($I$7="",$I$8,$I$7) -> 0
J60: Porcentaje capital | K60: =I18 -> 0.3849 | Q60: Kd(1-t) | R60: =$C$34 -> 0.03758216 | S60: =$C$34 -> 0.03758216 | T60: =$C$34 -> 0.03758216 | U60: =$C$34 -> 0.03758216 | V60: =$C$34 -> 0.03758216 | W60: =$C$34 -> 0.03758216 | Y60: Kd(1-t) | Z60: =$F$34 -> 0.054311857 | AA60: =$F$34 -> 0.054311857 | AB60: =$F$34 -> 0.054311857 | AC60: =$F$34 -> 0.054311857 | AD60: =$F$34 -> 0.054311857 | AE60: =$F$34 -> 0.054311857 | AH60: Kd(1-t) | AI60: =$AI$59*(1-$I$20) -> 0 | AJ60: =$AI$59*(1-$I$20) -> 0 | AK60: =$AI$59*(1-$I$20) -> 0 | AL60: =$AI$59*(1-$I$20) -> 0 | AM60: =$AI$59*(1-$I$20) -> 0 | AN60: =$AI$59*(1-$I$20) -> 0
B61: Kd | C61: =I3 -> 0.0829 | J61: Acciones | K61: ='Plantilla Usuario'!C5 -> 847191.73 | Q61: WACC | R61: =R53*R60+R54*R57 -> 0.079368475 | S61: =S53*S60+S54*S57 -> 0.077943886 | T61: =T53*T60+T54*T57 -> 0.076764044 | U61: =U53*U60+U54*U57 -> 0.075770865 | V61: =V53*V60+V54*V57 -> 0.0749233 | W61: =W53*W60+W54*W57 -> 0.072967502 | Y61: WACC | Z61: =Z53*Z60+Z54*Z57 -> 0.094806571 | AA61: =AA53*AA60+AA54*AA57 -> 0.09366177 | AB61: =AB53*AB60+AB54*AB57 -> 0.092691563 | AC61: =AC53*AC60+AC54*AC57 -> 0.091858839 | AD61: =AD53*AD60+AD54*AD57 -> 0.091136309 | AE61: =AE53*AE60+AE54*AE57 -> 0.090503457 | AH61: WACC | AI61: =AI53*AI60+AI54*AI57 -> 0.10066848 | AJ61: =AJ53*AJ60+AJ54*AJ57 -> 0.082735317 | AK61: =AK53*AK60+AK54*AK57 -> 0.071795334 | AL61: =AL53*AL60+AL54*AL57 -> 0.064425399 | AM61: =AM53*AM60+AM54*AM57 -> 0.059123127 | AN61: =AN53*AN60+AN54*AN57 -> 0.055125426
B62: Moneda | C62: =J3 -> Dólares | AR62: Dólares | AS62: Moneda Nacional
AQ63: Costo de deuda (Kd) | AR63: =IF($I$7="",$I$8,$I$7) -> 0 | AS63: =(1+$AR$63)*(1+$J$7)-1 -> 0.0164
AQ64: Costo de deuda despúes de impuestos (Kd(1-T)) | AR64: =AR63*(1-$AR$50) -> 0 | AS64: =$AS$63*(1-$I$20) -> 0.011562
B65: Columna6 | C65: Columna1 | D65: Columna2 | E65: Columna3 | F65: Columna4 | G65: Columna5
C66: Parámetros del cálculo | AS66: Dólares | AT66: Moneda Nacional
B67: $$KMZGY$$ | C67: Prima de Mercado (Rm - Rf) | D67: =C9 -> 0.066379627 | AR67: Costo Promedio Ponderado de Capital (CPPC) | AS67: =$AR$54*$AO$48+$AR$64*$AO$47 -> 3.3246729 | AT67: =(1+$AS$67)*(1+$J$7)-1 -> 3.3955975
B68: $$KMZGZ$$ | C68: Tasa Libre de Riesgo (Rf) | D68: =C10 -> 0.0416
C69: Parámetros del sector
B70: $$KMZGX$$ | C70: Porcentaje de Deuda (%D) | D70: =+C17 -> 0.31029224 | AR70: CPPC | AS70: =IF('EE.FF Económicos'!$D$54="Soles",AT67,AS67) -> 3.3955975
B71: $$KMZGH$$ | C71: Porcentaje de Capital (%C) | D71: =1-D70 -> 0.68970776
C72: Impuestos del Sector (t) | D72: =+C20 -> 0.3899
B73: Columna3 | C73: Columna1 | D73: Columna2
C74: Parámetros del Costo de Capital Financiero | D74: =C16 -> 0
B75: $$ASD256$$ | C75: Beta Apalancado (Be) | D75: =C21 -> 0.749
B76: $$KYZA9$$ | C76: Costo de Capital Financiero (Ke) | D76: =+C24 -> 0.09131834
B77: Columna3 | C77: Columna1 | D77: Columna2
C78: Parámetros del Costo de Capital Económico | D78: =C20 -> 0.3899
B79: $$7TZYU$$ | C79: Beta Desapalancado (Boa) | D79: =C27 -> 0.56897692
B80: $$7TZYV$$ | C80: Costo de Capital Económico (Koa) | D80: =C28 -> 0.079368475
B81: Columna3 | C81: Columna1 | D81: Columna2
C82: Parámetros del Costo de Deuda | D82: =C24 -> 0.09131834
B83: $$FGBGB$$ | C83: Spread de la Deuda | D83: =C32 -> 0.02
B84: $$FGBGC$$ | C84: Impuestos del Sector (t) | D84: =C20 -> 0.3899
B85: $$FGBGD$$ | C85: Costo de Deuda (Kd) | D85: =C33 -> 0.0616
B86: $$FGBGE$$ | C86: Costo de Deuda Después de Impuestos Kd(1-t) | D86: =C34 -> 0.03758216
B87: Columna3 | C87: Columna1 | D87: Columna2
C88: Parámetros del CPPC | D88: =C30
B89: $$WPBYC$$ | C89: Porcentaje de Deuda (%D) | D89: =C17 -> 0.31029224
B90: $$WPBYD$$ | C90: Porcentaje de Capital (%C) | D90: =C18 -> 0.68970776
B91: $$WPBYE$$ | C91: Costo de Capital Financiero (Ke) | D91: =C24 -> 0.09131834
B92: $$WPBYF$$ | C92: Costo de Deuda Después de Impuestos Kd(1-t) | D92: =C34 -> 0.03758216
B93: $$WPBYG$$ | C93: Costo Promedio Ponderado de Capital (CPPC) | D93: =C37 -> 0.07464442
B94: Columna3 | C94: Columna1 | D94: Columna2 | O94: 4. Estructura de Capital
C95: Parámetros del País Seleccionado | D95: =C37 -> 0.07464442
B96: $$NPQ3H$$ | C96: País | D96: =F6 -> Peru | P96: M. Desarrollado | Q96: M. Emergente | R96: Empresa
B97: $$HG8KI$$ | C97: Devaluación Esperada | D97: =F7 -> 0.0164 | O97: %D | P97: =$C$17 -> 0.31029224 | Q97: =$F$17 -> 0.31029224 | R97: =$I$17 -> 0.6151
B98: $$HG8KJ$$ | C98: Riesgo País | D98: =F9 -> 0.015438095 | O98: %C | P98: =1-P97 -> 0.68970776 | Q98: =1-Q97 -> 0.68970776 | R98: =1-R97 -> 0.3849
B99: $$HG8KK$$ | C99: Tasa Impositiva | D99: =F20 -> 0.295 | O99: *MD: Mercado Desarrollado
C100: Columna1 | D100: Columna2
C101: Parámetros de la Estructura del Financiamiento | D101: =C43 -> 0 | O101: **ME: Mercado Emergente
B102: $$GH7RV$$ | C102: Porcentaje de Deuda (%D) | D102: =F17 -> 0.31029224
B103: $$GH7RU$$ | C103: Porcentaje de Capital (%C) | D103: =F18 -> 0.68970776
B104: Columna3 | C104: Columna1 | D104: Columna2
...

Sheet Damondaran Industries
B1: 2021 | C1: 2021 | D1: 2021 | E1: 2021 | F1: 2021 | G1: 2021 | H1: 2022 | I1: 2022 | J1: 2022 | K1: 2022 | L1: 2022 | M1: 2022 | N1: 2023 | O1: 2023 | P1: 2023 | Q1: 2023 | R1: 2023 | S1: 2023 | T1: 2024 | U1: 2024 | V1: 2024 | W1: 2024 | X1: 2024 | Y1: 2024 | Z1: 2025 | AA1: 2025 | AB1: 2025 | AC1: 2025 | AD1: 2025 | AE1: 2025
A2: Industry Name | B2: D/(D+E) | C2: E/(D+E) | D2: Tax rate2 | E2: Beta | F2: Std Dev in Stock | G2: Spread Debt | H2: D/(D+E) | I2: E/(D+E) | J2: Tax rate2 | K2: Beta | L2: Std Dev in Stock | M2: Spread debt | N2: D/(D+E) | O2: E/(D+E) | P2: Tax rate2 | Q2: Beta | R2: Std Dev in Stock | S2: Spread Debt | T2: D/(D+E) | U2: E/(D+E) | V2: Tax rate2 | W2: Beta | X2: Std Dev in Stock | Y2: Spread Debt | Z2: D/(D+E) | AA2: E/(D+E) | AB2: Tax rate2 | AC2: Beta | AD2: Std Dev in Stock | AE2: Spread Debt
A3: Publicidad | B3: 0.33979075 | C3: 0.66020925 | D3: 0.27 | E3: 1.3404215 | F3: 0.56696815 | G3: 0.02068 | H3: 0.33979075 | I3: 0.66020925 | J3: 0.27 | K3: 1.3404215 | L3: 0.56696815 | M3: 0.02068 | N3: 0.31029224 | O3: 0.68970776 | P3: 0.25 | Q3: 1.6317381 | R3: 0.52722114 | S3: 0.02 | T3: 0.25241808 | U3: 0.74758192 | V3: 0.25 | W3: 1.3723256 | X3: 0.56414425 | Y3: 0.014724 | Z3: 0.20758669 | AA3: 0.79241331 | AB3: 0.25 | AC3: 1.3372941 | AD3: 0.67185667 | AE3: 0.0183
A4: Aeroespacial/ Defensa | B4: 0.2275095 | C4: 0.7724905 | D4: 0.27 | E4: 1.2810484 | F4: 0.38232192 | G4: 0.0165 | H4: 0.2275095 | I4: 0.7724905 | J4: 0.27 | K4: 1.2810484 | L4: 0.38232192 | M4: 0.0165 | N4: 0.20670884 | O4: 0.79329116 | P4: 0.25 | Q4: 1.4141823 | R4: 0.37555545 | S4: 0.0162 | T4: 0.20291778 | U4: 0.79708222 | V4: 0.25 | W4: 1.076405 | X4: 0.3640215 | Y4: 0.012055 | Z4: 0.18562455 | AA4: 0.81437545 | AB4: 0.25 | AC4: 0.90155313 | AD4: 0.42742401 | AE4: 0.0095
A5: Transporte aéreo | B5: 0.60525992 | C5: 0.39474008 | D5: 0.27 | E5: 1.5829076 | F5: 0.40193094 | G5: 0.02068 | H5: 0.60525992 | I5: 0.39474008 | J5: 0.27 | K5: 1.5829076 | L5: 0.40193094 | M5: 0.02068 | N5: 0.65075796 | O5: 0.34924204 | P5: 0.25 | Q5: 1.4159651 | R5: 0.37727499 | S5: 0.0162 | T5: 0.61854039 | U5: 0.38145961 | V5: 0.25 | W5: 1.2668402 | X5: 0.44650999 | Y5: 0.012055 | Z5: 0.51650226 | AA5: 0.48349774 | AB5: 0.25 | AC5: 1.2360067 | AD5: 0.65271639 | AE5: 0.0183
A6: Confección de ropa | B6: 0.24009984 | C6: 0.75990016 | D6: 0.27 | E6: 1.2265826 | F6: 0.43487047 | G6: 0.02068 | H6: 0.24009984 | I6: 0.75990016 | J6: 0.27 | K6: 1.2265826 | L6: 0.43487047 | M6: 0.02068 | N6: 0.34024907 | O6: 0.65975093 | P6: 0.25 | Q6: 1.3246974 | R6: 0.38508747 | S6: 0.0162 | T6: 0.3277875 | U6: 0.6722125 | V6: 0.25 | W6: 1.1946999 | X6: 0.3703551 | Y6: 0.012055 | Z6: 0.3145444 | AA6: 0.6854556 | AB6: 0.25 | AC6: 0.99056805 | AD6: 0.50926388 | AE6: 0.012
A7: Automóviles y Camiones | B7: 0.16570496 | C7: 0.83429504 | D7: 0.27 | E7: 1.1293063 | F7: 0.5477688 | G7: 0.02068 | H7: 0.16570496 | I7: 0.83429504 | J7: 0.27 | K7: 1.1293063 | L7: 0.5477688 | M7: 0.02068 | N7: 0.33418107 | O7: 0.66581893 | P7: 0.25 | Q7: 1.5405977 | R7: 0.52614125 | S7: 0.02 | T7: 0.23675434 | U7: 0.76324566 | V7: 0.25 | W7: 1.5223779 | X7: 0.59698514 | Y7: 0.014724 | Z7: 0.18297971 | AA7: 0.81702029 | AB7: 0.25 | AC7: 1.6154126 | AD7: 0.77591112 | AE7: 0.0183
A8: Partes de Automóviles | B8: 0.24056373 | C8: 0.75943627 | D8: 0.27 | E8: 1.3980689 | F8: 0.3714042 | G8: 0.02068 | H8: 0.24056373 | I8: 0.75943627 | J8: 0.27 | K8: 1.3980689 | L8: 0.3714042 | M8: 0.0165 | N8: 0.29901008 | O8: 0.70098992 | P8: 0.25 | Q8: 1.4739918 | R8: 0.39519395 | S8: 0.0162 | T8: 0.27766272 | U8: 0.72233728 | V8: 0.25 | W8: 1.3444266 | X8: 0.37071964 | Y8: 0.012055 | Z8: 0.32356185 | AA8: 0.67643815 | AB8: 0.25 | AC8: 1.2251238 | AD8: 0.52623749 | AE8: 0.012
A9: Bebida alcohólicas | B9: 0.1763857 | C9: 0.8236143 | D9: 0.27 | E9: 0.81936465 | F9: 0.37865996 | G9: 0.0165 | H9: 0.1763857 | I9: 0.8236143 | J9: 0.27 | K9: 0.81936465 | L9: 0.37865996 | M9: 0.0165 | N9: 0.18639448 | O9: 0.81360552 | P9: 0.25 | Q9: 1.0129742 | R9: 0.49874676 | S9: 0.0162 | T9: 0.19656022 | U9: 0.80343978 | V9: 0.25 | W9: 1.1318349 | X9: 0.4970414 | Y9: 0.012055 | Z9: 0.23351097 | AA9: 0.76648903 | AB9: 0.25 | AC9: 0.61029786 | AD9: 0.63076376 | AE9: 0.012
A10: Bebidas sin alcohol | B10: 0.14271344 | C10: 0.85728656 | D10: 0.27 | E10: 1.2156865 | F10: 0.48265389 | G10: 0.02068 | H10: 0.14271344 | I10: 0.85728656 | J10: 0.27 | K10: 1.2156865 | L10: 0.48265389 | M10: 0.02068 | N10: 0.1324644 | O10: 0.8675356 | P10: 0.25 | Q10: 1.3034433 | R10: 0.41717147 | S10: 0.0162 | T10: 0.14615788 | U10: 0.85384212 | V10: 0.25 | W10: 0.76414588 | X10: 0.42961071 | Y10: 0.012055 | Z10: 0.16479515 | AA10: 0.83520485 | AB10: 0.25 | AC10: 0.5677661 | AD10: 0.47670268 | AE10: 0.012
A11: Radiofusión | B11: 0.53879276 | C11: 0.46120724 | D11: 0.27 | E11: 1.3520953 | F11: 0.4876941 | G11: 0.02068 | H11: 0.53879276 | I11: 0.46120724 | J11: 0.27 | K11: 1.3520953 | L11: 0.4876941 | M11: 0.02068 | N11: 0.59486627 | O11: 0.40513373 | P11: 0.25 | Q11: 1.3220586 | R11: 0.46898415 | S11: 0.0162 | T11: 0.63820799 | U11: 0.36179201 | V11: 0.25 | W11: 1.0609244 | X11: 0.38457134 | Y11: 0.012055 | Z11: 0.59929947 | AA11: 0.40070053 | AB11: 0.25 | AC11: 0.91752363 | AD11: 0.52595168 | AE11: 0.012
A12: Corretaje e inversión bancaria | B12: 0.64599682 | C12: 0.35400318 | D12: 0.27 | E12: 1.1749813 | F12: 0.31739361 | G12: 0.0165 | H12: 0.64599682 | I12: 0.35400318 | J12: 0.27 | K12: 1.1749813 | L12: 0.31739361 | M12: 0.0165 | N12: 0.66787154 | O12: 0.33212846 | P12: 0.25 | Q12: 1.2048083 | R12: 0.27996249 | S12: 0.0162 | T12: 0.69330766 | U12: 0.30669234 | V12: 0.25 | W12: 1.1203262 | X12: 0.25213732 | Y12: 0.012055 | Z12: 0.65106515 | AA12: 0.34893485 | AB12: 0.25 | AC12: 0.9522674 | AD12: 0.40490891 | AE12: 0.0095
A13: Materiales de construcción | B13: 0.15787202 | C13: 0.84212798 | D13: 0.27 | E13: 1.1871343 | F13: 0.34535009 | G13: 0.0165 | H13: 0.15787202 | I13: 0.84212798 | J13: 0.27 | K13: 1.1871343 | L13: 0.34535009 | M13: 0.0165 | N13: 0.22436252 | O13: 0.77563748 | P13: 0.25 | Q13: 1.2772801 | R13: 0.29189914 | S13: 0.0162 | T13: 0.15361123 | U13: 0.84638877 | V13: 0.25 | W13: 1.3177985 | X13: 0.2871588 | Y13: 0.012055 | Z13: 0.15947308 | AA13: 0.84052692 | AB13: 0.25 | AC13: 1.3598827 | AD13: 0.34747493 | AE13: 0.0095
A14: Servicios para empresas y consumidores | B14: 0.18294499 | C14: 0.81705501 | D14: 0.27 | E14: 1.0891943 | F14: 0.41173437 | G14: 0.02068 | H14: 0.18294499 | I14: 0.81705501 | J14: 0.27 | K14: 1.0891943 | L14: 0.41173437 | M14: 0.02068 | N14: 0.21552516 | O14: 0.78447484 | P14: 0.25 | Q14: 1.17092 | R14: 0.45782494 | S14: 0.0162 | T14: 0.15210607 | U14: 0.84789393 | V14: 0.25 | W14: 1.0221017 | X14: 0.41290055 | Y14: 0.012055 | Z14: 0.14369516 | AA14: 0.85630484 | AB14: 0.25 | AC14: 1.00385 | AD14: 0.45393206 | AE14: 0.012
... A95: Mercado Total (sin el sector financiero) | B95: 0.16662687 | C95: 0.83337313 | D95: 0.27 | E95: 1.1485779 | F95: 0.44991556 | G95: 0.02068 | H95: 0.16662687 | I95: 0.83337313 | J95: 0.27 | K95: 1.1485779 | L95: 0.44991556 | M95: 0.02068 | N95: 0.20885367 | O95: 0.79114633 | P95: 0.25 | Q95: 1.292817 | R95: 0.47976813 | S95: 0.0162 | T95: 0.18433859 | U95: 0.81566141 | V95: 0.25 | W95: 1.0975226 | X95: 0.4700346 | Y95: 0.012055 | Z95: 0.16170905 | AA95: 0.83829095 | AB95: 0.25 | AC95: 1.0857817 | AD95: 0.57396285 | AE95: 0.012
B130: Cost of Debt Lookup Table (based on std dev in stock prices) | I130: Cost of Debt Lookup Table (based on std dev in stock prices) | P130: Cost of Debt Lookup Table (based on std dev in stock prices) | W130: Cost of Debt Lookup Table (based on std dev in stock prices) | AD130: Cost of Debt Lookup Table (based on std dev in stock prices)
A131: 2021 | B131: Standard Deviation | D131: Basis Spread | H131: 2022 | I131: Standard Deviation | K131: Basis Spread | O131: 2023 | P131: Standard Deviation | R131: Basis Spread | V131: 2024 | W131: Standard Deviation | Z131: Basis Spread | AC131: 2025 | AD131: Standard Deviation | AF131: Basis Spread
B132: 0 | C132: 0.25 | D132: 0.0099 | I132: 0 | J132: 0.25 | K132: 0.0099 | P132: 0 | Q132: 0.25 | R132: 0.0085 | W132: 0 | X132: 0.25 | Z132: 0.006243 | AD132: 0 | AF132: 0.005
B133: 0.25 | C133: 0.4 | D133: 0.0165 | I133: 0.25 | J133: 0.4 | K133: 0.0165 | P133: 0.250001 | Q133: 0.5 | R133: 0.0162 | W133: 0.250001 | X133: 0.5 | Z133: 0.012055 | AD133: 0.30001 | AF133: 0.0095
A134: Yes | B134: 0.4 | C134: 0.65 | D134: 0.02068 | H134: Yes | I134: 0.4 | J134: 0.65 | K134: 0.02068 | O134: Yes | P134: 0.500001 | Q134: 0.65 | R134: 0.02 | V134: Yes | W134: 0.500001 | X134: 0.65 | Z134: 0.014724 | AC134: Yes | AD134: 0.45001 | AF134: 0.012
A135: 0.27 | B135: 0.65 | C135: 0.75 | D135: 0.031625 | H135: 0.27 | I135: 0.65 | J135: 0.75 | K135: 0.031625 | O135: 0.25 | P135: 0.650001 | Q135: 0.8 | R135: 0.0313 | V135: 0.25 | W135: 0.650001 | X135: 0.8 | Z135: 0.022079 | AC135: 0.25 | AD135: 0.650001 | AF135: 0.0183
B136: 0.75 | C136: 0.9 | D136: 0.066125 | I136: 0.75 | J136: 0.9 | K136: 0.066125 | P136: 0.800001 | Q136: 0.9 | R136: 0.0526 | W136: 0.800001 | X136: 0.9 | Z136: 0.036056 | AD136: 0.800001 | AF136: 0.03
B137: 0.9 | C137: 1 | D137: 0.083375 | I137: 0.9 | J137: 1 | K137: 0.083375 | P137: 0.900001 | Q137: 1 | R137: 0.0737 | W137: 0.900001 | X137: 1 | Z137: 0.052404 | AD137: 0.900001 | AF137: 0.0442
B138: 1 | C138: 10 | D138: 0.100625 | I138: 1 | J138: 10 | K138: 0.100625 | P138: 1.000001 | Q138: 10 | R138: 0.1157 | W138: 1.000001 | X138: 10 | Z138: 0.0851 | AD138: 1.000001 | AF138: 0.0728

Sheet M. por conceptos
B2: MÉTODO POR CONCEPTOS
B4: 1. Proyección de cuentas
D6: =+AVERAGE(C9:D9) -> 7618983.5
B7: Ingresos | C7: =IFERROR('EE.FF Económicos'!D2,"") -> 2017 | D7: =IFERROR('EE.FF Económicos'!E2,"") -> 2018 | E7: =IFERROR('EE.FF Económicos'!F2,"") -> 2019 | F7: =IFERROR('EE.FF Económicos'!G2,"") -> 2020 | G7: =IFERROR('EE.FF Económicos'!H2,"") -> 2021 | H7: =G7+1 -> 2022 | I7: =H7+1 -> 2023 | J7: =I7+1 -> 2024 | K7: =J7+1 -> 2025 | L7: =K7+1 -> 2026 | M7: =L7+1 -> 2027 | N7: =M7+1 -> 2028 | O7: =N7+1 -> 2029 | ... V7: =U7+1 -> 2036
C8: =IFERROR('EE.FF Económicos'!D3,"") -> 1 | D8: =IFERROR('EE.FF Económicos'!E3,"") -> 2 | E8: =IFERROR('EE.FF Económicos'!F3,"") -> 3 | F8: =IFERROR('EE.FF Económicos'!G3,"") -> 4 | G8: =IFERROR('EE.FF Económicos'!H3,"") -> 5 | H8: =G8+1 -> 6 | I8: =H8+1 -> 7 | J8: =I8+1 -> 8 | K8: =J8+1 -> 9 | L8: =K8+1 -> 10 | M8: =L8+1 -> 11 | N8: =M8+1 -> 12 | O8: =N8+1 -> 13 | ... V8: =U8+1 -> 20
B9: Histórico | C9: =IF('EE.FF Económicos'!D35=0,"",'EE.FF Económicos'!D35) -> 6949265 | D9: =IF('EE.FF Económicos'!E35=0,"",'EE.FF Económicos'!E35) -> 8288702 | E9: =IF('EE.FF Económicos'!F35=0,"",'EE.FF Económicos'!F35) -> 9872187 | F9: =IF('EE.FF Económicos'!G35=0,"",'EE.FF Económicos'!G35) -> 10131767 | G9: =IF('EE.FF Económicos'!H35=0,"",'EE.FF Económicos'!H35) -> 12227663
B10: Promedio Móvil | D10: =IF(C9="","",AVERAGE(C9:D9)) -> 7618983.5 | E10: =IF(D9="","",AVERAGE(D9:E9)) -> 9080444.5 | F10: =IF(E9="","",AVERAGE(E9:F9)) -> 10001977 | G10: =IF(F9="","",AVERAGE(F9:G9)) -> 11179715
B11: Tendencia Logarítmica | G11: =LN(F8)*$E$16+$F$21 -> #REF! | H11: =LN(G8)*$E$16+$F$21 -> #REF! | I11: =LN(H8)*$E$16+$F$21 -> #REF! | J11: =LN(I8)*$E$16+$F$21 -> #REF! | K11: =LN(J8)*$E$16+$F$21 -> #REF! | L11: =LN(K8)*$E$16+$F$21 -> #REF! | M11: =LN(L8)*$E$16+$F$21 -> #REF! | N11: =LN(M8)*$E$16+$F$21 -> #REF! | ... V11: =LN(U8)*$E$16+$F$21 -> #REF!
B12: Tasa de crecimiento | H12: =IF(H11/G11-1>'EE.FF Económicos'!$D$53,H11/G11-1,'EE.FF Económicos'!$D$53) -> 0.015 | I12: =IF(I11/H11-1>'EE.FF Económicos'!$D$53,I11/H11-1,'EE.FF Económicos'!$D$53) -> 0.015 | J12: =IF(J11/I11-1>'EE.FF Económicos'!$D$53,J11/I11-1,'EE.FF Económicos'!$D$53) -> 0.015 | K12: =IF(K11/J11-1>'EE.FF Económicos'!$D$53,K11/J11-1,'EE.FF Económicos'!$D$53) -> 0.015 | L12: =IF(L11/K11-1>'EE.FF Económicos'!$D$53,L11/K11-1,'EE.FF Económicos'!$D$53) -> 0.015 | M12: =IF(M11/L11-1>'EE.FF Económicos'!$D$53,M11/L11-1,'EE.FF Económicos'!$D$53) -> 0.015 | N12: =IF(N11/M11-1>'EE.FF Económicos'!$D$53,N11/M11-1,'EE.FF Económicos'!$D$53) -> 0.015 | O12: =IF(O11/N11-1>'EE.FF Económicos'!$D$53,O11/N11-1,'EE.FF Económicos'!$D$53) -> 0.015 | ... V12: =IF(V11/U11-1>'EE.FF Económicos'!$D$53,V11/U11-1,'EE.FF Económicos'!$D$53) -> 0.015
B13: Proyección final | C13: =C9 -> 6949265 | D13: =D9 -> 8288702 | E13: =E9 -> 9872187 | F13: =F9 -> 10131767 | G13: =G9 -> 12227663 | H13: =G11*(1+H12) -> #REF! | I13: =H13*(1+I12) -> #REF! | J13: =I13*(1+J12) -> #REF! | K13: =J13*(1+K12) -> #REF! | L13: =K13*(1+L12) -> #REF! | M13: =L13*(1+M12) -> #REF! | N13: =M13*(1+N12) -> #REF! | O13: =N13*(1+O12) -> #REF! | P13: =O13*(1+P12) -> #REF! | ... V13: =U13*(1+V12) -> #REF!
E15: Pendiente | F15: Constante
E16: =INDEX(LINEST(INDEX(C10:G10,COUNTBLANK(C10:G10)+1):G10,LN(INDEX(C8:G8,COUNTBLANK(C10:G10)):INDEX(C8:G8,4)),TRUE,),1) -> #REF! | F16: =INDEX(LINEST(INDEX(C10:G10,COUNTBLANK(C10:G10)+1):G10,LN(INDEX(C8:G8,COUNTBLANK(C10:G10)):INDEX(C8:G8,4)),TRUE,),2) -> #REF!
E18: Ajuste de la constante
E19: Valor real | F19: =G10 -> 11179715
E20: Valor est. | F20: =LN(F8)*E16+F16 -> #REF!
E21: Const. Aj. | F21: =F19-F20+F16 -> #REF!
B24: Costo de ventas | C24: =C$7 -> 2017 | D24: =D$7 -> 2018 | E24: =E$7 -> 2019 | F24: =F$7 -> 2020 | G24: =G$7 -> 2021 | H24: =G24+1 -> 2022 | I24: =H24+1 -> 2023 | J24: =I24+1 -> 2024 | K24: =J24+1 -> 2025 | L24: =K24+1 -> 2026 | M24: =L24+1 -> 2027 | N24: =M24+1 -> 2028 | O24: =N24+1 -> 2029 | ... V24: =U24+1 -> 2036
C25: =C$8 -> 1 | D25: =D$8 -> 2 | E25: =E$8 -> 3 | F25: =F$8 -> 4 | G25: =G$8 -> 5 | H25: =G25+1 -> 6 | I25: =H25+1 -> 7 | J25: =I25+1 -> 8 | K25: =J25+1 -> 9 | L25: =K25+1 -> 10 | M25: =L25+1 -> 11 | N25: =M25+1 -> 12 | O25: =N25+1 -> 13 | ... V25: =U25+1 -> 20
B26: Histórico | C26: =IF('EE.FF Económicos'!D36=0,"",-'EE.FF Económicos'!D36) -> 5042402 | D26: =IF('EE.FF Económicos'!E36=0,"",-'EE.FF Económicos'!E36) -> 6244012 | E26: =IF('EE.FF Económicos'!F36=0,"",-'EE.FF Económicos'!F36) -> 7420013 | F26: =IF('EE.FF Económicos'!G36=0,"",-'EE.FF Económicos'!G36) -> 7712254 | G26: =IF('EE.FF Económicos'!H36=0,"",-'EE.FF Económicos'!H36) -> 9831454
B27: Promedio Móvil | D27: =IF(C26="","",AVERAGE(C26:D26)) -> 5643207 | E27: =IF(D26="","",AVERAGE(D26:E26)) -> 6832012.5 | F27: =IF(E26="","",AVERAGE(E26:F26)) -> 7566133.5 | G27: =IF(F26="","",AVERAGE(F26:G26)) -> 8771854
B28: Tendencia Logarítmica | G28: =LN(F25)*$E$33+$F$38 -> #REF! | H28: =LN(G25)*$E$33+$F$38 -> #REF! | I28: =LN(H25)*$E$33+$F$38 -> #REF! | J28: =LN(I25)*$E$33+$F$38 -> #REF! | K28: =LN(J25)*$E$33+$F$38 -> #REF! | L28: =LN(K25)*$E$33+$F$38 -> #REF! | M28: =LN(L25)*$E$33+$F$38 -> #REF! | N28: =LN(M25)*$E$33+$F$38 -> #REF! | ... V28: =LN(U25)*$E$33+$F$38 -> #REF!
B29: Tasa de crecimiento | H29: =IF(H$12>'EE.FF Económicos'!$D$53,H28/G28-1,'EE.FF Económicos'!$D$53) -> 0.015 | I29: =IF(I$12>'EE.FF Económicos'!$D$53,I28/H28-1,'EE.FF Económicos'!$D$53) -> 0.015 | J29: =IF(J$12>'EE.FF Económicos'!$D$53,J28/I28-1,'EE.FF Económicos'!$D$53) -> 0.015 | K29: =IF(K$12>'EE.FF Económicos'!$D$53,K28/J28-1,'EE.FF Económicos'!$D$53) -> 0.015 | L29: =IF(L$12>'EE.FF Económicos'!$D$53,L28/K28-1,'EE.FF Económicos'!$D$53) -> 0.015 | M29: =IF(M$12>'EE.FF Económicos'!$D$53,M28/L28-1,'EE.FF Económicos'!$D$53) -> 0.015 | N29: =IF(N$12>'EE.FF Económicos'!$D$53,N28/M28-1,'EE.FF Económicos'!$D$53) -> 0.015 | O29: =IF(O$12>'EE.FF Económicos'!$D$53,O28/N28-1,'EE.FF Económicos'!$D$53) -> 0.015 | ... V29: =IF(V$12>'EE.FF Económicos'!$D$53,V28/U28-1,'EE.FF Económicos'!$D$53) -> 0.015
B30: Proyección final | C30: =C26 -> 5042402 | D30: =D26 -> 6244012 | E30: =E26 -> 7420013 | F30: =F26 -> 7712254 | G30: =G26 -> 9831454 | H30: =G28*(1+H29) -> #REF! | I30: =H30*(1+I29) -> #REF! | J30: =I30*(1+J29) -> #REF! | K30: =J30*(1+K29) -> #REF! | L30: =K30*(1+L29) -> #REF! | M30: =L30*(1+M29) -> #REF! | N30: =M30*(1+N29) -> #REF! | O30: =N30*(1+O29) -> #REF! | P30: =O30*(1+P29) -> #REF! | ... V30: =U30*(1+V29) -> #REF!
E32: Pendiente | F32: Constante
E33: =INDEX(LINEST(INDEX(C27:G27,COUNTBLANK(C27:G27)+1):G27,LN(INDEX(C25:G25,COUNTBLANK(C27:G27)):INDEX(C25:G25,4)),TRUE,),1) -> #REF! | F33: =INDEX(LINEST(INDEX(C27:G27,COUNTBLANK(C27:G27)+1):G27,LN(INDEX(C25:G25,COUNTBLANK(C27:G27)):INDEX(C25:G25,4)),TRUE,),2) -> #REF!
E35: Ajuste de la constante
E36: Valor real | F36: =G27 -> 8771854
E37: Valor est. | F37: =LN(F25)*E33+F33 -> #REF!
E38: Const. Aj. | F38: =F36-F37+F33 -> #REF!
B42: Gasto de ventas | C42: =C$7 -> 2017 | D42: =D$7 -> 2018 | E42: =E$7 -> 2019 | F42: =F$7 -> 2020 | G42: =G$7 -> 2021 | H42: =G42+1 -> 2022 | I42: =H42+1 -> 2023 | J42: =I42+1 -> 2024 | K42: =J42+1 -> 2025 | L42: =K42+1 -> 2026 | M42: =L42+1 -> 2027 | N42: =M42+1 -> 2028 | O42: =N42+1 -> 2029 | ... V42: =U42+1 -> 2036
C43: =C$8 -> 1 | D43: =D$8 -> 2 | E43: =E$8 -> 3 | F43: =F$8 -> 4 | G43: =G$8 -> 5 | H43: =G43+1 -> 6 | I43: =H43+1 -> 7 | J43: =I43+1 -> 8 | K43: =J43+1 -> 9 | L43: =K43+1 -> 10 | M43: =L43+1 -> 11 | N43: =M43+1 -> 12 | O43: =N43+1 -> 13 | ... V43: =U43+1 -> 20
B44: Histórico | C44: =IF('EE.FF Económicos'!D38=0,"",-'EE.FF Económicos'!D38) -> 633605 | D44: =IF('EE.FF Económicos'!E38=0,"",-'EE.FF Económicos'!E38) -> 681336 | E44: =IF('EE.FF Económicos'!F38=0,"",-'EE.FF Económicos'!F38) -> 801905 | F44: =IF('EE.FF Económicos'!G38=0,"",-'EE.FF Económicos'!G38) -> 862157 | G44: =IF('EE.FF Económicos'!H38=0,"",-'EE.FF Económicos'!H38) -> 786246
B45: Promedio Móvil | D45: =IF(C44="","",AVERAGE(C44:D44)) -> 657470.5 | E45: =IF(D44="","",AVERAGE(D44:E44)) -> 741620.5 | F45: =IF(E44="","",AVERAGE(E44:F44)) -> 832031 | G45: =IF(F44="","",AVERAGE(F44:G44)) -> 824201.5
B46: Tendencia Logarítmica | G46: =LN(F43)*$E$51+$F$56 -> #REF! | H46: =LN(G43)*$E$51+$F$56 -> #REF! | I46: =LN(H43)*$E$51+$F$56 -> #REF! | J46: =LN(I43)*$E$51+$F$56 -> #REF! | K46: =LN(J43)*$E$51+$F$56 -> #REF! | L46: =LN(K43)*$E$51+$F$56 -> #REF! | M46: =LN(L43)*$E$51+$F$56 -> #REF! | N46: =LN(M43)*$E$51+$F$56 -> #REF! | ... V46: =LN(U43)*$E$51+$F$56 -> #REF!
B47: Tasa de crecimiento | H47: =IF(H$12>'EE.FF Económicos'!$D$53,H46/G46-1,'EE.FF Económicos'!$D$53) -> 0.015 | I47: =IF(I$12>'EE.FF Económicos'!$D$53,I46/H46-1,'EE.FF Económicos'!$D$53) -> 0.015 | J47: =IF(J$12>'EE.FF Económicos'!$D$53,J46/I46-1,'EE.FF Económicos'!$D$53) -> 0.015 | K47: =IF(K$12>'EE.FF Económicos'!$D$53,K46/J46-1,'EE.FF Económicos'!$D$53) -> 0.015 | L47: =IF(L$12>'EE.FF Económicos'!$D$53,L46/K46-1,'EE.FF Económicos'!$D$53) -> 0.015 | M47: =IF(M$12>'EE.FF Económicos'!$D$53,M46/L46-1,'EE.FF Económicos'!$D$53) -> 0.015 | N47: =IF(N$12>'EE.FF Económicos'!$D$53,N46/M46-1,'EE.FF Económicos'!$D$53) -> 0.015 | O47: =IF(O$12>'EE.FF Económicos'!$D$53,O46/N46-1,'EE.FF Económicos'!$D$53) -> 0.015 | ... V47: =IF(V$12>'EE.FF Económicos'!$D$53,V46/U46-1,'EE.FF Económicos'!$D$53) -> 0.015
B48: Proyección final | C48: =C44 -> 633605 | D48: =D44 -> 681336 | E48: =E44 -> 801905 | F48: =F44 -> 862157 | G48: =G44 -> 786246 | H48: =G46*(1+H47) -> #REF! | I48: =H48*(1+I47) -> #REF! | J48: =I48*(1+J47) -> #REF! | K48: =J48*(1+K47) -> #REF! | L48: =K48*(1+L47) -> #REF! | M48: =L48*(1+M47) -> #REF! | N48: =M48*(1+N47) -> #REF! | O48: =N48*(1+O47) -> #REF! | P48: =O48*(1+P47) -> #REF! | ... V48: =U48*(1+V47) -> #REF!
E50: Pendiente | F50: Constante
E51: =INDEX(LINEST(INDEX(C45:G45,COUNTBLANK(C45:G45)+1):G45,LN(INDEX(C43:G43,COUNTBLANK(C45:G45)):INDEX(C43:G43,4)),TRUE,),1) -> #REF! | F51: =INDEX(LINEST(INDEX(C45:G45,COUNTBLANK(C45:G45)+1):G45,LN(INDEX(C43:G43,COUNTBLANK(C45:G45)):INDEX(C43:G43,4)),TRUE,),2) -> #REF!
E53: Ajuste de la constante
E54: Valor real | F54: =G45 -> 824201.5
E55: Valor est. | F55: =LN(F43)*E51+F51 -> #REF!
E56: Const. Aj. | F56: =F54-F55+F51 -> #REF!
B60: Gastos administrativos | C60: =C$7 -> 2017 | D60: =D$7 -> 2018 | E60: =E$7 -> 2019 | F60: =F$7 -> 2020 | G60: =G$7 -> 2021 | H60: =G60+1 -> 2022 | I60: =H60+1 -> 2023 | J60: =I60+1 -> 2024 | K60: =J60+1 -> 2025 | L60: =K60+1 -> 2026 | M60: =L60+1 -> 2027 | N60: =M60+1 -> 2028 | O60: =N60+1 -> 2029 | ... V60: =U60+1 -> 2036
C61: =C$8 -> 1 | D61: =D$8 -> 2 | E61: =E$8 -> 3 | F61: =F$8 -> 4 | G61: =G$8 -> 5 | H61: =G61+1 -> 6 | I61: =H61+1 -> 7 | J61: =I61+1 -> 8 | K61: =J61+1 -> 9 | L61: =K61+1 -> 10 | M61: =L61+1 -> 11 | N61: =M61+1 -> 12 | O61: =N61+1 -> 13 | ... V61: =U61+1 -> 20
B62: Histórico | C62: =IF('EE.FF Económicos'!D39=0,"",-'EE.FF Económicos'!D39) -> 487579 | D62: =IF('EE.FF Económicos'!E39=0,"",-'EE.FF Económicos'!E39) -> 603139 | E62: =IF('EE.FF Económicos'!F39=0,"",-'EE.FF Económicos'!F39) -> 651838 | F62: =IF('EE.FF Económicos'!G39=0,"",-'EE.FF Económicos'!G39) -> 688428 | G62: =IF('EE.FF Económicos'!H39=0,"",-'EE.FF Económicos'!H39) -> 732928
B63: Promedio Móvil | D63: =IF(C62="","",AVERAGE(C62:D62)) -> 545359 | E63: =IF(D62="","",AVERAGE(D62:E62)) -> 627488.5 | F63: =IF(E62="","",AVERAGE(E62:F62)) -> 670133 | G63: =IF(F62="","",AVERAGE(F62:G62)) -> 710678
B64: Tendencia Logarítmica | G64: =LN(F61)*$E$69+$F$74 -> #REF! | H64: =LN(G61)*$E$69+$F$74 -> #REF! | I64: =LN(H61)*$E$69+$F$74 -> #REF! | J64: =LN(I61)*$E$69+$F$74 -> #REF! | K64: =LN(J61)*$E$69+$F$74 -> #REF! | L64: =LN(K61)*$E$69+$F$74 -> #REF! | M64: =LN(L61)*$E$69+$F$74 -> #REF! | N64: =LN(M61)*$E$69+$F$74 -> #REF! | ... V64: =LN(U61)*$E$69+$F$74 -> #REF!
B65: Tasa de crecimiento | H65: =IF(H$12>'EE.FF Económicos'!$D$53,H64/G64-1,'EE.FF Económicos'!$D$53) -> 0.015 | I65: =IF(I$12>'EE.FF Económicos'!$D$53,I64/H64-1,'EE.FF Económicos'!$D$53) -> 0.015 | J65: =IF(J$12>'EE.FF Económicos'!$D$53,J64/I64-1,'EE.FF Económicos'!$D$53) -> 0.015 | K65: =IF(K$12>'EE.FF Económicos'!$D$53,K64/J64-1,'EE.FF Económicos'!$D$53) -> 0.015 | L65: =IF(L$12>'EE.FF Económicos'!$D$53,L64/K64-1,'EE.FF Económicos'!$D$53) -> 0.015 | M65: =IF(M$12>'EE.FF Económicos'!$D$53,M64/L64-1,'EE.FF Económicos'!$D$53) -> 0.015 | N65: =IF(N$12>'EE.FF Económicos'!$D$53,N64/M64-1,'EE.FF Económicos'!$D$53) -> 0.015 | O65: =IF(O$12>'EE.FF Económicos'!$D$53,O64/N64-1,'EE.FF Económicos'!$D$53) -> 0.015 | ... V65: =IF(V$12>'EE.FF Económicos'!$D$53,V64/U64-1,'EE.FF Económicos'!$D$53) -> 0.015
B66: Proyección final | C66: =C62 -> 487579 | D66: =D62 -> 603139 | E66: =E62 -> 651838 | F66: =F62 -> 688428 | G66: =G62 -> 732928 | H66: =G64*(1+H65) -> #REF! | I66: =H66*(1+I65) -> #REF! | J66: =I66*(1+J65) -> #REF! | K66: =J66*(1+K65) -> #REF! | L66: =K66*(1+L65) -> #REF! | M66: =L66*(1+M65) -> #REF! | N66: =M66*(1+N65) -> #REF! | O66: =N66*(1+O65) -> #REF! | P66: =O66*(1+P65) -> #REF! | ... V66: =U66*(1+V65) -> #REF!
E68: Pendiente | F68: Constante
E69: =INDEX(LINEST(INDEX(C63:G63,COUNTBLANK(C63:G63)+1):G63,LN(INDEX(C61:G61,COUNTBLANK(C63:G63)):INDEX(C61:G61,4)),TRUE,),1) -> #REF! | F69: =INDEX(LINEST(INDEX(C63:G63,COUNTBLANK(C63:G63)+1):G63,LN(INDEX(C61:G61,COUNTBLANK(C63:G63)):INDEX(C61:G61,4)),TRUE,),2) -> #REF!
E71: Ajuste de la constante
E72: Valor real | F72: =G63 -> 710678
E73: Valor est. | F73: =LN(F61)*E69+F69 -> #REF!
E74: Const. Aj. | F74: =F72-F73+F69 -> #REF!
B78: Otros (Neto) | C78: =C$7 -> 2017 | D78: =D$7 -> 2018 | E78: =E$7 -> 2019 | F78: =F$7 -> 2020 | G78: =G$7 -> 2021 | H78: =G78+1 -> 2022 | I78: =H78+1 -> 2023 | J78: =I78+1 -> 2024 | K78: =J78+1 -> 2025 | L78: =K78+1 -> 2026 | M78: =L78+1 -> 2027 | N78: =M78+1 -> 2028 | O78: =N78+1 -> 2029 | ... V78: =U78+1 -> 2036
C79: =C$8 -> 1 | D79: =D$8 -> 2 | E79: =E$8 -> 3 | F79: =F$8 -> 4 | G79: =G$8 -> 5 | H79: =G79+1 -> 6 | I79: =H79+1 -> 7 | J79: =I79+1 -> 8 | K79: =J79+1 -> 9 | L79: =K79+1 -> 10 | M79: =L79+1 -> 11 | N79: =M79+1 -> 12 | O79: =N79+1 -> 13 | ... V79: =U79+1 -> 20
B80: Histórico | C80: =IF('EE.FF Económicos'!D40=0,"",'EE.FF Económicos'!D40) -> -42607 | D80: =IF('EE.FF Económicos'!E40=0,"",'EE.FF Económicos'!E40) -> 26059 | E80: =IF('EE.FF Económicos'!F40=0,"",'EE.FF Económicos'!F40) -> -49856 | F80: =IF('EE.FF Económicos'!G40=0,"",'EE.FF Económicos'!G40) -> -75085 | G80: =IF('EE.FF Económicos'!H40=0,"",'EE.FF Económicos'!H40) -> 39531
B81: Promedio Móvil | D81: =IF(C80="","",AVERAGE(C80:D80)) -> -8274 | E81: =IF(D80="","",AVERAGE(D80:E80)) -> -11898.5 | F81: =IF(E80="","",AVERAGE(E80:F80)) -> -62470.5 | G81: =IF(F80="","",AVERAGE(F80:G80)) -> -17777
B82: Tendencia Logarítmica | G82: =LN(F79)*$E$87+$F$92 -> #REF! | H82: =LN(G79)*$E$87+$F$92 -> #REF! | I82: =LN(H79)*$E$87+$F$92 -> #REF! | J82: =LN(I79)*$E$87+$F$92 -> #REF! | K82: =LN(J79)*$E$87+$F$92 -> #REF! | L82: =LN(K79)*$E$87+$F$92 -> #REF! | M82: =LN(L79)*$E$87+$F$92 -> #REF! | N82: =LN(M79)*$E$87+$F$92 -> #REF! | ... V82: =LN(U79)*$E$87+$F$92 -> #REF!
B83: Tasa de crecimiento | H83: =IF(H$12>'EE.FF Económicos'!$D$53,H82/G82-1,'EE.FF Económicos'!$D$53) -> 0.015 | I83: =IF(I$12>'EE.FF Económicos'!$D$53,I82/H82-1,'EE.FF Económicos'!$D$53) -> 0.015 | J83: =IF(J$12>'EE.FF Económicos'!$D$53,J82/I82-1,'EE.FF Económicos'!$D$53) -> 0.015 | K83: =IF(K$12>'EE.FF Económicos'!$D$53,K82/J82-1,'EE.FF Económicos'!$D$53) -> 0.015 | L83: =IF(L$12>'EE.FF Económicos'!$D$53,L82/K82-1,'EE.FF Económicos'!$D$53) -> 0.015 | M83: =IF(M$12>'EE.FF Económicos'!$D$53,M82/L82-1,'EE.FF Económicos'!$D$53) -> 0.015 | N83: =IF(N$12>'EE.FF Económicos'!$D$53,N82/M82-1,'EE.FF Económicos'!$D$53) -> 0.015 | O83: =IF(O$12>'EE.FF Económicos'!$D$53,O82/N82-1,'EE.FF Económicos'!$D$53) -> 0.015 | ... V83: =IF(V$12>'EE.FF Económicos'!$D$53,V82/U82-1,'EE.FF Económicos'!$D$53) -> 0.015
B84: Proyección final | H84: =G82*(1+H83) -> #REF! | I84: =H84*(1+I83) -> #REF! | J84: =I84*(1+J83) -> #REF! | K84: =J84*(1+K83) -> #REF! | L84: =K84*(1+L83) -> #REF! | M84: =L84*(1+M83) -> #REF! | N84: =M84*(1+N83) -> #REF! | O84: =N84*(1+O83) -> #REF! | P84: =O84*(1+P83) -> #REF! | ... V84: =U84*(1+V83) -> #REF!
E86: Pendiente | F86: Constante
E87: =INDEX(LINEST(INDEX(C81:G81,COUNTBLANK(C81:G81)+1):G81,LN(INDEX(C79:G79,COUNTBLANK(C81:G81)):INDEX(C79:G79,4)),TRUE,),1) -> #REF! | F87: =INDEX(LINEST(INDEX(C81:G81,COUNTBLANK(C81:G81)+1):G81,LN(INDEX(C79:G79,COUNTBLANK(C81:G81)):INDEX(C79:G79,4)),TRUE,),2) -> #REF!
E89: Ajuste de la constante
E90: Valor real | F90: =G81 -> -17777
E91: Valor est. | F91: =LN(F79)*E87+F87 -> #REF!
E92: Const. Aj. | F92: =F90-F91+F87 -> #REF!
B96: Depreciación | C96: =C$7 -> 2017 | D96: =D$7 -> 2018 | E96: =E$7 -> 2019 | F96: =F$7 -> 2020 | G96: =G$7 -> 2021 | H96: =G96+1 -> 2022 | I96: =H96+1 -> 2023 | J96: =I96+1 -> 2024 | K96: =J96+1 -> 2025 | L96: =K96+1 -> 2026 | M96: =L96+1 -> 2027 | N96: =M96+1 -> 2028 | O96: =N96+1 -> 2029 | ... V96: =U96+1 -> 2036
C97: =C$8 -> 1 | D97: =D$8 -> 2 | E97: =E$8 -> 3 | F97: =F$8 -> 4 | G97: =G$8 -> 5 | H97: =G97+1 -> 6 | I97: =H97+1 -> 7 | J97: =I97+1 -> 8 | K97: =J97+1 -> 9 | L97: =K97+1 -> 10 | M97: =L97+1 -> 11 | N97: =M97+1 -> 12 | O97: =N97+1 -> 13 | ... V97: =U97+1 -> 20
B98: Histórico | C98: =IF('EE.FF Económicos'!D43=0,"",'EE.FF Económicos'!D43) -> 164314 | D98: =IF('EE.FF Económicos'!E43=0,"",'EE.FF Económicos'!E43) -> 202775 | E98: =IF('EE.FF Económicos'!F43=0,"",'EE.FF Económicos'!F43) -> 298028 | F98: =IF('EE.FF Económicos'!G43=0,"",'EE.FF Económicos'!G43) -> 286071 | G98: =IF('EE.FF Económicos'!H43=0,"",'EE.FF Económicos'!H43) -> 232476
B99: Promedio Móvil | D99: =IF(C98="","",AVERAGE(C98:D98)) -> 183544.5 | E99: =IF(D98="","",AVERAGE(D98:E98)) -> 250401.5 | F99: =IF(E98="","",AVERAGE(E98:F98)) -> 292049.5 | G99: =IF(F98="","",AVERAGE(F98:G98)) -> 259273.5
B100: Tendencia Logarítmica | G100: =LN(F97)*$E$105+$F$110 -> #REF! | H100: =LN(G97)*$E$105+$F$110 -> #REF! | I100: =LN(H97)*$E$105+$F$110 -> #REF! | J100: =LN(I97)*$E$105+$F$110 -> #REF! | K100: =LN(J97)*$E$105+$F$110 -> #REF! | L100: =LN(K97)*$E$105+$F$110 -> #REF! | M100: =LN(L97)*$E$105+$F$110 -> #REF! | N100: =LN(M97)*$E$105+$F$110 -> #REF! | ... V100: =LN(U97)*$E$105+$F$110 -> #REF!
B101: Tasa de crecimiento | H101: =IF(H$12>'EE.FF Económicos'!$D$53,H100/G100-1,'EE.FF Económicos'!$D$53) -> 0.015 | I101: =IF(I$12>'EE.FF Económicos'!$D$53,I100/H100-1,'EE.FF Económicos'!$D$53) -> 0.015 | J101: =IF(J$12>'EE.FF Económicos'!$D$53,J100/I100-1,'EE.FF Económicos'!$D$53) -> 0.015 | K101: =IF(K$12>'EE.FF Económicos'!$D$53,K100/J100-1,'EE.FF Económicos'!$D$53) -> 0.015 | L101: =IF(L$12>'EE.FF Económicos'!$D$53,L100/K100-1,'EE.FF Económicos'!$D$53) -> 0.015 | M101: =IF(M$12>'EE.FF Económicos'!$D$53,M100/L100-1,'EE.FF Económicos'!$D$53) -> 0.015 | N101: =IF(N$12>'EE.FF Económicos'!$D$53,N100/M100-1,'EE.FF Económicos'!$D$53) -> 0.015 | O101: =IF(O$12>'EE.FF Económicos'!$D$53,O100/N100-1,'EE.FF Económicos'!$D$53) -> 0.015 | ... V101: =IF(V$12>'EE.FF Económicos'!$D$53,V100/U100-1,'EE.FF Económicos'!$D$53) -> 0.015
B102: Proyección final | H102: =G100*(1+H101) -> #REF! | I102: =H102*(1+I101) -> #REF! | J102: =I102*(1+J101) -> #REF! | K102: =J102*(1+K101) -> #REF! | L102: =K102*(1+L101) -> #REF! | M102: =L102*(1+M101) -> #REF! | N102: =M102*(1+N101) -> #REF! | O102: =N102*(1+O101) -> #REF! | P102: =O102*(1+P101) -> #REF! | ... V102: =U102*(1+V101) -> #REF!
E104: Pendiente | F104: Constante
E105: =INDEX(LINEST(INDEX(C99:G99,COUNTBLANK(C99:G99)+1):G99,LN(INDEX(C97:G97,COUNTBLANK(C99:G99)):INDEX(C97:G97,4)),TRUE,),1) -> #REF! | F105: =INDEX(LINEST(INDEX(C99:G99,COUNTBLANK(C99:G99)+1):G99,LN(INDEX(C97:G97,COUNTBLANK(C99:G99)):INDEX(C97:G97,4)),TRUE,),2) -> #REF!
E107: Ajuste de la constante
E108: Valor real | F108: =G99 -> 259273.5
E109: Valor est. | F109: =LN(F97)*E105+F105 -> #REF!
E110: Const. Aj. | F110: =F108-F109+F105 -> #REF!
B115: CAPEX | C115: =C$7 -> 2017 | D115: =D$7 -> 2018 | E115: =E$7 -> 2019 | F115: =F$7 -> 2020 | G115: =G$7 -> 2021 | H115: =G115+1 -> 2022 | I115: =H115+1 -> 2023 | J115: =I115+1 -> 2024 | K115: =J115+1 -> 2025 | L115: =K115+1 -> 2026 | M115: =L115+1 -> 2027 | N115: =M115+1 -> 2028 | O115: =N115+1 -> 2029 | ... V115: =U115+1 -> 2036
C116: =C$8 -> 1 | D116: =D$8 -> 2 | E116: =E$8 -> 3 | F116: =F$8 -> 4 | G116: =G$8 -> 5 | H116: =G116+1 -> 6 | I116: =H116+1 -> 7 | J116: =I116+1 -> 8 | K116: =J116+1 -> 9 | L116: =K116+1 -> 10 | M116: =L116+1 -> 11 | N116: =M116+1 -> 12 | O116: =N116+1 -> 13 | ... V116: =U116+1 -> 20
B117: Histórico | C117: =IF('EE.FF Económicos'!D50=0,"",'EE.FF Económicos'!D50) -> 3063714 | D117: =IF('EE.FF Económicos'!E50=0,"",'EE.FF Económicos'!E50) -> 3898978 | E117: =IF('EE.FF Económicos'!F50=0,"",'EE.FF Económicos'!F50) -> 4863313 | F117: =IF('EE.FF Económicos'!G50=0,"",'EE.FF Económicos'!G50) -> 5212083 | G117: =IF('EE.FF Económicos'!H50=0,"",'EE.FF Económicos'!H50) -> 5317443 | H117: =G117+H122 -> #REF! | I117: =H117+I122 -> #REF! | J117: =I117+J122 -> #REF! | K117: =J117+K122 -> #REF! | L117: =K117+L122 -> #REF! | M117: =L117+M122 -> #REF! | N117: =M117+N122 -> #REF! | O117: =N117+O122 -> #REF! | ... V117: =U117+V122 -> #REF!
B118: Variación | C118: =IFERROR(C117-B117,"") | D118: =IFERROR(D117-C117,"") -> 835264 | E118: =IFERROR(E117-D117,"") -> 964335 | F118: =IFERROR(F117-E117,"") -> 348770 | G118: =IFERROR(G117-F117,"") -> 105360
B119: Variación / Ingresos | C119: =IFERROR(C118/C9,"") | D119: =IFERROR(D118/D9,"") -> 0.10077139 | E119: =IFERROR(E118/E9,"") -> 0.097682003 | F119: =IFERROR(F118/F9,"") -> 0.034423413 | G119: =IFERROR(G118/G9,"") -> 0.0086165279
B120: Tendencia Logarítmica | G120: =LN(F116)*$E$125+$F$130 -> #REF! | H120: =LN(G116)*$E$125+$F$130 -> #REF! | I120: =LN(H116)*$E$125+$F$130 -> #REF! | J120: =LN(I116)*$E$125+$F$130 -> #REF! | K120: =LN(J116)*$E$125+$F$130 -> #REF! | L120: =LN(K116)*$E$125+$F$130 -> #REF! | M120: =LN(L116)*$E$125+$F$130 -> #REF! | N120: =LN(M116)*$E$125+$F$130 -> #REF! | ... V120: =LN(U116)*$E$125+$F$130 -> #REF!
B121: Ajuste | H121: =IF(GESTEP(H120,0)=1,H120,G120) -> #REF! | I121: =IF(GESTEP(I120,0)=1,I120,H121) -> #REF! | J121: =IF(GESTEP(J120,0)=1,J120,I121) -> #REF! | K121: =IF(GESTEP(K120,0)=1,K120,J121) -> #REF! | L121: =IF(GESTEP(L120,0)=1,L120,K121) -> #REF! | M121: =IF(GESTEP(M120,0)=1,M120,L121) -> #REF! | N121: =IF(GESTEP(N120,0)=1,N120,M121) -> #REF! | O121: =IF(GESTEP(O120,0)=1,O120,N121) -> #REF! | P121: =IF(GESTEP(P120,0)=1,P120,O121) -> #REF! | ... V121: =IF(GESTEP(V120,0)=1,V120,U121) -> #REF!
B122: Variación del CAPEX | G122: =$G$120*G11 -> #REF! | H122: =H121*H13 -> #REF! | I122: =I121*I13 -> #REF! | J122: =J121*J13 -> #REF! | K122: =K121*K13 -> #REF! | L122: =L121*L13 -> #REF! | M122: =M121*M13 -> #REF! | N122: =N121*N13 -> #REF! | O122: =O121*O13 -> #REF! | ... V122: =V121*V13 -> #REF!
E124: Pendiente | F124: Constante
E125: =INDEX(LINEST(INDEX(C119:G119,COUNTBLANK(C119:G119)+1):G119,LN(INDEX(C116:G116,COUNTBLANK(C119:G119)):INDEX(C116:G116,4)),TRUE,),1) -> #REF! | F125: =INDEX(LINEST(INDEX(C119:G119,COUNTBLANK(C119:G119)+1):G119,LN(INDEX(C116:G116,COUNTBLANK(C119:G119)):INDEX(C116:G116,4)),TRUE,),2) -> #REF!
E127: Ajuste de la constante
E128: Valor real | F128: =G119 -> 0.0086165279
E129: Valor est. | F129: =LN(F116)*E125+F125 -> #REF!
E130: Const. Aj. | F130: =F128-F129+F125 -> #REF!
B135: Capital de trabajo | C135: =C$7 -> 2017 | D135: =D$7 -> 2018 | E135: =E$7 -> 2019 | F135: =F$7 -> 2020 | G135: =G$7 -> 2021 | H135: =G135+1 -> 2022 | I135: =H135+1 -> 2023 | J135: =I135+1 -> 2024 | K135: =J135+1 -> 2025 | L135: =K135+1 -> 2026 | M135: =L135+1 -> 2027 | N135: =M135+1 -> 2028 | O135: =N135+1 -> 2029 | ... V135: =U135+1 -> 2036
C136: =C$8 -> 1 | D136: =D$8 -> 2 | E136: =E$8 -> 3 | F136: =F$8 -> 4 | G136: =G$8 -> 5 | H136: =G136+1 -> 6 | I136: =H136+1 -> 7 | J136: =I136+1 -> 8 | K136: =J136+1 -> 9 | L136: =K136+1 -> 10 | M136: =L136+1 -> 11 | N136: =M136+1 -> 12 | O136: =N136+1 -> 13 | ... V136: =U136+1 -> 20
B137: Activo corriente | C137: =IF('EE.FF Económicos'!D8=0,"",'EE.FF Económicos'!D8) -> 3289719 | D137: =IF('EE.FF Económicos'!E8=0,"",'EE.FF Económicos'!E8) -> 4103986 | E137: =IF('EE.FF Económicos'!F8=0,"",'EE.FF Económicos'!F8) -> 4490817 | F137: =IF('EE.FF Económicos'!G8=0,"",'EE.FF Económicos'!G8) -> 4618768 | G137: =IF('EE.FF Económicos'!H8=0,"",'EE.FF Económicos'!H8) -> 6509850
B138: Pasivo corriente | C138: =IF('EE.FF Económicos'!D20=0,"",'EE.FF Económicos'!D20) -> 2823965 | D138: =IF('EE.FF Económicos'!E20=0,"",'EE.FF Económicos'!E20) -> 3084554 | E138: =IF('EE.FF Económicos'!F20=0,"",'EE.FF Económicos'!F20) -> 3462553 | F138: =IF('EE.FF Económicos'!G20=0,"",'EE.FF Económicos'!G20) -> 3604331 | G138: =IF('EE.FF Económicos'!H20=0,"",'EE.FF Económicos'!H20) -> 4645551
B139: Capital de trabajo | C139: =IFERROR(C137-C138,"") -> 465754 | D139: =IFERROR(D137-D138,"") -> 1019432 | E139: =IFERROR(E137-E138,"") -> 1028264 | F139: =IFERROR(F137-F138,"") -> 1014437 | G139: =IFERROR(G137-G138,"") -> 1864299
...

Sheet EE.FF Económicos
B2: N° | C2: BALANCE GENERAL | D2: =IFERROR(IF(E2>'Plantilla Usuario'!$C$7,E2-1,""),"") -> 2017 | E2: =IFERROR(IF(F2>'Plantilla Usuario'!$C$7,F2-1,""),"") -> 2018 | F2: =IFERROR(IF(G2>'Plantilla Usuario'!$C$7,G2-1,""),"") -> 2019 | G2: =IFERROR(IF(H2>'Plantilla Usuario'!$C$7,H2-1,""),"") -> 2020 | H2: ='Plantilla Usuario'!C8 -> 2021
B3: 1 | D3: =IFERROR(IF(E3-1<1,"",E3-1),"") -> 1 | E3: =IFERROR(IF(F3-1<1,"",F3-1),"") -> 2 | F3: =IFERROR(IF(G3-1<1,"",G3-1),"") -> 3 | G3: =IFERROR(IF(H3-1<1,"",H3-1),"") -> 4 | H3: =5-COUNTBLANK(D2:H2) -> 5
B4: 2 | C4: Efectivo y Equivalentes al Efectivo | D4: =IF('EE.FF Económicos'!$D$54="Soles",HLOOKUP(D$2,'Plantilla Usuario'!$B$10:$I$54,$B4),HLOOKUP(D$2,'Plantilla Usuario'!$B$10:$I$54,$B4)/VLOOKUP($H$2,Tablas!$B$52:$C$59,2)) -> 3289719 | E4: =IF('EE.FF Económicos'!$D$54="Soles",HLOOKUP(E$2,'Plantilla Usuario'!$B$10:$I$54,$B4),HLOOKUP(E$2,'Plantilla Usuario'!$B$10:$I$54,$B4)/VLOOKUP($H$2,Tablas!$B$52:$C$59,2)) -> 4103986 | F4: =IF('EE.FF Económicos'!$D$54="Soles",HLOOKUP(F$2,'Plantilla Usuario'!$B$10:$I$54,$B4),HLOOKUP(F$2,'Plantilla Usuario'!$B$10:$I$54,$B4)/VLOOKUP($H$2,Tablas!$B$52:$C$59,2)) -> 4490817 | G4: =IF('EE.FF Económicos'!$D$54="Soles",HLOOKUP(G$2,'Plantilla Usuario'!$B$10:$I$54,$B4),HLOOKUP(G$2,'Plantilla Usuario'!$B$10:$I$54,$B4)/VLOOKUP($H$2,Tablas!$B$52:$C$59,2)) -> 4618768 | H4: =IF('EE.FF Económicos'!$D$54="Soles",HLOOKUP(H$2,'Plantilla Usuario'!$B$10:$I$54,$B4),HLOOKUP(H$2,'Plantilla Usuario'!$B$10:$I$54,$B4)/VLOOKUP($H$2,Tablas!$B$52:$C$59,2)) -> 6509850
B5: 3 | C5: Cuentas por Cobrar Comerciales y Otras Cuentas por Cobrar | D5: =IF('EE.FF Económicos'!$D$54="Soles",HLOOKUP(D$2,'Plantilla Usuario'!$B$10:$I$54,$B5),HLOOKUP(D$2,'Plantilla Usuario'!$B$10:$I$54,$B5)/VLOOKUP($H$2,Tablas!$B$52:$C$59,2)) -> 0 | E5: =IF('EE.FF Económicos'!$D$54="Soles",HLOOKUP(E$2,'Plantilla Usuario'!$B$10:$I$54,$B5),HLOOKUP(E$2,'Plantilla Usuario'!$B$10:$I$54,$B5)/VLOOKUP($H$2,Tablas!$B$52:$C$59,2)) -> 0 | F5: =IF('EE.FF Económicos'!$D$54="Soles",HLOOKUP(F$2,'Plantilla Usuario'!$B$10:$I$54,$B5),HLOOKUP(F$2,'Plantilla Usuario'!$B$10:$I$54,$B5)/VLOOKUP($H$2,Tablas!$B$52:$C$59,2)) -> 0 | G5: =IF('EE.FF Económicos'!$D$54="Soles",HLOOKUP(G$2,'Plantilla Usuario'!$B$10:$I$54,$B5),HLOOKUP(G$2,'Plantilla Usuario'!$B$10:$I$54,$B5)/VLOOKUP($H$2,Tablas!$B$52:$C$59,2)) -> 0 | H5: =IF('EE.FF Económicos'!$D$54="Soles",HLOOKUP(H$2,'Plantilla Usuario'!$B$10:$I$54,$B5),HLOOKUP(H$2,'Plantilla Usuario'!$B$10:$I$54,$B5)/VLOOKUP($H$2,Tablas!$B$52:$C$59,2)) -> 0
B6: 4 | C6: Inventarios | D6: =IF('EE.FF Económicos'!$D$54="Soles",HLOOKUP(D$2,'Plantilla Usuario'!$B$10:$I$54,$B6),HLOOKUP(D$2,'Plantilla Usuario'!$B$10:$I$54,$B6)/VLOOKUP($H$2,Tablas!$B$52:$C$59,2)) -> 0 | E6: =IF('EE.FF Económicos'!$D$54="Soles",HLOOKUP(E$2,'Plantilla Usuario'!$B$10:$I$54,$B6),HLOOKUP(E$2,'Plantilla Usuario'!$B$10:$I$54,$B6)/VLOOKUP($H$2,Tablas!$B$52:$C$59,2)) -> 0 | F6: =IF('EE.FF Económicos'!$D$54="Soles",HLOOKUP(F$2,'Plantilla Usuario'!$B$10:$I$54,$B6),HLOOKUP(F$2,'Plantilla Usuario'!$B$10:$I$54,$B6)/VLOOKUP($H$2,Tablas!$B$52:$C$59,2)) -> 0 | G6: =IF('EE.FF Económicos'!$D$54="Soles",HLOOKUP(G$2,'Plantilla Usuario'!$B$10:$I$54,$B6),HLOOKUP(G$2,'Plantilla Usuario'!$B$10:$I$54,$B6)/VLOOKUP($H$2,Tablas!$B$52:$C$59,2)) -> 0 | H6: =IF('EE.FF Económicos'!$D$54="Soles",HLOOKUP(H$2,'Plantilla Usuario'!$B$10:$I$54,$B6),HLOOKUP(H$2,'Plantilla Usuario'!$B$10:$I$54,$B6)/VLOOKUP($H$2,Tablas!$B$52:$C$59,2)) -> 0
B7: 5 | C7: Otros activos no financieros | D7: =IF('EE.FF Económicos'!$D$54="Soles",HLOOKUP(D$2,'Plantilla Usuario'!$B$10:$I$54,$B7),HLOOKUP(D$2,'Plantilla Usuario'!$B$10:$I$54,$B7)/VLOOKUP($H$2,Tablas!$B$52:$C$59,2)) -> 0 | E7: =IF('EE.FF Económicos'!$D$54="Soles",HLOOKUP(E$2,'Plantilla Usuario'!$B$10:$I$54,$B7),HLOOKUP(E$2,'Plantilla Usuario'!$B$10:$I$54,$B7)/VLOOKUP($H$2,Tablas!$B$52:$C$59,2)) -> 0 | F7: =IF('EE.FF Económicos'!$D$54="Soles",HLOOKUP(F$2,'Plantilla Usuario'!$B$10:$I$54,$B7),HLOOKUP(F$2,'Plantilla Usuario'!$B$10:$I$54,$B7)/VLOOKUP($H$2,Tablas!$B$52:$C$59,2)) -> 0 | G7: =IF('EE.FF Económicos'!$D$54="Soles",HLOOKUP(G$2,'Plantilla Usuario'!$B$10:$I$54,$B7),HLOOKUP(G$2,'Plantilla Usuario'!$B$10:$I$54,$B7)/VLOOKUP($H$2,Tablas!$B$52:$C$59,2)) -> 0 | H7: =IF('EE.FF Económicos'!$D$54="Soles",HLOOKUP(H$2,'Plantilla Usuario'!$B$10:$I$54,$B7),HLOOKUP(H$2,'Plantilla Usuario'!$B$10:$I$54,$B7)/VLOOKUP($H$2,Tablas!$B$52:$C$59,2)) -> 0
B8: 6 | C8: Total Activos Corrientes | D8: =IF('EE.FF Económicos'!$D$54="Soles",HLOOKUP(D$2,'Plantilla Usuario'!$B$10:$I$54,$B8),HLOOKUP(D$2,'Plantilla Usuario'!$B$10:$I$54,$B8)/VLOOKUP($H$2,Tablas!$B$52:$C$59,2)) -> 3289719 | E8: =IF('EE.FF Económicos'!$D$54="Soles",HLOOKUP(E$2,'Plantilla Usuario'!$B$10:$I$54,$B8),HLOOKUP(E$2,'Plantilla Usuario'!$B$10:$I$54,$B8)/VLOOKUP($H$2,Tablas!$B$52:$C$59,2)) -> 4103986 | F8: =IF('EE.FF Económicos'!$D$54="Soles",HLOOKUP(F$2,'Plantilla Usuario'!$B$10:$I$54,$B8),HLOOKUP(F$2,'Plantilla Usuario'!$B$10:$I$54,$B8)/VLOOKUP($H$2,Tablas!$B$52:$C$59,2)) -> 4490817 | G8: =IF('EE.FF Económicos'!$D$54="Soles",HLOOKUP(G$2,'Plantilla Usuario'!$B$10:$I$54,$B8),HLOOKUP(G$2,'Plantilla Usuario'!$B$10:$I$54,$B8)/VLOOKUP($H$2,Tablas!$B$52:$C$59,2)) -> 4618768 | H8: =IF('EE.FF Económicos'!$D$54="Soles",HLOOKUP(H$2,'Plantilla Usuario'!$B$10:$I$54,$B8),HLOOKUP(H$2,'Plantilla Usuario'!$B$10:$I$54,$B8)/VLOOKUP($H$2,Tablas!$B$52:$C$59,2)) -> 6509850
B9: 7 | C9: Cuentas por Cobrar Comerciales y Otras Cuentas por Cobrar | D9: =IF('EE.FF Económicos'!$D$54="Soles",HLOOKUP(D$2,'Plantilla Usuario'!$B$10:$I$54,$B9),HLOOKUP(D$2,'Plantilla Usuario'!$B$10:$I$54,$B9)/VLOOKUP($H$2,Tablas!$B$52:$C$59,2)) -> 3826276 | E9: =IF('EE.FF Económicos'!$D$54="Soles",HLOOKUP(E$2,'Plantilla Usuario'!$B$10:$I$54,$B9),HLOOKUP(E$2,'Plantilla Usuario'!$B$10:$I$54,$B9)/VLOOKUP($H$2,Tablas!$B$52:$C$59,2)) -> 4955240 | F9: =IF('EE.FF Económicos'!$D$54="Soles",HLOOKUP(F$2,'Plantilla Usuario'!$B$10:$I$54,$B9),HLOOKUP(F$2,'Plantilla Usuario'!$B$10:$I$54,$B9)/VLOOKUP($H$2,Tablas!$B$52:$C$59,2)) -> 6751464 | G9: =IF('EE.FF Económicos'!$D$54="Soles",HLOOKUP(G$2,'Plantilla Usuario'!$B$10:$I$54,$B9),HLOOKUP(G$2,'Plantilla Usuario'!$B$10:$I$54,$B9)/VLOOKUP($H$2,Tablas!$B$52:$C$59,2)) -> 7031343 | H9: =IF('EE.FF Económicos'!$D$54="Soles",HLOOKUP(H$2,'Plantilla Usuario'!$B$10:$I$54,$B9),HLOOKUP(H$2,'Plantilla Usuario'!$B$10:$I$54,$B9)/VLOOKUP($H$2,Tablas!$B$52:$C$59,2)) -> 6898453
B10: 8 | C10: Inversiones Financieras e inmobiliarias | D10: =IF('EE.FF Económicos'!$D$54="Soles",HLOOKUP(D$2,'Plantilla Usuario'!$B$10:$I$54,$B10),HLOOKUP(D$2,'Plantilla Usuario'!$B$10:$I$54,$B10)/VLOOKUP($H$2,Tablas!$B$52:$C$59,2)) -> 0 | E10: =IF('EE.FF Económicos'!$D$54="Soles",HLOOKUP(E$2,'Plantilla Usuario'!$B$10:$I$54,$B10),HLOOKUP(E$2,'Plantilla Usuario'!$B$10:$I$54,$B10)/VLOOKUP($H$2,Tablas!$B$52:$C$59,2)) -> 0 | F10: =IF('EE.FF Económicos'!$D$54="Soles",HLOOKUP(F$2,'Plantilla Usuario'!$B$10:$I$54,$B10),HLOOKUP(F$2,'Plantilla Usuario'!$B$10:$I$54,$B10)/VLOOKUP($H$2,Tablas!$B$52:$C$59,2)) -> 0 | G10: =IF('EE.FF Económicos'!$D$54="Soles",HLOOKUP(G$2,'Plantilla Usuario'!$B$10:$I$54,$B10),HLOOKUP(G$2,'Plantilla Usuario'!$B$10:$I$54,$B10)/VLOOKUP($H$2,Tablas!$B$52:$C$59,2)) -> 0 | H10: =IF('EE.FF Económicos'!$D$54="Soles",HLOOKUP(H$2,'Plantilla Usuario'!$B$10:$I$54,$B10),HLOOKUP(H$2,'Plantilla Usuario'!$B$10:$I$54,$B10)/VLOOKUP($H$2,Tablas!$B$52:$C$59,2)) -> 0
B11: 9 | C11: Propiedades, Planta y Equipo | D11: =IF('EE.FF Económicos'!$D$54="Soles",HLOOKUP(D$2,'Plantilla Usuario'!$B$10:$I$54,$B11),HLOOKUP(D$2,'Plantilla Usuario'!$B$10:$I$54,$B11)/VLOOKUP($H$2,Tablas!$B$52:$C$59,2)) -> 1865624 | E11: =IF('EE.FF Económicos'!$D$54="Soles",HLOOKUP(E$2,'Plantilla Usuario'!$B$10:$I$54,$B11),HLOOKUP(E$2,'Plantilla Usuario'!$B$10:$I$54,$B11)/VLOOKUP($H$2,Tablas!$B$52:$C$59,2)) -> 2537852 | F11: =IF('EE.FF Económicos'!$D$54="Soles",HLOOKUP(F$2,'Plantilla Usuario'!$B$10:$I$54,$B11),HLOOKUP(F$2,'Plantilla Usuario'!$B$10:$I$54,$B11)/VLOOKUP($H$2,Tablas!$B$52:$C$59,2)) -> 3323015 | G11: =IF('EE.FF Económicos'!$D$54="Soles",HLOOKUP(G$2,'Plantilla Usuario'!$B$10:$I$54,$B11),HLOOKUP(G$2,'Plantilla Usuario'!$B$10:$I$54,$B11)/VLOOKUP($H$2,Tablas!$B$52:$C$59,2)) -> 3410774 | H11: =IF('EE.FF Económicos'!$D$54="Soles",HLOOKUP(H$2,'Plantilla Usuario'!$B$10:$I$54,$B11),HLOOKUP(H$2,'Plantilla Usuario'!$B$10:$I$54,$B11)/VLOOKUP($H$2,Tablas!$B$52:$C$59,2)) -> 3343589
B12: 10 | C12: Depreciación Acumulada | D12: =IF('EE.FF Económicos'!$D$54="Soles",HLOOKUP(D$2,'Plantilla Usuario'!$B$10:$I$54,$B12),HLOOKUP(D$2,'Plantilla Usuario'!$B$10:$I$54,$B12)/VLOOKUP($H$2,Tablas!$B$52:$C$59,2)) -> 1198090 | E12: =IF('EE.FF Económicos'!$D$54="Soles",HLOOKUP(E$2,'Plantilla Usuario'!$B$10:$I$54,$B12),HLOOKUP(E$2,'Plantilla Usuario'!$B$10:$I$54,$B12)/VLOOKUP($H$2,Tablas!$B$52:$C$59,2)) -> 1361126 | F12: =IF('EE.FF Económicos'!$D$54="Soles",HLOOKUP(F$2,'Plantilla Usuario'!$B$10:$I$54,$B12),HLOOKUP(F$2,'Plantilla Usuario'!$B$10:$I$54,$B12)/VLOOKUP($H$2,Tablas!$B$52:$C$59,2)) -> 1540298 | G12: =IF('EE.FF Económicos'!$D$54="Soles",HLOOKUP(G$2,'Plantilla Usuario'!$B$10:$I$54,$B12),HLOOKUP(G$2,'Plantilla Usuario'!$B$10:$I$54,$B12)/VLOOKUP($H$2,Tablas!$B$52:$C$59,2)) -> 1801309 | H12: =IF('EE.FF Económicos'!$D$54="Soles",HLOOKUP(H$2,'Plantilla Usuario'!$B$10:$I$54,$B12),HLOOKUP(H$2,'Plantilla Usuario'!$B$10:$I$54,$B12)/VLOOKUP($H$2,Tablas!$B$52:$C$59,2)) -> 1973854
B13: 11 | C13: Activos Intangibles | D13: =IF('EE.FF Económicos'!$D$54="Soles",HLOOKUP(D$2,'Plantilla Usuario'!$B$10:$I$54,$B13),HLOOKUP(D$2,'Plantilla Usuario'!$B$10:$I$54,$B13)/VLOOKUP($H$2,Tablas!$B$52:$C$59,2)) -> 0 | E13: =IF('EE.FF Económicos'!$D$54="Soles",HLOOKUP(E$2,'Plantilla Usuario'!$B$10:$I$54,$B13),HLOOKUP(E$2,'Plantilla Usuario'!$B$10:$I$54,$B13)/VLOOKUP($H$2,Tablas!$B$52:$C$59,2)) -> 0 | F13: =IF('EE.FF Económicos'!$D$54="Soles",HLOOKUP(F$2,'Plantilla Usuario'!$B$10:$I$54,$B13),HLOOKUP(F$2,'Plantilla Usuario'!$B$10:$I$54,$B13)/VLOOKUP($H$2,Tablas!$B$52:$C$59,2)) -> 0 | G13: =IF('EE.FF Económicos'!$D$54="Soles",HLOOKUP(G$2,'Plantilla Usuario'!$B$10:$I$54,$B13),HLOOKUP(G$2,'Plantilla Usuario'!$B$10:$I$54,$B13)/VLOOKUP($H$2,Tablas!$B$52:$C$59,2)) -> 0 | H13: =IF('EE.FF Económicos'!$D$54="Soles",HLOOKUP(H$2,'Plantilla Usuario'!$B$10:$I$54,$B13),HLOOKUP(H$2,'Plantilla Usuario'!$B$10:$I$54,$B13)/VLOOKUP($H$2,Tablas!$B$52:$C$59,2)) -> 0
B14: 12 | C14: Otros activos no financieros | D14: =IF('EE.FF Económicos'!$D$54="Soles",HLOOKUP(D$2,'Plantilla Usuario'!$B$10:$I$54,$B14),HLOOKUP(D$2,'Plantilla Usuario'!$B$10:$I$54,$B14)/VLOOKUP($H$2,Tablas!$B$52:$C$59,2)) -> 0 | E14: =IF('EE.FF Económicos'!$D$54="Soles",HLOOKUP(E$2,'Plantilla Usuario'!$B$10:$I$54,$B14),HLOOKUP(E$2,'Plantilla Usuario'!$B$10:$I$54,$B14)/VLOOKUP($H$2,Tablas!$B$52:$C$59,2)) -> 0 | F14: =IF('EE.FF Económicos'!$D$54="Soles",HLOOKUP(F$2,'Plantilla Usuario'!$B$10:$I$54,$B14),HLOOKUP(F$2,'Plantilla Usuario'!$B$10:$I$54,$B14)/VLOOKUP($H$2,Tablas!$B$52:$C$59,2)) -> 0 | G14: =IF('EE.FF Económicos'!$D$54="Soles",HLOOKUP(G$2,'Plantilla Usuario'!$B$10:$I$54,$B14),HLOOKUP(G$2,'Plantilla Usuario'!$B$10:$I$54,$B14)/VLOOKUP($H$2,Tablas!$B$52:$C$59,2)) -> 0 | H14: =IF('EE.FF Económicos'!$D$54="Soles",HLOOKUP(H$2,'Plantilla Usuario'!$B$10:$I$54,$B14),HLOOKUP(H$2,'Plantilla Usuario'!$B$10:$I$54,$B14)/VLOOKUP($H$2,Tablas!$B$52:$C$59,2)) -> 0
B15: 13 | C15: Total Activos No Corrientes | D15: =IF('EE.FF Económicos'!$D$54="Soles",HLOOKUP(D$2,'Plantilla Usuario'!$B$10:$I$54,$B15),HLOOKUP(D$2,'Plantilla Usuario'!$B$10:$I$54,$B15)/VLOOKUP($H$2,Tablas!$B$52:$C$59,2)) -> 3826276 | E15: =IF('EE.FF Económicos'!$D$54="Soles",HLOOKUP(E$2,'Plantilla Usuario'!$B$10:$I$54,$B15),HLOOKUP(E$2,'Plantilla Usuario'!$B$10:$I$54,$B15)/VLOOKUP($H$2,Tablas!$B$52:$C$59,2)) -> 4955240 | F15: =IF('EE.FF Económicos'!$D$54="Soles",HLOOKUP(F$2,'Plantilla Usuario'!$B$10:$I$54,$B15),HLOOKUP(F$2,'Plantilla Usuario'!$B$10:$I$54,$B15)/VLOOKUP($H$2,Tablas!$B$52:$C$59,2)) -> 6751464 | G15: =IF('EE.FF Económicos'!$D$54="Soles",HLOOKUP(G$2,'Plantilla Usuario'!$B$10:$I$54,$B15),HLOOKUP(G$2,'Plantilla Usuario'!$B$10:$I$54,$B15)/VLOOKUP($H$2,Tablas!$B$52:$C$59,2)) -> 7031343 | H15: =IF('EE.FF Económicos'!$D$54="Soles",HLOOKUP(H$2,'Plantilla Usuario'!$B$10:$I$54,$B15),HLOOKUP(H$2,'Plantilla Usuario'!$B$10:$I$54,$B15)/VLOOKUP($H$2,Tablas!$B$52:$C$59,2)) -> 6898453
... B31: 29 | C31: TOTAL PASIVOS Y PATRIMONIO | D31: =IF('EE.FF Económicos'!$D$54="Soles",HLOOKUP(D$2,'Plantilla Usuario'!$B$10:$I$54,$B31),HLOOKUP(D$2,'Plantilla Usuario'!$B$10:$I$54,$B31)/VLOOKUP($H$2,Tablas!$B$52:$C$59,2)) -> 7115995 | E31: =IF('EE.FF Económicos'!$D$54="Soles",HLOOKUP(E$2,'Plantilla Usuario'!$B$10:$I$54,$B31),HLOOKUP(E$2,'Plantilla Usuario'!$B$10:$I$54,$B31)/VLOOKUP($H$2,Tablas!$B$52:$C$59,2)) -> 9059226 | F31: =IF('EE.FF Económicos'!$D$54="Soles",HLOOKUP(F$2,'Plantilla Usuario'!$B$10:$I$54,$B31),HLOOKUP(F$2,'Plantilla Usuario'!$B$10:$I$54,$B31)/VLOOKUP($H$2,Tablas!$B$52:$C$59,2)) -> 11242281 | G31: =IF('EE.FF Económicos'!$D$54="Soles",HLOOKUP(G$2,'Plantilla Usuario'!$B$10:$I$54,$B31),HLOOKUP(G$2,'Plantilla Usuario'!$B$10:$I$54,$B31)/VLOOKUP($H$2,Tablas!$B$52:$C$59,2)) -> 11650111 | H31: =IF('EE.FF Económicos'!$D$54="Soles",HLOOKUP(H$2,'Plantilla Usuario'!$B$10:$I$54,$B31),HLOOKUP(H$2,'Plantilla Usuario'!$B$10:$I$54,$B31)/VLOOKUP($H$2,Tablas!$B$52:$C$59,2)) -> 13408303
B32: 30
B33: 31
B34: 32 | C34: ESTADO DE RESULTADOS | D34: =D2 -> 2017 | E34: =E2 -> 2018 | F34: =F2 -> 2019 | G34: =G2 -> 2020 | H34: =H2 -> 2021
B35: 33 | C35: Ingresos de Actividades Ordinarias | D35: =VALUE(IF('EE.FF Económicos'!$D$54="Soles",HLOOKUP(D$2,'Plantilla Usuario'!$B$10:$I$54,$B35),HLOOKUP(D$2,'Plantilla Usuario'!$B$10:$I$54,$B35)/VLOOKUP($H$2,Tablas!$B$52:$C$59,2))) -> 6949265 | E35: =VALUE(IF('EE.FF Económicos'!$D$54="Soles",HLOOKUP(E$2,'Plantilla Usuario'!$B$10:$I$54,$B35),HLOOKUP(E$2,'Plantilla Usuario'!$B$10:$I$54,$B35)/VLOOKUP($H$2,Tablas!$B$52:$C$59,2))) -> 8288702 | F35: =VALUE(IF('EE.FF Económicos'!$D$54="Soles",HLOOKUP(F$2,'Plantilla Usuario'!$B$10:$I$54,$B35),HLOOKUP(F$2,'Plantilla Usuario'!$B$10:$I$54,$B35)/VLOOKUP($H$2,Tablas!$B$52:$C$59,2))) -> 9872187 | G35: =VALUE(IF('EE.FF Económicos'!$D$54="Soles",HLOOKUP(G$2,'Plantilla Usuario'!$B$10:$I$54,$B35),HLOOKUP(G$2,'Plantilla Usuario'!$B$10:$I$54,$B35)/VLOOKUP($H$2,Tablas!$B$52:$C$59,2))) -> 10131767 | H35: =VALUE(IF('EE.FF Económicos'!$D$54="Soles",HLOOKUP(H$2,'Plantilla Usuario'!$B$10:$I$54,$B35),HLOOKUP(H$2,'Plantilla Usuario'!$B$10:$I$54,$B35)/VLOOKUP($H$2,Tablas!$B$52:$C$59,2))) -> 12227663
B36: 34 | C36: Costo de Ventas | D36: =IF('EE.FF Económicos'!$D$54="Soles",HLOOKUP(D$2,'Plantilla Usuario'!$B$10:$I$54,$B36),HLOOKUP(D$2,'Plantilla Usuario'!$B$10:$I$54,$B36)/VLOOKUP($H$2,Tablas!$B$52:$C$59,2)) -> -5042402 | E36: =IF('EE.FF Económicos'!$D$54="Soles",HLOOKUP(E$2,'Plantilla Usuario'!$B$10:$I$54,$B36),HLOOKUP(E$2,'Plantilla Usuario'!$B$10:$I$54,$B36)/VLOOKUP($H$2,Tablas!$B$52:$C$59,2)) -> -6244012 | F36: =IF('EE.FF Económicos'!$D$54="Soles",HLOOKUP(F$2,'Plantilla Usuario'!$B$10:$I$54,$B36),HLOOKUP(F$2,'Plantilla Usuario'!$B$10:$I$54,$B36)/VLOOKUP($H$2,Tablas!$B$52:$C$59,2)) -> -7420013 | G36: =IF('EE.FF Económicos'!$D$54="Soles",HLOOKUP(G$2,'Plantilla Usuario'!$B$10:$I$54,$B36),HLOOKUP(G$2,'Plantilla Usuario'!$B$10:$I$54,$B36)/VLOOKUP($H$2,Tablas!$B$52:$C$59,2)) -> -7712254 | H36: =IF('EE.FF Económicos'!$D$54="Soles",HLOOKUP(H$2,'Plantilla Usuario'!$B$10:$I$54,$B36),HLOOKUP(H$2,'Plantilla Usuario'!$B$10:$I$54,$B36)/VLOOKUP($H$2,Tablas!$B$52:$C$59,2)) -> -9831454
B37: 35 | C37: Utilidad Bruta | D37: =IF('EE.FF Económicos'!$D$54="Soles",HLOOKUP(D$2,'Plantilla Usuario'!$B$10:$I$54,$B37),HLOOKUP(D$2,'Plantilla Usuario'!$B$10:$I$54,$B37)/VLOOKUP($H$2,Tablas!$B$52:$C$59,2)) -> 1906863 | E37: =IF('EE.FF Económicos'!$D$54="Soles",HLOOKUP(E$2,'Plantilla Usuario'!$B$10:$I$54,$B37),HLOOKUP(E$2,'Plantilla Usuario'!$B$10:$I$54,$B37)/VLOOKUP($H$2,Tablas!$B$52:$C$59,2)) -> 2044690 | F37: =IF('EE.FF Económicos'!$D$54="Soles",HLOOKUP(F$2,'Plantilla Usuario'!$B$10:$I$54,$B37),HLOOKUP(F$2,'Plantilla Usuario'!$B$10:$I$54,$B37)/VLOOKUP($H$2,Tablas!$B$52:$C$59,2)) -> 2452174 | G37: =IF('EE.FF Económicos'!$D$54="Soles",HLOOKUP(G$2,'Plantilla Usuario'!$B$10:$I$54,$B37),HLOOKUP(G$2,'Plantilla Usuario'!$B$10:$I$54,$B37)/VLOOKUP($H$2,Tablas!$B$52:$C$59,2)) -> 2419513 | H37: =IF('EE.FF Económicos'!$D$54="Soles",HLOOKUP(H$2,'Plantilla Usuario'!$B$10:$I$54,$B37),HLOOKUP(H$2,'Plantilla Usuario'!$B$10:$I$54,$B37)/VLOOKUP($H$2,Tablas!$B$52:$C$59,2)) -> 2396209
B38: 36 | C38: Gastos de Ventas y Distribución | D38: =IF('EE.FF Económicos'!$D$54="Soles",HLOOKUP(D$2,'Plantilla Usuario'!$B$10:$I$54,$B38),HLOOKUP(D$2,'Plantilla Usuario'!$B$10:$I$54,$B38)/VLOOKUP($H$2,Tablas!$B$52:$C$59,2)) -> -633605 | E38: =IF('EE.FF Económicos'!$D$54="Soles",HLOOKUP(E$2,'Plantilla Usuario'!$B$10:$I$54,$B38),HLOOKUP(E$2,'Plantilla Usuario'!$B$10:$I$54,$B38)/VLOOKUP($H$2,Tablas!$B$52:$C$59,2)) -> -681336 | F38: =IF('EE.FF Económicos'!$D$54="Soles",HLOOKUP(F$2,'Plantilla Usuario'!$B$10:$I$54,$B38),HLOOKUP(F$2,'Plantilla Usuario'!$B$10:$I$54,$B38)/VLOOKUP($H$2,Tablas!$B$52:$C$59,2)) -> -801905 | G38: =IF('EE.FF Económicos'!$D$54="Soles",HLOOKUP(G$2,'Plantilla Usuario'!$B$10:$I$54,$B38),HLOOKUP(G$2,'Plantilla Usuario'!$B$10:$I$54,$B38)/VLOOKUP($H$2,Tablas!$B$52:$C$59,2)) -> -862157 | H38: =IF('EE.FF Económicos'!$D$54="Soles",HLOOKUP(H$2,'Plantilla Usuario'!$B$10:$I$54,$B38),HLOOKUP(H$2,'Plantilla Usuario'!$B$10:$I$54,$B38)/VLOOKUP($H$2,Tablas!$B$52:$C$59,2)) -> -786246
B39: 37 | C39: Gastos de Administración | D39: =IF('EE.FF Económicos'!$D$54="Soles",HLOOKUP(D$2,'Plantilla Usuario'!$B$10:$I$54,$B40),HLOOKUP(D$2,'Plantilla Usuario'!$B$10:$I$54,$B40)/VLOOKUP($H$2,Tablas!$B$52:$C$59,2)) -> -487579 | E39: =IF('EE.FF Económicos'!$D$54="Soles",HLOOKUP(E$2,'Plantilla Usuario'!$B$10:$I$54,$B40),HLOOKUP(E$2,'Plantilla Usuario'!$B$10:$I$54,$B40)/VLOOKUP($H$2,Tablas!$B$52:$C$59,2)) -> -603139 | F39: =IF('EE.FF Económicos'!$D$54="Soles",HLOOKUP(F$2,'Plantilla Usuario'!$B$10:$I$54,$B40),HLOOKUP(F$2,'Plantilla Usuario'!$B$10:$I$54,$B40)/VLOOKUP($H$2,Tablas!$B$52:$C$59,2)) -> -651838 | G39: =IF('EE.FF Económicos'!$D$54="Soles",HLOOKUP(G$2,'Plantilla Usuario'!$B$10:$I$54,$B40),HLOOKUP(G$2,'Plantilla Usuario'!$B$10:$I$54,$B40)/VLOOKUP($H$2,Tablas!$B$52:$C$59,2)) -> -688428 | H39: =IF('EE.FF Económicos'!$D$54="Soles",HLOOKUP(H$2,'Plantilla Usuario'!$B$10:$I$54,$B40),HLOOKUP(H$2,'Plantilla Usuario'!$B$10:$I$54,$B40)/VLOOKUP($H$2,Tablas!$B$52:$C$59,2)) -> -732928
B40: 38 | C40: Otros ingresos (gastos) netos | D40: =IF('EE.FF Económicos'!$D$54="Soles",HLOOKUP(D$2,'Plantilla Usuario'!$B$10:$I$54,$B41),HLOOKUP(D$2,'Plantilla Usuario'!$B$10:$I$54,$B41)/VLOOKUP($H$2,Tablas!$B$52:$C$59,2)) -> -42607 | E40: =IF('EE.FF Económicos'!$D$54="Soles",HLOOKUP(E$2,'Plantilla Usuario'!$B$10:$I$54,$B41),HLOOKUP(E$2,'Plantilla Usuario'!$B$10:$I$54,$B41)/VLOOKUP($H$2,Tablas!$B$52:$C$59,2)) -> 26059 | F40: =IF('EE.FF Económicos'!$D$54="Soles",HLOOKUP(F$2,'Plantilla Usuario'!$B$10:$I$54,$B41),HLOOKUP(F$2,'Plantilla Usuario'!$B$10:$I$54,$B41)/VLOOKUP($H$2,Tablas!$B$52:$C$59,2)) -> -49856 | G40: =IF('EE.FF Económicos'!$D$54="Soles",HLOOKUP(G$2,'Plantilla Usuario'!$B$10:$I$54,$B41),HLOOKUP(G$2,'Plantilla Usuario'!$B$10:$I$54,$B41)/VLOOKUP($H$2,Tablas!$B$52:$C$59,2)) -> -75085 | H40: =IF('EE.FF Económicos'!$D$54="Soles",HLOOKUP(H$2,'Plantilla Usuario'!$B$10:$I$54,$B41),HLOOKUP(H$2,'Plantilla Usuario'!$B$10:$I$54,$B41)/VLOOKUP($H$2,Tablas!$B$52:$C$59,2)) -> 39531
B41: 39 | C41: Utilidad Operativa | D41: =SUM(D37:D40) -> 743072 | E41: =SUM(E37:E40) -> 786274 | F41: =SUM(F37:F40) -> 948575 | G41: =SUM(G37:G40) -> 793843 | H41: =SUM(H37:H40) -> 916566
B42: 41 | C42: Impuesto | D42: =-29.5%*D41 -> -219206.24 | E42: =-29.5%*E41 -> -231950.83 | F42: =-29.5%*F41 -> -279829.62 | G42: =-29.5%*G41 -> -234183.68 | H42: =-29.5%*H41 -> -270386.97
B43: 42 | C43: Depreciación | D43: =IF('EE.FF Económicos'!$D$54="Soles",HLOOKUP(D$2,'Plantilla Usuario'!$B$10:$I$54,$B39),HLOOKUP(D$2,'Plantilla Usuario'!$B$10:$I$54,$B39)/VLOOKUP($H$2,Tablas!$B$52:$C$59,2)) -> 164314 | E43: =IF('EE.FF Económicos'!$D$54="Soles",HLOOKUP(E$2,'Plantilla Usuario'!$B$10:$I$54,$B39),HLOOKUP(E$2,'Plantilla Usuario'!$B$10:$I$54,$B39)/VLOOKUP($H$2,Tablas!$B$52:$C$59,2)) -> 202775 | F43: =IF('EE.FF Económicos'!$D$54="Soles",HLOOKUP(F$2,'Plantilla Usuario'!$B$10:$I$54,$B39),HLOOKUP(F$2,'Plantilla Usuario'!$B$10:$I$54,$B39)/VLOOKUP($H$2,Tablas!$B$52:$C$59,2)) -> 298028 | G43: =IF('EE.FF Económicos'!$D$54="Soles",HLOOKUP(G$2,'Plantilla Usuario'!$B$10:$I$54,$B39),HLOOKUP(G$2,'Plantilla Usuario'!$B$10:$I$54,$B39)/VLOOKUP($H$2,Tablas!$B$52:$C$59,2)) -> 286071 | H43: =IF('EE.FF Económicos'!$D$54="Soles",HLOOKUP(H$2,'Plantilla Usuario'!$B$10:$I$54,$B39),HLOOKUP(H$2,'Plantilla Usuario'!$B$10:$I$54,$B39)/VLOOKUP($H$2,Tablas!$B$52:$C$59,2)) -> 232476
B44: 43 | C44: Flujo de caja Operativo | D44: =D41+D42+D43 -> 688179.76 | E44: =E41+E42+E43 -> 757098.17 | F44: =F41+F42+F43 -> 966773.38 | G44: =G41+G42+G43 -> 845730.31 | H44: =H41+H42+H43 -> 878655.03
B45: 44
B46: 45
B47: 46 | C47: Cálculo del CAPEX | D47: =D34 -> 2017 | E47: =E34 -> 2018 | F47: =F34 -> 2019 | G47: =G34 -> 2020 | H47: =H34 -> 2021
B48: 47 | C48: Propiedad Planta y Equipo | D48: =IF('EE.FF Económicos'!$D$54="Soles",HLOOKUP(D$2,'Plantilla Usuario'!$B$10:$I$54,$B11),HLOOKUP(D$2,'Plantilla Usuario'!$B$10:$I$54,$B11)/VLOOKUP($H$2,Tablas!$B$52:$C$59,2)) -> 1865624 | E48: =IF('EE.FF Económicos'!$D$54="Soles",HLOOKUP(E$2,'Plantilla Usuario'!$B$10:$I$54,$B11),HLOOKUP(E$2,'Plantilla Usuario'!$B$10:$I$54,$B11)/VLOOKUP($H$2,Tablas!$B$52:$C$59,2)) -> 2537852 | F48: =IF('EE.FF Económicos'!$D$54="Soles",HLOOKUP(F$2,'Plantilla Usuario'!$B$10:$I$54,$B11),HLOOKUP(F$2,'Plantilla Usuario'!$B$10:$I$54,$B11)/VLOOKUP($H$2,Tablas!$B$52:$C$59,2)) -> 3323015 | G48: =IF('EE.FF Económicos'!$D$54="Soles",HLOOKUP(G$2,'Plantilla Usuario'!$B$10:$I$54,$B11),HLOOKUP(G$2,'Plantilla Usuario'!$B$10:$I$54,$B11)/VLOOKUP($H$2,Tablas!$B$52:$C$59,2)) -> 3410774 | H48: =IF('EE.FF Económicos'!$D$54="Soles",HLOOKUP(H$2,'Plantilla Usuario'!$B$10:$I$54,$B11),HLOOKUP(H$2,'Plantilla Usuario'!$B$10:$I$54,$B11)/VLOOKUP($H$2,Tablas!$B$52:$C$59,2)) -> 3343589
B49: 48 | C49: Depreciación acumulada | D49: =IF('EE.FF Económicos'!$D$54="Soles",HLOOKUP(D$2,'Plantilla Usuario'!$B$10:$I$54,$B12),HLOOKUP(D$2,'Plantilla Usuario'!$B$10:$I$54,$B12)/VLOOKUP($H$2,Tablas!$B$52:$C$59,2)) -> 1198090 | E49: =IF('EE.FF Económicos'!$D$54="Soles",HLOOKUP(E$2,'Plantilla Usuario'!$B$10:$I$54,$B12),HLOOKUP(E$2,'Plantilla Usuario'!$B$10:$I$54,$B12)/VLOOKUP($H$2,Tablas!$B$52:$C$59,2)) -> 1361126 | F49: =IF('EE.FF Económicos'!$D$54="Soles",HLOOKUP(F$2,'Plantilla Usuario'!$B$10:$I$54,$B12),HLOOKUP(F$2,'Plantilla Usuario'!$B$10:$I$54,$B12)/VLOOKUP($H$2,Tablas!$B$52:$C$59,2)) -> 1540298 | G49: =IF('EE.FF Económicos'!$D$54="Soles",HLOOKUP(G$2,'Plantilla Usuario'!$B$10:$I$54,$B12),HLOOKUP(G$2,'Plantilla Usuario'!$B$10:$I$54,$B12)/VLOOKUP($H$2,Tablas!$B$52:$C$59,2)) -> 1801309 | H49: =IF('EE.FF Económicos'!$D$54="Soles",HLOOKUP(H$2,'Plantilla Usuario'!$B$10:$I$54,$B12),HLOOKUP(H$2,'Plantilla Usuario'!$B$10:$I$54,$B12)/VLOOKUP($H$2,Tablas!$B$52:$C$59,2)) -> 1973854
B50: 49 | C50: Total Costo de Activos de Adquisición | D50: =D48+D49 -> 3063714 | E50: =E48+E49 -> 3898978 | F50: =F48+F49 -> 4863313 | G50: =G48+G49 -> 5212083 | H50: =H48+H49 -> 5317443
C53: Gradiente | D53: 0.015
C54: Moneda (Estados Financieros) | D54: Soles

Sheet Devaluación
A1: 2021 | N1: 2022 | AA1: 2023 | AN1: 2024 | BA1: 2025
A2: Periodo (años) | B2: Argentina | C2: Brazil | D2: Chile | E2: Colombia | F2: Ecuador | G2: Mexico | H2: Peru | I2: United States | K2: Horizonte del proyecto (en años) | L2: =WACC!$C$6 -> 1 | N2: Periodo (años) | O2: Argentina | P2: Brazil | Q2: Chile | R2: Colombia | S2: Ecuador | T2: Mexico | U2: Peru | V2: United States | X2: Horizonte del proyecto (en años) | Y2: =WACC!$C$6 -> 1 | AA2: Periodo (años) | AB2: Argentina | AC2: Brazil | AD2: Chile | AE2: Colombia | AF2: Ecuador | AG2: Mexico | AH2: Peru | AI2: United States | AK2: Horizonte del proyecto (en años) | AL2: =WACC!$C$6 -> 1 | AN2: Periodo (años) | AO2: Argentina | AP2: Brazil | AQ2: Chile | AR2: Colombia | AS2: Ecuador | AT2: Mexico | AU2: Peru | AV2: United States | AX2: Horizonte del proyecto (en años) | AY2: =WACC!$C$6 -> 1 | BA2: Periodo (años) | BB2: Argentina | BC2: Brazil | BD2: Chile | BE2: Colombia | BF2: Ecuador | BG2: Mexico | BH2: Peru | BI2: United States | BK2: Horizonte del proyecto (en años) | BL2: =WACC!$C$6 -> 1
B3: 1 | C3: 2 | D3: 3 | E3: 4 | F3: 5 | G3: 6 | H3: 7 | I3: 8 | O3: 1 | P3: 2 | Q3: 3 | R3: 4 | S3: 5 | T3: 6 | U3: 7 | V3: 8 | AB3: 1 | AC3: 2 | AD3: 3 | AE3: 4 | AF3: 5 | AG3: 6 | AH3: 7 | AI3: 8 | AO3: 1 | AP3: 2 | AQ3: 3 | AR3: 4 | AS3: 5 | AT3: 6 | AU3: 7 | AV3: 8 | BB3: 1 | BC3: 2 | BD3: 3 | BE3: 4 | BF3: 5 | BG3: 6 | BH3: 7 | BI3: 8
A4: 0 | H4: 0.021662294 | I4: 0 | K4: País | L4: =WACC!$F$6 -> Peru | N4: 0 | U4: 0.024774919 | V4: 0 | X4: País | Y4: =WACC!$F$6 -> Peru | AA4: 0 | AH4: 0.0098310077 | AI4: 0 | AK4: País | AL4: =WACC!$F$6 -> Peru | AN4: 0 | AP4: 0 | AQ4: 0 | AR4: 0 | AT4: 0 | AU4: -0.001 | AV4: 0 | AX4: País | AY4: =WACC!$F$6 -> Peru | BA4: 0 | BH4: 0.0029292816 | BI4: 0 | BK4: País | BL4: =WACC!$F$6 -> Peru
A5: 0.24657534 | H5: 0.022852124 | I5: 0 | N5: 0.24657534 | U5: 0.021018341 | V5: 0 | AA5: 0.24657534 | AH5: 0.0053781541 | AI5: 0 | AN5: 0.24657534 | AP5: 0.0384 | AQ5: 0.008 | AR5: 0.0145 | AT5: 0.0626 | AU5: -0.0027 | AV5: 0 | BA5: 0.24657534 | BH5: 0.00060164759 | BI5: 0
A6: 0.49315068 | H6: 0.023929123 | I6: 0 | K6: Código | L6: =HLOOKUP(L4,B2:I3,2) -> 7 | N6: 0.49315068 | U6: 0.018361111 | V6: 0 | X6: Código | Y6: =HLOOKUP(Y4,O2:V3,2) -> 7 | AA6: 0.49315068 | AH6: 0.0025582539 | AI6: 0 | AK6: Código | AL6: =HLOOKUP(AL4,AB2:AI3,2) -> 7 | AN6: 0.49315068 | AP6: 0.0414 | AQ6: 0.0067 | AR6: 0.0169 | AT6: 0.0616 | AU6: -0.0037 | AV6: 0 | AX6: Código | AY6: =HLOOKUP(AY4,AO2:AV3,2) -> 7 | BA6: 0.49315068 | BH6: -0.0011902241 | BI6: 0 | BK6: Código | BL6: =HLOOKUP(BL4,BB2:BI3,2) -> 7
A7: 0.73972603 | H7: 0.024902279 | I7: 0 | N7: 0.73972603 | U7: 0.016535071 | V7: 0 | AA7: 0.73972603 | AH7: 0.00091154423 | AI7: 0 | AN7: 0.73972603 | AP7: 0.044 | AQ7: 0.0056 | AR7: 0.0189 | AT7: 0.0607 | AU7: -0.0043 | AV7: 0 | BA7: 0.73972603 | BH7: -0.002533899 | BI7: 0
A8: 0.98630137 | H8: 0.025779944 | I8: 0 | K8: Devaluación | L8: {=+IF(L$2="0.25 (3 m)",INDEX($B$4:$I$144,MATCH(0.25,$A$4:$A$144,1),HLOOKUP(L4,B2:I3,2)),IF(L$2="0.5 (6 m)",INDEX($B$4:$I$144,MATCH(0.5,$A$4:$A$144,1),HLOOKUP(L4,B2:I3,2)),INDEX($B$4:$I$144,MATCH(L2,$A$4:$A$144,1),HLOOKUP(L4,B2:I3,2))))} | N8: 0.98630137 | U8: 0.015334342 | V8: 0 | X8: Devaluación | Y8: {=+IF(Y$2="0.25 (3 m)",INDEX($O$4:$V$144,MATCH(0.25,$N$4:$N$144,1),HLOOKUP(Y4,O2:V3,2)),IF(Y$2="0.5 (6 m)",INDEX($O$4:$V$144,MATCH(0.5,$N$4:$N$144,1),HLOOKUP(Y4,O2:V3,2)),INDEX($O$4:$V$144,MATCH(Y2,$N$4:$N$144,1),HLOOKUP(Y4,O2:V3,2))))} | AA8: 0.98630137 | AH8: 0.00010161783 | AI8: 0 | AK8: Devaluación | AL8: {=+IF(AL$2="0.25 (3 m)",INDEX($AB$4:$AI$144,MATCH(0.25,$AA$4:$AA$144,1),HLOOKUP(AL4,AB2:AI3,2)),IF(AL$2="0.5 (6 m)",INDEX($AB$4:$AI$144,MATCH(0.5,$AA$4:$AA$144,1),HLOOKUP(AL4,AB2:AI3,2)),INDEX($AB$4:$AI$144,MATCH(AL2,$AA$4:$AA$144,1),HLOOKUP(AL4,AB2:AI3,2))))} | AN8: 0.98630137 | AP8: 0.0464 | AQ8: 0.0047 | AR8: 0.0206 | AT8: 0.06 | AU8: -0.0045 | AV8: 0 | AX8: Devaluación | AY8: {=+IF(AY$2="0.25 (3 m)",INDEX($AO$4:$AV$144,MATCH(0.25,$AN$4:$AN$144,1),HLOOKUP(AY4,AO2:AV3,2)),IF(AY$2="0.5 (6 m)",INDEX($AO$4:$AV$144,MATCH(0.5,$AN$4:$AN$144,1),HLOOKUP(AY4,AO2:AV3,2)),INDEX($AO$4:$AV$144,MATCH(AY2,$AN$4:$AN$144,1),HLOOKUP(AY4,AO2:AV3,2))))} | BA8: 0.98630137 | BH8: -0.0035034675 | BI8: 0 | BK8: Devaluación | BL8: {=+IF(BL$2="0.25 (3 m)",INDEX($AO$4:$AV$144,MATCH(0.25,$AN$4:$AN$144,1),HLOOKUP(BL4,BB2:BI3,2)),IF(BL$2="0.5 (6 m)",INDEX($AO$4:$AV$144,MATCH(0.5,$AN$4:$AN$144,1),HLOOKUP(BL4,BB2:BI3,2)),INDEX($AO$4:$AV$144,MATCH(BL2,$AN$4:$AN$144,1),HLOOKUP(BL4,BB2:BI3,2))))}
A9: 1.2328767 | H9: 0.026569862 | I9: 0 | N9: 1.2328767 | U9: 0.014600745 | V9: 0 | AA9: 1.2328767 | AH9: -0.00011796596 | AI9: 0 | AN9: 1.2328767 | AP9: 0.0485 | AQ9: 0.0039 | AR9: 0.0221 | AT9: 0.0594 | AU9: -0.0044 | AV9: 0 | BA9: 1.2328767 | BH9: -0.0041616751 | BI9: 0
A10: 1.4794521 | H10: 0.027279223 | I10: 0 | N10: 1.4794521 | U10: 0.014212776 | V10: 0 | AA10: 1.4794521 | AH10: 7.2366445e-05 | AI10: 0 | AN10: 1.4794521 | AP10: 0.0503 | AQ10: 0.0032 | AR10: 0.0232 | AT10: 0.0588 | AU10: -0.0041 | AV10: 0 | BA10: 1.4794521 | BH10: -0.0045616818 | BI10: 0
A11: 1.7260274 | H11: 0.027914685 | I11: 0 | N11: 1.7260274 | U11: 0.014077237 | V11: 0 | AA11: 1.7260274 | AH11: 0.00054081905 | AI11: 0 | AN11: 1.7260274 | AP11: 0.052 | AQ11: 0.0027 | AR11: 0.0242 | AT11: 0.0583 | AU11: -0.0036 | AV11: 0 | BA11: 1.7260274 | BH11: -0.0047485367 | BI11: 0
A12: 1.9726027 | H12: 0.028482423 | I12: 0 | N12: 1.9726027 | U12: 0.014122798 | V12: 0 | AA12: 1.9726027 | AH12: 0.0011914957 | AI12: 0 | AN12: 1.9726027 | AP12: 0.0535 | AQ12: 0.0023 | AR12: 0.025 | AT12: 0.0579 | AU12: -0.0031 | AV12: 0 | BA12: 1.9726027 | BH12: -0.0047604097 | BI12: 0
A13: 2.2191781 | H13: 0.028988151 | I13: 0 | K13: 2021 | L13: =$L$8 -> 0.025779944 | N13: 2.2191781 | U13: 0.01429506 | V13: 0 | AA13: 2.2191781 | AH13: 0.0019550319 | AI13: 0 | AN13: 2.2191781 | AP13: 0.0548 | AQ13: 0.0021 | AR13: 0.0256 | AT13: 0.0575 | AU13: -0.0024 | AV13: 0 | BA13: 2.2191781 | BH13: -0.0046296256 | BI13: 0
A14: 2.4657534 | H14: 0.029437158 | I14: 0 | K14: 2022 | L14: =$Y$8 -> 0.015334342 | N14: 2.4657534 | U14: 0.014552729 | V14: 0 | AA14: 2.4657534 | AH14: 0.0027816439 | AI14: 0 | AN14: 2.4657534 | AP14: 0.0559 | AQ14: 0.0018 | AR14: 0.0261 | AT14: 0.0572 | AU14: -0.0017 | AV14: 0 | BA14: 2.4657534 | BH14: -0.00438354 | BI14: 0
A15: 2.7123288 | H15: 0.029834341 | I15: 0 | K15: 2023 | L15: =+$AL$8 -> 0.00010161783 | N15: 2.7123288 | U15: 0.014864643 | V15: 0 | AA15: 2.7123288 | AH15: 0.0036359901 | AI15: 0 | AN15: 2.7123288 | AP15: 0.057 | AQ15: 0.0017 | AR15: 0.0265 | AT15: 0.0568 | AU15: -0.001 | AV15: 0 | BA15: 2.7123288 | BH15: -0.0040452741 | BI15: 0
A16: 2.9589041 | H16: 0.030184222 | I16: 0 | K16: 2024 | L16: =+$AY$8 -> -0.0045 | N16: 2.9589041 | U16: 0.015207474 | V16: 0 | AA16: 2.9589041 | AH16: 0.0044933407 | AI16: 0 | AN16: 2.9589041 | AP16: 0.0579 | AQ16: 0.0016 | AR16: 0.0268 | AT16: 0.0565 | AU16: -0.0002 | AV16: 0 | BA16: 2.9589041 | BH16: -0.0036343456 | BI16: 0
A17: 3.2054795 | H17: 0.030490987 | I17: 0 | K17: 2025 | L17: =+$BL$8 -> -0.0045 | N17: 3.2054795 | U17: 0.015563931 | V17: 0 | AA17: 3.2054795 | AH17: 0.005336736 | AI17: 0 | AN17: 3.2054795 | AP17: 0.0587 | AQ17: 0.0016 | AR17: 0.027 | AT17: 0.0562 | AU17: 0.0006 | AV17: 0 | BA17: 3.2054795 | BH17: -0.0031671994 | BI17: 0
A18: 3.4520548 | H18: 0.030758502 | I18: 0 | K18: 2026 | N18: 3.4520548 | U18: 0.01592137 | V18: 0 | AA18: 3.4520548 | AH18: 0.0061548732 | AI18: 0 | AN18: 3.4520548 | AP18: 0.0594 | AQ18: 0.0017 | AR18: 0.0271 | AT18: 0.056 | AU18: 0.0013 | AV18: 0 | BA18: 3.4520548 | BH18: -0.0026576619 | BI18: 0
A19: 3.6986301 | H19: 0.030990333 | I19: 0 | K19: 2027 | N19: 3.6986301 | U19: 0.016270709 | V19: 0 | AA19: 3.6986301 | AH19: 0.006940543 | AI19: 0 | AN19: 3.6986301 | AP19: 0.06 | AQ19: 0.0018 | AR19: 0.0272 | AT19: 0.0557 | AU19: 0.002 | AV19: 0 | BA19: 3.6986301 | BH19: -0.0021173241 | BI19: 0
A20: 3.9452055 | H20: 0.031189778 | I20: 0 | K20: 2028 | N20: 3.9452055 | U20: 0.016605585 | V20: 0 | AA20: 3.9452055 | AH20: 0.0076894714 | AI20: 0 | AN20: 3.9452055 | AP20: 0.0606 | AQ20: 0.0019 | AR20: 0.0273 | AT20: 0.0554 | AU20: 0.0027 | AV20: 0 | BA20: 3.9452055 | BH20: -0.0015558765 | BI20: 0
A21: 4.1917808 | H21: 0.031359876 | I21: 0 | K21: 2029 | N21: 4.1917808 | U21: 0.016921696 | V21: 0 | AA21: 4.1917808 | AH21: 0.0083994613 | AI21: 0 | AN21: 4.1917808 | AP21: 0.061 | AQ21: 0.002 | AR21: 0.0273 | AT21: 0.0552 | AU21: 0.0034 | AV21: 0 | BA21: 4.1917808 | BH21: -0.00098138602 | BI21: 0
A22: 4.4383562 | H22: 0.031503433 | I22: 0 | K22: 2030 | N22: 4.4383562 | U22: 0.017216302 | V22: 0 | AA22: 4.4383562 | AH22: 0.0090697688 | AI22: 0 | AN22: 4.4383562 | AP22: 0.0615 | AQ22: 0.0022 | AR22: 0.0272 | AT22: 0.0549 | AU22: 0.0041 | AV22: 0 | BA22: 4.4383562 | BH22: -0.00040054421 | BI22: 0
A23: 4.6849315 | H23: 0.031623031 | I23: 0 | N23: 4.6849315 | U23: 0.017487828 | V23: 0 | AA23: 4.6849315 | AH23: 0.009700642 | AI23: 0 | AN23: 4.6849315 | AP23: 0.0618 | AQ23: 0.0024 | AR23: 0.0272 | AT23: 0.0546 | AU23: 0.0047 | AV23: 0 | BA23: 4.6849315 | BH23: 0.00018113349 | BI23: 0
A24: 4.9315068 | H24: 0.031721057 | I24: 0 | N24: 4.9315068 | U24: 0.01773556 | V24: 0 | AA24: 4.9315068 | AH24: 0.010292991 | AI24: 0 | AN24: 4.9315068 | AP24: 0.0622 | AQ24: 0.0026 | AR24: 0.0271 | AT24: 0.0544 | AU24: 0.0053 | AV24: 0 | BA24: 4.9315068 | BH24: 0.00075913112 | BI24: 0
A25: 5.1780822 | H25: 0.031799701 | I25: 0 | N25: 5.1780822 | U25: 0.017959417 | V25: 0 | AA25: 5.1780822 | AH25: 0.010848143 | AI25: 0 | AN25: 5.1780822 | AP25: 0.0625 | AQ25: 0.0029 | AR25: 0.027 | AT25: 0.0541 | AU25: 0.0058 | AV25: 0 | BA25: 5.1780822 | BH25: 0.0013297734 | BI25: 0
A26: 5.4246575 | H26: 0.031860986 | I26: 0 | N26: 5.4246575 | U26: 0.018159769 | V26: 0 | AA26: 5.4246575 | AH26: 0.011367671 | AI26: 0 | AN26: 5.4246575 | AP26: 0.0627 | AQ26: 0.0031 | AR26: 0.0269 | AT26: 0.0539 | AU26: 0.0064 | AV26: 0 | BA26: 5.4246575 | BH26: 0.0018901082 | BI26: 0
A27: 5.6712329 | H27: 0.03190677 | I27: 0 | N27: 5.6712329 | U27: 0.018337307 | V27: 0 | AA27: 5.6712329 | AH27: 0.011853284 | AI27: 0 | AN27: 5.6712329 | AP27: 0.0629 | AQ27: 0.0034 | AR27: 0.0268 | AT27: 0.0536 | AU27: 0.0069 | AV27: 0 | BA27: 5.6712329 | BH27: 0.0024377851 | BI27: 0
A28: 5.9178082 | H28: 0.031938763 | I28: 0 | N28: 5.9178082 | U28: 0.018492931 | V28: 0 | AA28: 5.9178082 | AH28: 0.012306725 | AI28: 0 | AN28: 5.9178082 | AP28: 0.0631 | AQ28: 0.0037 | AR28: 0.0267 | AT28: 0.0534 | AU28: 0.0073 | AV28: 0 | BA28: 5.9178082 | BH28: 0.002970967 | BI28: 0
A29: 6.1643836 | H29: 0.031958536 | I29: 0 | N29: 6.1643836 | U29: 0.018627683 | V29: 0 | AA29: 6.1643836 | AH29: 0.012729729 | AI29: 0 | AN29: 6.1643836 | AP29: 0.0633 | AQ29: 0.0039 | AR29: 0.0265 | AT29: 0.0531 | AU29: 0.0078 | AV29: 0 | BA29: 6.1643836 | BH29: 0.0034882486 | BI29: 0
A30: 6.4109589 | H30: 0.031967533 | I30: 0 | N30: 6.4109589 | U30: 0.018742684 | V30: 0 | AA30: 6.4109589 | AH30: 0.01312398 | AI30: 0 | AN30: 6.4109589 | AP30: 0.0635 | AQ30: 0.0042 | AR30: 0.0264 | AT30: 0.0528 | AU30: 0.0082 | AV30: 0 | BA30: 6.4109589 | BH30: 0.0039885864 | BI30: 0
A31: 6.6575342 | H31: 0.031967079 | I31: 0 | N31: 6.6575342 | U31: 0.018839088 | V31: 0 | AA31: 6.6575342 | AH31: 0.013491089 | AI31: 0 | AN31: 6.6575342 | AP31: 0.0636 | AQ31: 0.0045 | AR31: 0.0263 | AT31: 0.0526 | AU31: 0.0085 | AV31: 0 | BA31: 6.6575342 | BH31: 0.0044712397 | BI31: 0
A32: 6.9041096 | H32: 0.03195839 | I32: 0 | N32: 6.9041096 | U32: 0.018918058 | V32: 0 | AA32: 6.9041096 | AH32: 0.013832578 | AI32: 0 | AN32: 6.9041096 | AP32: 0.0637 | AQ32: 0.0048 | AR32: 0.0262 | AT32: 0.0523 | AU32: 0.0089 | AV32: 0 | BA32: 6.9041096 | BH32: 0.0049357219 | BI32: 0
A33: 7.1506849 | H33: 0.031942581 | I33: 0 | N33: 7.1506849 | U33: 0.018980741 | V33: 0 | AA33: 7.1506849 | AH33: 0.014149878 | AI33: 0 | AN33: 7.1506849 | AP33: 0.0638 | AQ33: 0.005 | AR33: 0.0261 | AT33: 0.0521 | AU33: 0.0092 | AV33: 0 | BA33: 7.1506849 | BH33: 0.0053817537 | BI33: 0
A34: 7.3972603 | H34: 0.031920672 | I34: 0 | N34: 7.3972603 | U34: 0.01902825 | V34: 0 | AA34: 7.3972603 | AH34: 0.014444326 | AI34: 0 | AN34: 7.3972603 | AP34: 0.0639 | AQ34: 0.0053 | AR34: 0.0259 | AT34: 0.0518 | AU34: 0.0095 | AV34: 0 | BA34: 7.3972603 | BH34: 0.0058092319 | BI34: 0
... A163: 39.205479 | H163: 0.07235988 | I163: 0 | N163: 39.205479 | U163: 0.079338965 | V163: 0 | AA163: 39.205479 | AH163: 0.070211494 | AI163: 0 | AN163: 39.205479 | AP163: 0.0452 | AQ163: 0.0068 | AR163: 0.0211 | AT163: 0.041 | AU163: 0.0665 | AV163: 0 | BA163: 39.205479 | BH163: 0.0070164918 | BI163: 0
A164: 39.452055 | H164: 0.072378421 | I164: 0 | N164: 39.452055 | U164: 0.079313489 | V164: 0 | AA164: 39.452055 | AH164: 0.070213284 | AI164: 0 | AN164: 39.452055 | AU164: 0.0664 | AV164: 0 | BA164: 39.452055 | BH164: 0.0069108015 | BI164: 0

Sheet Rf Ajustado
A2: TIR | B2: =IRR(E3:DU3) -> 0.079308265 | D2: Periodo | E2: 0 | F2: 1 | G2: 2 | H2: 3 | I2: 4 | J2: 5 | K2: 6 | L2: 7 | M2: 8 | N2: 9 | O2: 10 | P2: 11 | Q2: 12 | R2: 13 | S2: 14 | T2: 15 | U2: 16 | V2: 17 | W2: 18 | X2: 19 | Y2: 20 | Z2: 21 | AA2: 22 | AB2: 23 | AC2: 24 | AD2: 25 | AE2: 26 | AF2: 27 | AG2: 28 | AH2: 29 | AI2: 30 | AJ2: 31 | AK2: 32 | AL2: 33 | AM2: 34 | AN2: 35 | AO2: 36 | AP2: 37 | AQ2: 38 | AR2: 39 | AS2: 40 | AT2: 41 | AU2: 42 | AV2: 43 | AW2: 44 | AX2: 45 | AY2: 46 | AZ2: 47 | BA2: 48 | BB2: 49 | BC2: 50 | BD2: 51 | BE2: 52 | BF2: 53 | BG2: 54 | BH2: 55 | BI2: 56 | BJ2: 57 | BK2: 58 | BL2: 59 | BM2: 60 | BN2: 61 | BO2: 62 | BP2: 63 | BQ2: 64 | BR2: 65 | BS2: 66 | BT2: 67 | BU2: 68 | BV2: 69 | BW2: 70 | BX2: 71 | BY2: 72 | BZ2: 73 | CA2: 74 | CB2: 75 | CC2: 76 | CD2: 77 | CE2: 78 | CF2: 79 | CG2: 80 | CH2: 81 | CI2: 82 | CJ2: 83 | CK2: 84 | CL2: 85 | CM2: 86 | CN2: 87 | CO2: 88 | CP2: 89 | CQ2: 90 | CR2: 91 | CS2: 92 | CT2: 93 | CU2: 94 | CV2: 95 | CW2: 96 | CX2: 97 | CY2: 98 | CZ2: 99 | DA2: 100 | DB2: 101 | DC2: 102 | DD2: 103 | DE2: 104 | DF2: 105 | DG2: 106 | DH2: 107 | DI2: 108 | DJ2: 109 | DK2: 110 | DL2: 111 | DM2: 112 | DN2: 113 | DO2: 114 | DP2: 115 | DQ2: 116 | DR2: 117 | DS2: 118 | DT2: 119 | DU2: 120
A3: Número de periodos | B3: =Flujos!C6 -> 5 | D3: Flujo de caja para TIR | E3: =-B6 -> -2000 | F3: =F4 -> 500 | G3: =G4 -> 500 | H3: =H4 -> 500 | I3: =I4 -> 500 | J3: =J4 -> 500 | K3: =K4 | L3: =L4 | M3: =M4 | ... DU3: =DU4
A4: Periodicidad | B4: =Flujos!C5 -> Anual | D4: Flujo de caja_O | E4: =Flujos!C11 | F4: =Flujos!D11 -> 500 | G4: =Flujos!E11 -> 500 | H4: =Flujos!F11 -> 500 | I4: =Flujos!G11 -> 500 | J4: =Flujos!H11 -> 500 | K4: =Flujos!I11 | L4: =Flujos!J11 | ... DU4: =Flujos!DS11
A5: VP(Flujo*t) | B5: =NPV(B2,F5:AI5) -> 5695.4865 | D5: Flujo*Periodo | F5: =F3*F2 -> 500 | G5: =G3*G2 -> 1000 | H5: =H3*H2 -> 1500 | I5: =I3*I2 -> 2000 | J5: =J3*J2 -> 2500 | K5: =K3*K2 -> 0 | L5: =L3*L2 -> 0 | M5: =M3*M2 -> 0 | ... DU5: =DU3*DU2 -> 0
A6: Valor actual de las inversiones | B6: =-(NPV(E8,F6:DU6)+E6) -> 2000 | D6: Flujo de inversiones | E6: =-Flujos!C12 -> -2000 | F6: =-Flujos!D12 -> #VALUE! | G6: =-Flujos!E12 -> #VALUE! | H6: =-Flujos!F12 -> #VALUE! | I6: =-Flujos!G12 -> #VALUE! | J6: =-Flujos!H12 -> #VALUE! | K6: =-Flujos!I12 -> #VALUE! | L6: =-Flujos!J12 -> #VALUE! | ... DU6: =-Flujos!DS12 -> #VALUE!
A7: Duration | B7: =B5/B6 -> 2.8477432 | D7: FFE | E7: =E4+E6 -> -2000 | F7: =F4+F6 -> #VALUE! | G7: =G4+G6 -> #VALUE! | H7: =H4+H6 -> #VALUE! | I7: =I4+I6 -> #VALUE! | J7: =J4+J6 -> #VALUE! | K7: =K4+K6 -> #VALUE! | L7: =L4+L6 -> #VALUE! | ... DU7: =DU4+DU6 -> #VALUE!
A8: Duaratio (Anual) | B8: =IF(B4="Trimestral",B7*1/4,IF(B4="Semestral",B7*1/2,B7)) -> 2.8477432 | D8: TIR FFE | E8: =IRR(E7:DU7) -> #VALUE!
A10: Elección de Rf en función de la duración
D11: Duration | E11: =B8 -> 2.8477432 | G11: X | H11: Y
B12: Date | D12: Rendimiento | E12: =((E11-G12)*H13+(G13-E11)*H12)/(G13-G12) -> 0.042669549 | G12: =INDEX($A$14:$B$25,MATCH(E11,$A$14:$A$25,1),1) -> 2 | H12: =VLOOKUP(G12,$A$14:$B$25,2,TRUE) -> 0.0425
A13: Curva de rendimiento (en años) | B13: =WACC!F3 -> 45838 | G13: =IF(INDEX($A$14:$B$25,MATCH(E11,$A$14:$A$25,1)+1,1,1)="0.25 (3 meses)",0.25,INDEX($A$14:$B$25,MATCH(E11,$A$14:$A$25,1)+1,1,1)) -> 3 | H13: =VLOOKUP(G13,$A$14:$B$25,2,TRUE) -> 0.0427
A14: =1/12 -> 0.083333333 | B14: =+_xlfn.XLOOKUP($B$13,'Rf Base de datos'!$A:$A,'Rf Base de datos'!B:B) -> 0.044
A15: =2/12 -> 0.16666667 | B15: =+_xlfn.XLOOKUP($B$13,'Rf Base de datos'!$A:$A,'Rf Base de datos'!C:C) -> 0.0439
A16: 0.25 (3 m) | B16: =+_xlfn.XLOOKUP($B$13,'Rf Base de datos'!$A:$A,'Rf Base de datos'!D:D) -> 0.0437
A17: 0.5 (6 m) | B17: =+_xlfn.XLOOKUP($B$13,'Rf Base de datos'!$A:$A,'Rf Base de datos'!E:E) -> 0.0424
A18: 1 | B18: =+_xlfn.XLOOKUP($B$13,'Rf Base de datos'!$A:$A,'Rf Base de datos'!F:F) -> 0.0416
A19: 2 | B19: =+_xlfn.XLOOKUP($B$13,'Rf Base de datos'!$A:$A,'Rf Base de datos'!G:G) -> 0.0425
A20: 3 | B20: =+_xlfn.XLOOKUP($B$13,'Rf Base de datos'!$A:$A,'Rf Base de datos'!H:H) -> 0.0427
A21: 5 | B21: =+_xlfn.XLOOKUP($B$13,'Rf Base de datos'!$A:$A,'Rf Base de datos'!I:I) -> 0.0438
A22: 7 | B22: =+_xlfn.XLOOKUP($B$13,'Rf Base de datos'!$A:$A,'Rf Base de datos'!J:J) -> 0.0448
A23: 10 | B23: =+_xlfn.XLOOKUP($B$13,'Rf Base de datos'!$A:$A,'Rf Base de datos'!K:K) -> 0.0458
A24: 20 | B24: =+_xlfn.XLOOKUP($B$13,'Rf Base de datos'!$A:$A,'Rf Base de datos'!L:L) -> 0.0486
A25: 30 | B25: =+_xlfn.XLOOKUP($B$13,'Rf Base de datos'!$A:$A,'Rf Base de datos'!M:M) -> 0.0478
A27: Rf seleccionado | B27: =B8 -> 2.8477432

Sheet Rf Base de datos
B1: =1/12 -> 0.083333333 | C1: =2/12 -> 0.16666667 | D1: 0.25 | E1: 0.5 | F1: 1 | G1: 2 | H1: 3 | I1: 5 | J1: 7 | K1: 10 | L1: 20 | M1: 30
A2: 45838 | B2: 0.0428 | C2: 0.0445 | D2: 0.0441 | E2: 0.0429 | F2: 0.0396 | G2: 0.0372 | H2: 0.0368 | I2: 0.0379 | J2: 0.0398 | K2: 0.0424 | L2: 0.0479 | M2: 0.0478
A3: 45747 | B3: 0.0438 | C3: 0.0435 | D3: 0.0432 | E3: 0.0423 | F3: 0.0403 | G3: 0.0389 | H3: 0.0389 | I3: 0.0396 | J3: 0.0409 | K3: 0.0423 | L3: 0.0462 | M3: 0.0459
A4: 45657 | B4: 0.044 | C4: 0.0439 | D4: 0.0437 | E4: 0.0424 | F4: 0.0416 | G4: 0.0425 | H4: 0.0427 | I4: 0.0438 | J4: 0.0448 | K4: 0.0458 | L4: 0.0486 | M4: 0.0478
A5: 45565 | B5: 0.0493 | C5: 0.0487 | D5: 0.0473 | E5: 0.0438 | F5: 0.0398 | G5: 0.0366 | H5: 0.0358 | I5: 0.0358 | J5: 0.0367 | K5: 0.0381 | L5: 0.0419 | M5: 0.0414
A6: 45473 | B6: 0.0547 | C6: 0.0547 | D6: 0.0548 | E6: 0.0533 | F6: 0.0509 | G6: 0.0471 | H6: 0.0452 | I6: 0.0433 | J6: 0.0433 | K6: 0.0436 | L6: 0.0461 | M6: 0.0451
A7: 45382 | B7: 0.0549 | C7: 0.0548 | D7: 0.0546 | E7: 0.0538 | F7: 0.0503 | G7: 0.0459 | H7: 0.044 | I7: 0.0421 | J7: 0.042 | K7: 0.042 | L7: 0.0445 | M7: 0.0434
A8: 45291 | B8: 0.056 | C8: 0.0559 | D8: 0.054 | E8: 0.054 | F8: 0.0526 | G8: 0.0479 | H8: 0.0423 | I8: 0.0401 | J8: 0.0384 | K8: 0.0388 | L8: 0.0388 | M8: 0.042
A9: 45199 | B9: 0.0555 | C9: 0.056 | D9: 0.0555 | E9: 0.0553 | F9: 0.0546 | G9: 0.0503 | H9: 0.048 | I9: 0.046 | J9: 0.0461 | K9: 0.0459 | L9: 0.0492 | M9: 0.0473
A10: 45107 | B10: 0.0524 | C10: 0.0539 | D10: 0.0543 | E10: 0.0547 | F10: 0.054 | G10: 0.0487 | H10: 0.0449 | I10: 0.0413 | J10: 0.0397 | K10: 0.0381 | L10: 0.0406 | M10: 0.0385
A11: 45016 | B11: 0.0474 | C11: 0.0479 | D11: 0.0485 | E11: 0.0494 | F11: 0.0494 | G11: 0.0464 | H11: 0.0406 | I11: 0.0381 | J11: 0.036 | K11: 0.0355 | L11: 0.0348 | M11: 0.0381
A12: 44926 | B12: 0.0017 | C12: 0.0035 | D12: 0.0052 | E12: 0.0106 | F12: 0.0163 | G12: 0.0228 | H12: 0.0245 | I12: 0.0242 | J12: 0.024 | K12: 0.0232 | L12: 0.0259 | M12: 0.0244
A13: 44834 | B13: 0.0279 | C13: 0.032 | D13: 0.0333 | E13: 0.0392 | F13: 0.0405 | G13: 0.0422 | H13: 0.0425 | I13: 0.0406 | J13: 0.0397 | K13: 0.0383 | L13: 0.0408 | M13: 0.0379
... A19: 44286 | B19: 0.0001 | C19: 0.0001 | D19: 0.0003 | E19: 0.0005 | F19: 0.0007 | G19: 0.0016 | H19: 0.0035 | I19: 0.0092 | J19: 0.014 | K19: 0.0174 | L19: 0.0231 | M19: 0.0241

Sheet Embi
A1: Fecha | B1: Argentina | C1: Brazil | D1: Chile | E1: Colombia | F1: Ecuador | G1: Mexico | H1: Peru | I1: United States | M1: Fecha
A2: 45838 | H2: 163.32847 | M2: =+WACC!$F$3 -> 45838
A3: 45747 | H3: 159.45558 | L3: Argentina | M3: =+_xlfn.XLOOKUP($M$2,$A:$A,B:B) -> 693.38095
A4: 45657 | B4: 693.38095 | C4: 232.04762 | D4: 118.14286 | E4: 322.90476 | F4: 1204.2381 | G4: 313.14286 | H4: 154.38095 | L4: Brazil | M4: =+_xlfn.XLOOKUP($M$2,$A:$A,C:C) -> 232.04762
A5: 45565 | B5: 1372.1053 | C5: 219.84211 | D5: 127.31579 | E5: 322.94737 | F5: 1207.8421 | G5: 329.57895 | H5: 162.57895 | L5: Chile | M5: =+_xlfn.XLOOKUP($M$2,$A:$A,D:D) -> 118.14286
A6: 45473 | B6: 1452.15 | C6: 217 | D6: 125.15 | E6: 313.05 | F6: 1368.65 | G6: 315.75 | H6: 160.9 | L6: Colombia | M6: =+_xlfn.XLOOKUP($M$2,$A:$A,E:E) -> 322.90476
A7: 45382 | B7: 1552.1429 | C7: 202.85714 | D7: 130.42857 | E7: 295.57143 | F7: 1257.2857 | G7: 324.14286 | H7: 152.66667 | L7: Ecuador | M7: =+_xlfn.XLOOKUP($M$2,$A:$A,F:F) -> 1204.2381
A8: 45291 | B8: 1887.4762 | C8: 199.90476 | D8: 134.52381 | E8: 290.57143 | F8: 2069.3333 | G8: 351.52381 | H8: 162.42857 | L8: Mexico | M8: =+_xlfn.XLOOKUP($M$2,$A:$A,G:G) -> 313.14286
A9: 45199 | B9: 2239.8095 | C9: 209.71429 | D9: 131.80952 | E9: 328.95238 | F9: 1780.1905 | G9: 367.90476 | H9: 169.09524 | L9: Peru | M9: =+_xlfn.XLOOKUP($M$2,$A:$A,H:H) -> 154.38095
A10: 45107 | B10: 2301.8636 | C10: 233.31818 | D10: 135.68182 | E10: 366.59091 | F10: 1875.0909 | G10: 386.86364 | H10: 181.09091 | L10: United States | M10: =+_xlfn.XLOOKUP($M$2,$A:$A,I:I) -> 0
A11: 45016 | B11: 2294.7391 | C11: 258.34783 | D11: 152 | E11: 411.6087 | F11: 1807.6957 | G11: 400.69565 | H11: 203.82609 | I11: 0
A12: 44926 | B12: 1819 | C12: 303 | D12: 179 | E12: 364 | F12: 793 | G12: 373 | H12: 201 | I12: 0
A13: 44834 | B13: 2449 | C13: 287 | D13: 194 | E13: 424 | F13: 1549 | G13: 444 | H13: 225 | I13: 0
A14: 44742 | B14: 2153 | C14: 323 | D14: 179 | E14: 389 | F14: 970 | G14: 428 | H14: 214 | I14: 0
A15: 44651 | B15: 1819 | C15: 303 | D15: 179 | E15: 364 | F15: 793 | G15: 373 | H15: 201 | I15: 0
A16: 44561 | B16: 1730 | C16: 316 | D16: 155 | E16: 347 | F16: 867 | G16: 358 | H16: 174 | I16: 0
A17: 44469 | B17: 1541.0909 | C17: 292.04545 | D17: 141.09091 | E17: 281.77273 | F17: 798.5 | G17: 350.54545 | H17: 174 | I17: 0
A18: 44377 | B18: 1513.3182 | C18: 247.45455 | D18: 139.31818 | E18: 243.54545 | F18: 757.63636 | G18: 337.63636 | H18: 169.22727 | I18: 0
A19: 44286 | B19: 1565.9565 | C19: 281.3913 | D19: 132.91304 | E19: 223.30435 | F19: 1260.8261 | G19: 356.04348 | H19: 165.08696

Sheet Koa-Boa
B1: 2020 | D1: 2021 | F1: 2022 | H1: 2023 | J1: 2024
A2: Industry Name | B2: Koa | C2: Boa | D2: Koa | E2: Boa | F2: Koa | G2: Boa | H2: Koa | I2: Boa | J2: Koa | K2: Boa
A3: Publicidad | B3: 0.022621378 | C3: 0.14337127 | D3: 0.080486733 | E3: 0.97434886 | F3: 0.10700249 | G3: 1.1481902 | H3: 0.095962814 | I3: 1.2200667 | J3: 0.11326029 | K3: 1.095027
A4: Aeroespacial/ Defensa | B4: 0.038483583 | C4: 0.37973912 | D4: 0.08585645 | E4: 1.0543648 | F4: 0.10664485 | G4: 1.1421691 | H4: 0.093441789 | I4: 1.182992 | J4: 0.10025946 | K4: 0.90383432
A5: Transporte aéreo | B5: 0.040523106 | C5: 0.4101307 | D5: 0.065222712 | E5: 0.74689475 | F5: 0.070322286 | G5: 0.53067822 | H5: 0.053159881 | I5: 0.59059874 | J5: 0.077671032 | K5: 0.57164469
A6: Confección de ropa | B6: 0.041490501 | C6: 0.42454617 | D6: 0.081986197 | E6: 0.99669285 | F6: 0.092931023 | G6: 0.91129668 | H6: 0.077953874 | I6: 0.95522385 | J6: 0.098283633 | K6: 0.87477747
A7: Automóviles y Camiones | B7: 0.042238429 | C7: 0.43569129 | D7: 0.081288896 | E7: 0.98630215 | F7: 0.10034658 | G7: 1.0361376 | H7: 0.089108692 | I7: 1.1192687 | J7: 0.1227816 | K7: 1.2350491
A8: Partes de Automóviles | B8: 0.045127388 | C8: 0.47874061 | D8: 0.091301102 | E8: 1.1354973 | F8: 0.10193014 | G8: 1.062797 | H8: 0.088936195 | I8: 1.1167319 | J8: 0.10976126 | K8: 1.0435695
A9: Bebida alcohólicas | B9: 0.045244289 | C9: 0.48048258 | D9: 0.0626519 | E9: 0.70858625 | F9: 0.088627645 | G9: 0.83884925 | H9: 0.071780924 | I9: 0.86444329 | J9: 0.1038309 | K9: 0.95635661
A10: Bebidas sin alcohol | B10: 0.045850474 | C10: 0.48951554 | D10: 0.087842501 | E10: 1.0839595 | F10: 0.10654433 | G10: 1.140477 | H10: 0.092525246 | I10: 1.1695132 | J10: 0.08484896 | K10: 0.67720464
A11: Radiofusión | B11: 0.04666901 | C11: 0.50171281 | D11: 0.064072617 | E11: 0.72975681 | F11: 0.073907282 | G11: 0.59103168 | H11: 0.055783355 | I11: 0.62918005 | J11: 0.069855066 | K11: 0.45670163
A12: Corretaje e inversión bancaria | B12: 0.047410156 | C12: 0.51275687 | D12: 0.04891066 | E12: 0.50382358 | F12: 0.065277485 | G12: 0.4457489 | H12: 0.045663461 | I12: 0.48035498 | J12: 0.067062692 | K12: 0.41563645
A13: Materiales de construcción | B13: 0.047935749 | C13: 0.5205889 | D13: 0.085176308 | E13: 1.0442297 | F13: 0.099939545 | G13: 1.0292853 | H13: 0.084369809 | I13: 1.0495778 | J13: 0.1176725 | K13: 1.1599138
A14: Servicios para empresas y consumidores | B14: 0.048279465 | C14: 0.52571072 | D14: 0.077924897 | E14: 0.93617412 | F14: 0.094493782 | G14: 0.93760576 | H14: 0.07901772 | I14: 0.97086897 | J14: 0.10005936 | K14: 0.90089162
... A95: Mercado Total (sin el sector financiero) | B95: 0.10458087 | C95: 1.3646761 | D95: 0.082361549 | E95: 1.0022861 | F95: 0.10037585 | G95: 1.0366305 | H95: 0.086380932 | I95: 1.0791537 | J95: 0.10261363 | K95: 0.93845524

Sheet Prima de mercado
B2: PRM (T-bonds) actual | C2: Rm | D2: Rf (t-bonds)
A3: 2021 | B3: 0.067108133 | C3: 0.11821279 | D3: 0.051104658
A4: 2022 | B4: 0.066375604 | C4: 0.11506541 | D4: 0.048689804
A5: 2023 | B5: 0.067998589 | C5: 0.11658544 | D5: 0.048586853
A6: 2024 | B6: 0.066379627 | C6: 0.1150695 | D6: 0.048689872

Sheet IR
A1: Country | B1: 2015 | C1: 2016 | D1: 2017 | E1: 2018 | F1: 2019 | G1: 2020 | H1: 2021 | I1: 2022 | J1: 2023 | K1: 2024 | L1: 2025
A2: Afghanistan | B2: 0.2 | C2: 0.2 | D2: 0.2 | E2: 0.2 | F2: 0.2 | G2: 0.2 | H2: 0.2 | I2: 0.2 | J2: 0.2 | K2: 0.2 | L2: 0.2
A3: Albania | B3: 0.15 | C3: 0.15 | D3: 0.15 | E3: 0.15 | F3: 0.15 | G3: 0.15 | H3: 0.15 | I3: 0.15 | J3: 0.15 | K3: 0.15 | L3: 0.15
A4: Algeria | B4: 0.26 | C4: 0.26 | D4: 0.26 | E4: 0.26 | F4: 0.26 | G4: 0.26 | H4: 0.26 | I4: 0.26 | J4: 0.26 | K4: 0.26 | L4: 0.26
A5: Andorra | B5: 0 | C5: 0 | D5: 0.1 | E5: 0.1 | F5: 0.1 | G5: 0.1 | H5: 0.1 | I5: 0.1 | J5: 0.1 | K5: 0.1 | L5: 0.1
A6: Angola | B6: 0.3 | C6: 0.3 | D6: 0.3 | E6: 0.3 | F6: 0.3 | G6: 0.3 | H6: 0.25 | I6: 0.25 | J6: 0.25 | K6: 0.25 | L6: 0.25
A7: Anguilla | B7: 0 | C7: 0 | D7: 0 | E7: 0 | F7: 0 | G7: 0 | H7: 0 | I7: 0 | J7: 0 | K7: 0 | L7: 0
A8: Antigua and Barbuda | B8: 0 | C8: 0 | D8: 0.25 | E8: 0.25 | F8: 0.25 | G8: 0.25 | H8: 0.25 | I8: 0.25 | J8: 0.25 | K8: 0.25 | L8: 0.25
A9: Argentina | B9: 0.35 | C9: 0.35 | D9: 0.35 | E9: 0.3 | F9: 0.3 | G9: 0.3 | H9: 0.25 | I9: 0.35 | J9: 0.35 | K9: 0.35 | L9: 0.35
A10: Armenia | B10: 0.2 | C10: 0.2 | D10: 0.2 | E10: 0.2 | F10: 0.2 | G10: 0.18 | H10: 0.18 | I10: 0.18 | J10: 0.18 | K10: 0.18 | L10: 0.18
A11: Aruba | B11: 0.25 | C11: 0.25 | D11: 0.25 | E11: 0.25 | F11: 0.25 | G11: 0.25 | H11: 0.25 | I11: 0.25 | J11: 0.25 | K11: 0.22 | L11: 0.22
A12: Australia | B12: 0.3 | C12: 0.3 | D12: 0.3 | E12: 0.3 | F12: 0.3 | G12: 0.3 | H12: 0.3 | I12: 0.3 | J12: 0.3 | K12: 0.3 | L12: 0.3
A13: Austria | B13: 0.25 | C13: 0.25 | D13: 0.25 | E13: 0.25 | F13: 0.25 | G13: 0.25 | H13: 0.25 | I13: 0.25 | J13: 0.24 | K13: 0.24 | L13: 0.24
... A15: Bahamas | B15: 0 | C15: 0 | D15: 0 | E15: 0 | F15: 0 | G15: 0 | H15: 0 | I15: 0 | J15: 0 | K15: 0 | L15: 0
A16: Bahrain | B16: 0 | C16: #N/A | D16: 0 | E16: 0 | F16: 0 | G16: 0 | H16: 0 | I16: 0 | J16: 0 | K16: 0 | L16: 0
A17: Bangladesh | B17: 0.25 | C17: 0.25 | D17: 0.25 | E17: 0.25 | F17: 0.25 | G17: 0.25 | H17: 0.325 | I17: 0.325 | J17: 0.325 | K17: 0.275 | L17: 0.275
A18: Barbados | B18: 0.25 | C18: 0.25 | D18: 0.25 | E18: 0.3 | F18: 0.055 | G18: 0.055 | H18: 0.055 | I18: 0.055 | J18: 0.055 | K18: 0.055 | L18: 0.055
A19: Belarus | B19: 0.18 | C19: 0.18 | D19: 0.18 | E19: 0.18 | F19: 0.18 | G19: 0.18 | H19: 0.18 | I19: 0.18 | J19: 0.18 | K19: 0.2 | L19: 0.2
A20: Belgium | B20: 0.3399 | C20: 0.3399 | D20: 0.3399 | E20: 0.29 | F20: 0.29 | G20: 0.25 | H20: 0.25 | I20: 0.25 | J20: 0.25 | K20: 0.25 | L20: 0.25
A21: Benin | B21: 0 | C21: 0 | D21: 0.3 | E21: 0.3 | F21: 0.3 | G21: 0.3 | H21: 0.3 | I21: 0.3 | J21: 0.3 | K21: 0.3 | L21: 0.3
A22: Bermuda | B22: 0 | C22: 0 | D22: 0 | E22: 0 | F22: 0 | G22: 0 | H22: 0 | I22: 0 | J22: 0 | K22: 0 | L22: 0
A23: Bolivia | B23: 0.25 | C23: 0.25 | D23: 0.25 | E23: 0.25 | F23: 0.25 | G23: 0.25 | H23: 0.25 | I23: 0.25 | J23: 0.25 | K23: 0.25 | L23: 0.25
A24: Bonaire, Saint Eustatius and Saba | B24: 0 | C24: 0 | D24: 0.25 | E24: 0.25 | F24: 0.25 | G24: 0.25 | H24: 0.25 | I24: 0.25 | J24: 0.25 | K24: 0.258 | L24: 0.258
A25: Bosnia and Herzegovina | B25: 0.1 | C25: 0.1 | D25: 0.1 | E25: 0.1 | F25: 0.1 | G25: 0.1 | H25: 0.1 | I25: 0.1 | J25: 0.1 | K25: 0.1 | L25: 0.1
A26: Botswana | B26: 0.22 | C26: 0.22 | D26: 0.22 | E26: 0.22 | F26: 0.22 | G26: 0.22 | H26: 0.22 | I26: 0.22 | J26: 0.22 | K26: 0.22 | L26: 0.22
A27: Brazil | B27: 0.34 | C27: 0.34 | D27: 0.34 | E27: 0.34 | F27: 0.34 | G27: 0.34 | H27: 0.34 | I27: 0.34 | J27: 0.34 | K27: 0.34 | L27: 0.34
A28: Brunei Darussalam | B28: 0 | C28: 0 | D28: 0.185 | E28: 0.185 | F28: 0.185 | G28: 0.185 | H28: 0.185 | I28: 0.185 | J28: 0.185 | K28: 0.185 | L28: 0.185
... A38: Colombia | B38: 0.25 | C38: 0.25 | D38: 0.34 | E38: 0.33 | F38: 0.33 | G38: 0.32 | H38: 0.31 | I38: 0.35 | J38: 0.35 | K38: 0.35 | L38: 0.35
A39: Congo | B39: 0 | C39: 0 | D39: 0 | E39: NA | F39: NA | G39: 0.3 | H39: 0.28 | I39: 0.28 | J39: 0.28 | K39: 0.28 | L39: 0.28
A40: Congo (Democratic Republic of the) | B40: 0 | C40: 0 | D40: 0.35 | E40: 0.35 | F40: 0.35 | G40: 0.35 | H40: 0.3 | I40: 0.3 | J40: 0.3 | K40: 0.3 | L40: 0.3
A41: Costa Rica | B41: 0.3 | C41: 0.3 | D41: 0.3 | E41: 0.3 | F41: 0.3 | G41: 0.3 | H41: 0.3 | I41: 0.3 | J41: 0.3 | K41: 0.3 | L41: 0.3
A42: Croatia | B42: 0.2 | C42: 0.2 | D42: 0.2 | E42: 0.18 | F42: 0.18 | G42: 0.18 | H42: 0.18 | I42: 0.18 | J42: 0.18 | K42: 0.18 | L42: 0.18
A43: Curacao | B43: 0.22 | C43: 0.22 | D43: 0.22 | E43: 0.22 | F43: 0.22 | G43: 0.22 | H43: 0.22 | I43: 0.22 | J43: 0.22 | K43: 0.22 | L43: 0.22
A44: Cyprus | B44: 0.125 | C44: 0.125 | D44: 0.125 | E44: 0.125 | F44: 0.125 | G44: 0.125 | H44: 0.125 | I44: 0.125 | J44: 0.125 | K44: 0.125 | L44: 0.125
A45: Czech Republic | B45: 0.19 | C45: 0.19 | D45: 0.19 | E45: 0.19 | F45: 0.19 | G45: 0.19 | H45: 0.19 | I45: 0.19 | J45: 0.19 | K45: 0.19 | L45: 0.19
A46: Denmark | B46: 0.22 | C46: 0.22 | D46: 0.22 | E46: 0.22 | F46: 0.22 | G46: 0.22 | H46: 0.22 | I46: 0.22 | J46: 0.22 | K46: 0.22 | L46: 0.22
A47: Djibouti | B47: 0 | C47: 0 | D47: 0.25 | E47: 0.25 | F47: 0.25 | G47: 0.25 | H47: 0.25 | I47: 0.25 | J47: 0.25 | K47: 0.25 | L47: 0.25
A48: Dominica | B48: 0 | C48: 0 | D48: 0.25 | E48: 0.25 | F48: 0.25 | G48: 0.25 | H48: 0.25 | I48: 0.25 | J48: 0.25 | K48: 0.25 | L48: 0.25
A49: Dominican Republic | B49: 0.27 | C49: 0.27 | D49: 0.27 | E49: 0.27 | F49: 0.27 | G49: 0.27 | H49: 0.27 | I49: 0.27 | J49: 0.27 | K49: 0.27 | L49: 0.27
A50: Ecuador | B50: 0.22 | C50: 0.22 | D50: 0.22 | E50: 0.25 | F50: 0.25 | G50: 0.25 | H50: 0.25 | I50: 0.25 | J50: 0.25 | K50: 0.25 | L50: 0.25
A51: Egypt | B51: 0.225 | C51: 0.225 | D51: 0.225 | E51: 0.23 | F51: 0.225 | G51: 0.225 | H51: 0.225 | I51: 0.225 | J51: 0.225 | K51: 0.225 | L51: 0.225
... A173: Zimbabwe | B173: 0.2575 | C173: 0.2575 | D173: 0.25 | E173: 0.25 | F173: 0.25 | G173: 0.24 | H173: 0.24 | I173: 0.2472 | J173: 0.2472 | K173: 0.2472 | L173: 0.2472
A174: Africa average | B174: 0.2814 | C174: 0.2803 | D174: 0.2821 | E174: 0.2826 | F174: 0.2823 | G174: 0.2825 | H174: 0.24 | I174: 0.24
A175: Americas average | B175: 0.2761 | C175: 0.2771 | D175: 0.2829 | E175: 0.2811 | F175: 0.2736 | G175: 0.2733 | H175: 0.2733 | I175: 0.2733
A176: Asia average | B176: 0.2198 | C176: 0.2141 | D176: 0.2108 | E176: 0.2121 | F176: 0.2118 | G176: 0.2113 | H176: 0.2113 | I176: 0.2113
A177: EU average | B177: 0.2215 | C177: 0.2209 | D177: 0.2133 | E177: 0.2129 | F177: 0.2098 | G177: 0.2087 | H177: 0.2087 | I177: 0.2087
A178: Europe average | B178: 0.2005 | C178: 0.1997 | D178: 0.1953 | E178: 0.1948 | F178: 0.1926 | G178: 0.1912 | H178: 0.1912 | I178: 0.1912
A179: Global average | B179: 0.2377 | C179: 0.2362 | D179: 0.2406 | E179: 0.2405 | F179: 0.2381 | G179: 0.2379 | H179: 0.2379 | I179: 0.2379
A180: Latin America average | B180: 0.2716 | C180: 0.2729 | D180: 0.2798 | E180: 0.282 | F180: 0.2739 | G180: 0.2736 | H180: 0.2736 | I180: 0.2736
A181: North America average | B181: 0.3325 | C181: 0.3325 | D181: 0.3325 | E181: 0.2675 | F181: 0.2675 | G181: 0.2675 | H181: 0.2675 | I181: 0.2675
A182: Oceania average | B182: 0.27 | C182: 0.27 | D182: 0.2843 | E182: 0.2843 | F182: 0.2843 | G182: 0.2843 | H182: 0.2843 | I182: 0.2843
A183: OECD average | B183: 0.2477 | C183: 0.2469 | D183: 0.2395 | E183: 0.2353 | F183: 0.2323 | G183: 0.2305 | H183: 0.2305 | I183: 0.2305
A184: South America average | B184: 0.2716 | C184: 0.2729 | D184: 0.2798 | E184: 0.282 | F184: 0.2739 | G184: 0.2736 | H184: 0.2736 | I184: 0.2736

Sheet Flujos
B2: Detalle de los flujos de la inversión
B4: Horizonte de evaluación (en años) | C4: 5
B5: Periodicidad de los flujos | C5: Anual
B6: Periodos de la inversión | C6: =IF($C$5="Trimestral",$C$4*4,IF($C$5="Anual",$C$4,$C$4*2)) -> 5
B10: Periodo | C10: 0 | D10: 1 | E10: 2 | F10: 3 | G10: 4 | H10: 5 | I10: 6 | J10: 7 | K10: 8 | L10: 9 | M10: 10 | N10: 11 | O10: 12 | P10: 13 | Q10: 14 | R10: 15 | S10: 16 | T10: 17 | U10: 18 | V10: 19 | W10: 20 | X10: 21 | Y10: 22 | Z10: 23 | AA10: 24 | AB10: 25 | AC10: 26 | AD10: 27 | AE10: 28 | AF10: 29 | AG10: 30 | AH10: 31 | AI10: 32 | AJ10: 33 | AK10: 34 | AL10: 35 | AM10: 36 | AN10: 37 | AO10: 38 | AP10: 39 | AQ10: 40 | AR10: 41 | AS10: 42 | AT10: 43 | AU10: 44 | AV10: 45 | AW10: 46 | AX10: 47 | AY10: 48 | AZ10: 49 | BA10: 50 | BB10: 51 | BC10: 52 | BD10: 53 | BE10: 54 | BF10: 55 | BG10: 56 | BH10: 57 | BI10: 58 | BJ10: 59 | BK10: 60 | BL10: 61 | BM10: 62 | BN10: 63 | BO10: 64 | BP10: 65 | BQ10: 66 | BR10: 67 | BS10: 68 | BT10: 69 | BU10: 70 | BV10: 71 | BW10: 72 | BX10: 73 | BY10: 74 | BZ10: 75 | CA10: 76 | CB10: 77 | CC10: 78 | CD10: 79 | CE10: 80 | CF10: 81 | CG10: 82 | CH10: 83 | CI10: 84 | CJ10: 85 | CK10: 86 | CL10: 87 | CM10: 88 | CN10: 89 | CO10: 90 | CP10: 91 | CQ10: 92 | CR10: 93 | CS10: 94 | CT10: 95 | CU10: 96 | CV10: 97 | CW10: 98 | CX10: 99 | CY10: 100 | CZ10: 101 | DA10: 102 | DB10: 103 | DC10: 104 | DD10: 105 | DE10: 106 | DF10: 107 | DG10: 108 | DH10: 109 | DI10: 110 | DJ10: 111 | DK10: 112 | DL10: 113 | DM10: 114 | DN10: 115 | DO10: 116 | DP10: 117 | DQ10: 118 | DR10: 119 | DS10: 120
B11: Flujo de caja | D11: 500 | E11: 500 | F11: 500 | G11: 500 | H11: 500
B12: Flujo de inversiones | C12: 2000

Sheet Tablas
A1: Rf | C1: Bonos | E1: Periocidad de los flujos | G1: Horizonte de evaluación | I1: Rangos | L1: Moneda | N1: Países
A2: Bono EE.UU | C2: 0.25 (3 m) | E2: Trimestral | G2: 1 | I2: Inicio | J2: Fin | L2: Dólares | N2: Argentina
A3: Ajustar Rf según la duración del proyecto | C3: 0.5 (6 m) | E3: Semestral | G3: 2 | I3: 44197 | J3: 44561 | L3: Soles | N3: Brazil
C4: 1 | E4: Anual | G4: 3 | I4: 44562 | J4: 44926 | N4: Chile
C5: 2 | G5: 4 | I5: 44927 | J5: 45291 | N5: Colombia
C6: 3 | G6: 5 | I6: 45292 | J6: 46022 | N6: Ecuador
C7: 5 | G7: 6 | I7: 45658 | J7: 45658 | N7: Mexico
C8: 7 | G8: 7 | N8: Peru
C9: 10 | G9: 8 | N9: United States
C10: 20 | G10: 9
C11: 30 | G11: 10
G12: 11
G13: 12
G14: 13
G15: 14
G16: 15
G17: 16
G18: 17
G19: 18
G20: 19
G21: 20
G22: 21
G23: 22
... G31: 30
A40: Fechas
A41: 45838
A42: 45747
A43: 45657
A44: 45565
A45: 45473
A46: 45382
A47: 45291
A48: 45199
A49: 45107
A50: 45016
A51: 44926
A52: 44834 | B52: =YEAR(A58) -> 2021 | C52: 3.411
A53: 44742 | B53: =YEAR(A59) -> 2016 | C53: 3.356
A54: 44651 | B54: =YEAR(A60) -> 2017 | C54: 3.241
A55: 44561 | B55: =YEAR(A61) -> 2018 | C55: 3.373
A56: 44469 | B56: =YEAR(A62) -> 2019 | C56: 3.314
A57: 44377 | B57: =YEAR(A63) -> 2020 | C57: 3.621
A58: 44286 | B58: =YEAR(A64) -> 2021 | C58: 3.987
A59: 42734 | B59: =YEAR(A65) -> 2022 | C59: 3.852
A60: 43098
A61: 43465
A62: 43830
A63: 44196
A64: 44561
A65: 44895

Sheet M. Integrado
B2: MÉTODO INTEGRADO
B4: 1. Proyección de cuentas
B7: Flujo de caja operativo | C7: =IFERROR('EE.FF Económicos'!D2,"") -> 2017 | D7: =IFERROR('EE.FF Económicos'!E2,"") -> 2018 | E7: =IFERROR('EE.FF Económicos'!F2,"") -> 2019 | F7: =IFERROR('EE.FF Económicos'!G2,"") -> 2020 | G7: =IFERROR('EE.FF Económicos'!H2,"") -> 2021 | H7: 2022 | I7: 2023 | J7: 2024 | K7: 2025 | L7: 2026 | M7: 2027 | N7: 2028 | O7: 2029 | P7: 2030 | Q7: 2031 | R7: 2032 | S7: 2033 | T7: 2034 | U7: 2035 | V7: 2036
C8: =IFERROR('EE.FF Económicos'!D3,"") -> 1 | D8: =IFERROR('EE.FF Económicos'!E3,"") -> 2 | E8: =IFERROR('EE.FF Económicos'!F3,"") -> 3 | F8: =IFERROR('EE.FF Económicos'!G3,"") -> 4 | G8: =IFERROR('EE.FF Económicos'!H3,"") -> 5 | H8: 6 | I8: 7 | J8: 8 | K8: 9 | L8: 10 | M8: 11 | N8: 12 | O8: 13 | P8: 14 | Q8: 15 | R8: 16 | S8: 17 | T8: 18 | U8: 19 | V8: 20
B9: Histórico | C9: =IF('EE.FF Económicos'!D44=0,"",'EE.FF Económicos'!D44) -> 688179.76 | D9: =IF('EE.FF Económicos'!E44=0,"",'EE.FF Económicos'!E44) -> 757098.17 | E9: =IF('EE.FF Económicos'!F44=0,"",'EE.FF Económicos'!F44) -> 966773.38 | F9: =IF('EE.FF Económicos'!G44=0,"",'EE.FF Económicos'!G44) -> 845730.31 | G9: =IF('EE.FF Económicos'!H44=0,"",'EE.FF Económicos'!H44) -> 878655.03
B10: Promedio Móvil | D10: =IF(C9="","",AVERAGE(C9:D9)) -> 722638.96 | E10: =IF(D9="","",AVERAGE(D9:E9)) -> 861935.77 | F10: =IF(E9="","",AVERAGE(E9:F9)) -> 906251.84 | G10: =IF(F9="","",AVERAGE(F9:G9)) -> 862192.67
B11: Tendencia Logarítmica | G11: =LN(F8)*$E$16+$F$21 -> #REF! | H11: =LN(G8)*$E$16+$F$21 -> #REF! | I11: =LN(H8)*$E$16+$F$21 -> #REF! | J11: =LN(I8)*$E$16+$F$21 -> #REF! | K11: =LN(J8)*$E$16+$F$21 -> #REF! | L11: =LN(K8)*$E$16+$F$21 -> #REF! | M11: =LN(L8)*$E$16+$F$21 -> #REF! | N11: =LN(M8)*$E$16+$F$21 -> #REF! | ... V11: =LN(U8)*$E$16+$F$21 -> #REF!
B12: Tasa de crecimiento | H12: =IF(H11/G11-1>'EE.FF Económicos'!$D$53,H11/G11-1,'EE.FF Económicos'!$D$53) -> 0.015 | I12: =IF(I11/H11-1>'EE.FF Económicos'!$D$53,I11/H11-1,'EE.FF Económicos'!$D$53) -> 0.015 | J12: =IF(J11/I11-1>'EE.FF Económicos'!$D$53,J11/I11-1,'EE.FF Económicos'!$D$53) -> 0.015 | K12: =IF(K11/J11-1>'EE.FF Económicos'!$D$53,K11/J11-1,'EE.FF Económicos'!$D$53) -> 0.015 | L12: =IF(L11/K11-1>'EE.FF Económicos'!$D$53,L11/K11-1,'EE.FF Económicos'!$D$53) -> 0.015 | M12: =IF(M11/L11-1>'EE.FF Económicos'!$D$53,M11/L11-1,'EE.FF Económicos'!$D$53) -> 0.015 | N12: =IF(N11/M11-1>'EE.FF Económicos'!$D$53,N11/M11-1,'EE.FF Económicos'!$D$53) -> 0.015 | O12: =IF(O11/N11-1>'EE.FF Económicos'!$D$53,O11/N11-1,'EE.FF Económicos'!$D$53) -> 0.015 | ... V12: =IF(V11/U11-1>'EE.FF Económicos'!$D$53,V11/U11-1,'EE.FF Económicos'!$D$53) -> 0.015
B13: Proyección final | C13: =C9 -> 688179.76 | D13: =D9 -> 757098.17 | E13: =E9 -> 966773.38 | F13: =F9 -> 845730.31 | G13: =G9 -> 878655.03 | H13: =G11*(1+H12) -> #REF! | I13: =H13*(1+I12) -> #REF! | J13: =I13*(1+J12) -> #REF! | K13: =J13*(1+K12) -> #REF! | L13: =K13*(1+L12) -> #REF! | M13: =L13*(1+M12) -> #REF! | N13: =M13*(1+N12) -> #REF! | O13: =N13*(1+O12) -> #REF! | P13: =O13*(1+P12) -> #REF! | ... V13: =U13*(1+V12) -> #REF!
E15: Pendiente | F15: Constante
E16: =INDEX(LINEST(INDEX(C10:G10,COUNTBLANK(C10:G10)+1):G10,LN(INDEX(C8:G8,COUNTBLANK(C10:G10)):INDEX(C8:G8,4)),TRUE,),1) -> #REF! | F16: =INDEX(LINEST(INDEX(C10:G10,COUNTBLANK(C10:G10)+1):G10,LN(INDEX(C8:G8,COUNTBLANK(C10:G10)):INDEX(C8:G8,4)),TRUE,),2) -> #REF!
E18: Ajuste de la constante
E19: Valor real | F19: =G10 -> 862192.67
E20: Valor est. | F20: =LN(F8)*E16+F16 -> #REF!
E21: Const. Aj. | F21: =F16+F19-F20 -> #REF!
B25: 2. Flujo de caja económico
B27: CAPEX | H27: ='M. por conceptos'!H171 -> #REF! | I27: ='M. por conceptos'!I171 -> #REF! | J27: ='M. por conceptos'!J171 -> #REF! | K27: ='M. por conceptos'!K171 -> #REF! | L27: ='M. por conceptos'!L171 -> #REF! | M27: ='M. por conceptos'!M171 -> #REF! | N27: ='M. por conceptos'!N171 -> #REF! | O27: ='M. por conceptos'!O171 -> #REF! | ... V27: ='M. por conceptos'!V171 -> #REF!
B28: Inversiones en capital de trabajo | H28: ='M. por conceptos'!H172 -> #REF! | I28: ='M. por conceptos'!I172 -> #REF! | J28: ='M. por conceptos'!J172 -> #REF! | K28: ='M. por conceptos'!K172 -> #REF! | L28: ='M. por conceptos'!L172 -> #REF! | M28: ='M. por conceptos'!M172 -> #REF! | N28: ='M. por conceptos'!N172 -> #REF! | O28: ='M. por conceptos'!O172 -> #REF! | ... V28: ='M. por conceptos'!V172 -> #REF!
B29: FLUJO DE CAJA ECONÓMICO | H29: =H13+H27+H28 -> #REF! | I29: =I13+I27+I28 -> #REF! | J29: =J13+J27+J28 -> #REF! | K29: =K13+K27+K28 -> #REF! | L29: =L13+L27+L28 -> #REF! | M29: =M13+M27+M28 -> #REF! | N29: =N13+N27+N28 -> #REF! | O29: =O13+O27+O28 -> #REF! | ... V29: =V13+V27+V28 -> #REF!
B30: Valor Terminal | V30: =V29*(1+'EE.FF Económicos'!$D$53)/(WACC!I44-'EE.FF Económicos'!$D$53) -> #REF!
B31: Flujo de caja económico + Valor Terminal | H31: =H29 -> #REF! | I31: =I29 -> #REF! | J31: =J29 -> #REF! | K31: =K29 -> #REF! | L31: =L29 -> #REF! | M31: =M29 -> #REF! | N31: =N29 -> #REF! | O31: =O29 -> #REF! | ... U31: =U29 -> #REF! | V31: =V29+V30 -> #REF!
B34: 3. Valorización con WACC (VALOR CONTABLE)
L36: Valora | M36: BVL | N36: Kallpa
I37: Valor Financiero del Flujo Económico | L37: =NPV(WACC!I44,H31:V31) -> 0
I38: Pasivo | L38: ='EE.FF Económicos'!H24 -> 5437375
I39: Valor del patrimonio | L39: =L37-L38 -> -5437375
I40: Valor por acción | L40: =L39/'Plantilla Usuario'!C5 -> -6.4181162 | M40: 6.05 | N40: 10.1
B42: 4. Valorización con WACC(CAPITALIZACIÓN DE MERCADO)
B44: FLUJO DE CAJA ECONÓMICO | H44: =H29 -> #REF! | I44: =I29 -> #REF! | J44: =J29 -> #REF! | K44: =K29 -> #REF! | L44: =L29 -> #REF! | M44: =M29 -> #REF! | N44: =N29 -> #REF! | O44: =O29 -> #REF! | ... V44: =V29 -> #REF!
B45: Valor Terminal | V45: =V44*(1+'EE.FF Económicos'!$D$53)/(WACC!$AO$38-'EE.FF Económicos'!$D$53) -> #REF!
B46: Flujo de caja económico + Valor Terminal | H46: =H44 -> #REF! | I46: =I44 -> #REF! | J46: =J44 -> #REF! | K46: =K44 -> #REF! | L46: =L44 -> #REF! | M46: =M44 -> #REF! | N46: =N44 -> #REF! | O46: =O44 -> #REF! | ... U46: =U44 -> #REF! | V46: =V44+V45 -> #REF!
L48: Valora | M48: BVL | N48: Kallpa
I49: Valor Financiero del Flujo Económico | L49: =NPV(WACC!AO38,H46:V46) -> 0
I50: Pasivo | L50: =L38 -> 5437375
I51: Valor del patrimonio | L51: =L49-L50 -> -5437375
I52: Valor por acción | L52: =L51/'Plantilla Usuario'!C5 -> -6.4181162 | M52: 6.05 | N52: 10.1
B54: Columna1 | C54: Columna2
B55: Valor Contable del patrimonio | C55: =+L39 -> -5437375
B56: Valor Financiero del Patrimonio | C56: =+L51 -> -5437375
B57: Valor por acción | C57: =+L52 -> -6.4181162

Sheet Hoja1

Sheet Sensibilidad
A2: Método por conceptos
B4: Ingresos | C4: 2021 | D4: 2022 | E4: 2023 | F4: 2024 | G4: 2025 | H4: 2026 | I4: 2027 | J4: 2028 | K4: 2029 | L4: 2030 | M4: 2031 | N4: 2032 | O4: 2033 | P4: 2034 | Q4: 2035 | R4: 2036
C5: 5 | D5: 6 | E5: 7 | F5: 8 | G5: 9 | H5: 10 | I5: 11 | J5: 12 | K5: 13 | L5: 14 | M5: 15 | N5: 16 | O5: 17 | P5: 18 | Q5: 19 | R5: 20
B6: Proyección | C6: ='M. por conceptos'!G11 -> #REF! | D6: ='M. por conceptos'!H11 -> #REF! | E6: ='M. por conceptos'!I11 -> #REF! | F6: ='M. por conceptos'!J11 -> #REF! | G6: ='M. por conceptos'!K11 -> #REF! | H6: ='M. por conceptos'!L11 -> #REF! | I6: ='M. por conceptos'!M11 -> #REF! | J6: ='M. por conceptos'!N11 -> #REF! | ... R6: ='M. por conceptos'!V11 -> #REF!
B7: dProyección/dt | D7: =D6/C6-1 -> #REF! | E7: =E6/D6-1 -> #REF! | F7: =F6/E6-1 -> #REF! | G7: =G6/F6-1 -> #REF! | H7: =H6/G6-1 -> #REF! | I7: =I6/H6-1 -> #REF! | J7: =J6/I6-1 -> #REF! | K7: =K6/J6-1 -> #REF! | ... R7: =R6/Q6-1 -> #REF!
B8: d2Proyección/dt2 | E8: =E7/D7-1 -> #REF! | F8: =F7/E7-1 -> #REF! | G8: =G7/F7-1 -> #REF! | H8: =H7/G7-1 -> #REF! | I8: =I7/H7-1 -> #REF! | J8: =J7/I7-1 -> #REF! | K8: =K7/J7-1 -> #REF! | L8: =L7/K7-1 -> #REF! | ... R8: =R7/Q7-1 -> #REF!
B10: Tasa de Crecimiento | D10: =D7 -> #REF! | E10: =IF(D10*(1+E8)>$G$14,D10*(1+E8),$G$14) -> 0.015 | F10: =IF(E10*(1+F8)>$G$14,E10*(1+F8),$G$14) -> 0.015 | G10: =IF(F10*(1+G8)>$G$14,F10*(1+G8),$G$14) -> 0.015 | H10: =IF(G10*(1+H8)>$G$14,G10*(1+H8),$G$14) -> 0.015 | I10: =IF(H10*(1+I8)>$G$14,H10*(1+I8),$G$14) -> 0.015 | J10: =IF(I10*(1+J8)>$G$14,I10*(1+J8),$G$14) -> 0.015 | K10: =IF(J10*(1+K8)>$G$14,J10*(1+K8),$G$14) -> 0.015 | L10: =IF(K10*(1+L8)>$G$14,K10*(1+L8),$G$14) -> 0.015 | ... R10: =IF(Q10*(1+R8)>$G$14,Q10*(1+R8),$G$14) -> 0.015
B11: Proyección | C11: =C6 -> #REF! | D11: =C11*(1+D10) -> #REF! | E11: =D11*(1+E10) -> #REF! | F11: =E11*(1+F10) -> #REF! | G11: =F11*(1+G10) -> #REF! | H11: =G11*(1+H10) -> #REF! | I11: =H11*(1+I10) -> #REF! | J11: =I11*(1+J10) -> #REF! | K11: =J11*(1+K10) -> #REF! | ... R11: =Q11*(1+R10) -> #REF!
B14: Relación Ingresos - Otras variables | D14: =D10/D7-1 -> #REF! | F14: Gradiente | G14: ='EE.FF Económicos'!D53 -> 0.015
B17: Costos de Ventas | C17: =C$4 -> 2021 | D17: =D$4 -> 2022 | E17: =E$4 -> 2023 | F17: =F$4 -> 2024 | G17: =G$4 -> 2025 | H17: =H$4 -> 2026 | I17: =I$4 -> 2027 | J17: =J$4 -> 2028 | ... R17: =R$4 -> 2036
C18: =C$5 -> 5 | D18: =D$5 -> 6 | E18: =E$5 -> 7 | F18: =F$5 -> 8 | G18: =G$5 -> 9 | H18: =H$5 -> 10 | I18: =I$5 -> 11 | J18: =J$5 -> 12 | ... R18: =R$5 -> 20
B19: Proyección | C19: ='M. por conceptos'!G28 -> #REF! | D19: ='M. por conceptos'!H28 -> #REF! | E19: ='M. por conceptos'!I28 -> #REF! | F19: ='M. por conceptos'!J28 -> #REF! | G19: ='M. por conceptos'!K28 -> #REF! | H19: ='M. por conceptos'!L28 -> #REF! | I19: ='M. por conceptos'!M28 -> #REF! | J19: ='M. por conceptos'!N28 -> #REF! | ... R19: ='M. por conceptos'!V28 -> #REF!
B20: dProyección/dt | D20: =D19/C19-1 -> #REF! | E20: =E19/D19-1 -> #REF! | F20: =F19/E19-1 -> #REF! | G20: =G19/F19-1 -> #REF! | H20: =H19/G19-1 -> #REF! | I20: =I19/H19-1 -> #REF! | J20: =J19/I19-1 -> #REF! | K20: =K19/J19-1 -> #REF! | ... R20: =R19/Q19-1 -> #REF!
B21: d2Proyección/dt2 | E21: =E20/D20-1 -> #REF! | F21: =F20/E20-1 -> #REF! | G21: =G20/F20-1 -> #REF! | H21: =H20/G20-1 -> #REF! | I21: =I20/H20-1 -> #REF! | J21: =J20/I20-1 -> #REF! | K21: =K20/J20-1 -> #REF! | L21: =L20/K20-1 -> #REF! | ... R21: =R20/Q20-1 -> #REF!
B23: Tasa de Crecimiento | D23: =D20*(1+$D$14) -> #REF! | E23: =IF(E10>$G$14,D23*(1+E21),$G$14) -> 0.015 | F23: =IF(F10>$G$14,E23*(1+F21),$G$14) -> 0.015 | G23: =IF(G10>$G$14,F23*(1+G21),$G$14) -> 0.015 | H23: =IF(H10>$G$14,G23*(1+H21),$G$14) -> 0.015 | I23: =IF(I10>$G$14,H23*(1+I21),$G$14) -> 0.015 | J23: =IF(J10>$G$14,I23*(1+J21),$G$14) -> 0.015 | K23: =IF(K10>$G$14,J23*(1+K21),$G$14) -> 0.015 | L23: =IF(L10>$G$14,K23*(1+L21),$G$14) -> 0.015 | ... R23: =IF(R10>$G$14,Q23*(1+R21),$G$14) -> 0.015
B24: Proyección | C24: =C19 -> #REF! | D24: =C24*(1+D23) -> #REF! | E24: =D24*(1+E23) -> #REF! | F24: =E24*(1+F23) -> #REF! | G24: =F24*(1+G23) -> #REF! | H24: =G24*(1+H23) -> #REF! | I24: =H24*(1+I23) -> #REF! | J24: =I24*(1+J23) -> #REF! | K24: =J24*(1+K23) -> #REF! | ... R24: =Q24*(1+R23) -> #REF!
B27: Gastos de ventas | C27: =C$4 -> 2021 | D27: =D$4 -> 2022 | E27: =E$4 -> 2023 | F27: =F$4 -> 2024 | G27: =G$4 -> 2025 | H27: =H$4 -> 2026 | I27: =I$4 -> 2027 | J27: =J$4 -> 2028 | ... R27: =R$4 -> 2036
C28: =C$5 -> 5 | D28: =D$5 -> 6 | E28: =E$5 -> 7 | F28: =F$5 -> 8 | G28: =G$5 -> 9 | H28: =H$5 -> 10 | I28: =I$5 -> 11 | J28: =J$5 -> 12 | ... R28: =R$5 -> 20
B29: Proyección | C29: ='M. por conceptos'!G46 -> #REF! | D29: ='M. por conceptos'!H46 -> #REF! | E29: ='M. por conceptos'!I46 -> #REF! | F29: ='M. por conceptos'!J46 -> #REF! | G29: ='M. por conceptos'!K46 -> #REF! | H29: ='M. por conceptos'!L46 -> #REF! | I29: ='M. por conceptos'!M46 -> #REF! | J29: ='M. por conceptos'!N46 -> #REF! | ... R29: ='M. por conceptos'!V46 -> #REF!
B30: dProyección/dt | D30: =D29/C29-1 -> #REF! | E30: =E29/D29-1 -> #REF! | F30: =F29/E29-1 -> #REF! | G30: =G29/F29-1 -> #REF! | H30: =H29/G29-1 -> #REF! | I30: =I29/H29-1 -> #REF! | J30: =J29/I29-1 -> #REF! | K30: =K29/J29-1 -> #REF! | ... R30: =R29/Q29-1 -> #REF!
B31: d2Proyección/dt2 | E31: =E30/D30-1 -> #REF! | F31: =F30/E30-1 -> #REF! | G31: =G30/F30-1 -> #REF! | H31: =H30/G30-1 -> #REF! | I31: =I30/H30-1 -> #REF! | J31: =J30/I30-1 -> #REF! | K31: =K30/J30-1 -> #REF! | L31: =L30/K30-1 -> #REF! | ... R31: =R30/Q30-1 -> #REF!
B33: Tasa de Crecimiento | D33: =D30*(1+$D$14) -> #REF! | E33: =IF(E$10>$G$14,D33*(1+E31),$G$14) -> 0.015 | F33: =IF(F$10>$G$14,E33*(1+F31),$G$14) -> 0.015 | G33: =IF(G$10>$G$14,F33*(1+G31),$G$14) -> 0.015 | H33: =IF(H$10>$G$14,G33*(1+H31),$G$14) -> 0.015 | I33: =IF(I$10>$G$14,H33*(1+I31),$G$14) -> 0.015 | J33: =IF(J$10>$G$14,I33*(1+J31),$G$14) -> 0.015 | K33: =IF(K$10>$G$14,J33*(1+K31),$G$14) -> 0.015 | L33: =IF(L$10>$G$14,K33*(1+L31),$G$14) -> 0.015 | ... R33: =IF(R$10>$G$14,Q33*(1+R31),$G$14) -> 0.015
B34: Proyección | C34: =C29 -> #REF! | D34: =C34*(1+D33) -> #REF! | E34: =D34*(1+E33) -> #REF! | F34: =E34*(1+F33) -> #REF! | G34: =F34*(1+G33) -> #REF! | H34: =G34*(1+H33) -> #REF! | I34: =H34*(1+I33) -> #REF! | J34: =I34*(1+J33) -> #REF! | K34: =J34*(1+K33) -> #REF! | ... R34: =Q34*(1+R33) -> #REF!
B37: Gastos administrativos | C37: =C$4 -> 2021 | D37: =D$4 -> 2022 | E37: =E$4 -> 2023 | F37: =F$4 -> 2024 | G37: =G$4 -> 2025 | H37: =H$4 -> 2026 | I37: =I$4 -> 2027 | J37: =J$4 -> 2028 | ... R37: =R$4 -> 2036
C38: =C$5 -> 5 | D38: =D$5 -> 6 | E38: =E$5 -> 7 | F38: =F$5 -> 8 | G38: =G$5 -> 9 | H38: =H$5 -> 10 | I38: =I$5 -> 11 | J38: =J$5 -> 12 | ... R38: =R$5 -> 20
B39: Proyección | C39: ='M. por conceptos'!G64 -> #REF! | D39: ='M. por conceptos'!H64 -> #REF! | E39: ='M. por conceptos'!I64 -> #REF! | F39: ='M. por conceptos'!J64 -> #REF! | G39: ='M. por conceptos'!K64 -> #REF! | H39: ='M. por conceptos'!L64 -> #REF! | I39: ='M. por conceptos'!M64 -> #REF! | J39: ='M. por conceptos'!N64 -> #REF! | ... R39: ='M. por conceptos'!V64 -> #REF!
B40: dProyección/dt | D40: =D39/C39-1 -> #REF! | E40: =E39/D39-1 -> #REF! | F40: =F39/E39-1 -> #REF! | G40: =G39/F39-1 -> #REF! | H40: =H39/G39-1 -> #REF! | I40: =I39/H39-1 -> #REF! | J40: =J39/I39-1 -> #REF! | K40: =K39/J39-1 -> #REF! | ... R40: =R39/Q39-1 -> #REF!
B41: d2Proyección/dt2 | E41: =E40/D40-1 -> #REF! | F41: =F40/E40-1 -> #REF! | G41: =G40/F40-1 -> #REF! | H41: =H40/G40-1 -> #REF! | I41: =I40/H40-1 -> #REF! | J41: =J40/I40-1 -> #REF! | K41: =K40/J40-1 -> #REF! | L41: =L40/K40-1 -> #REF! | ... R41: =R40/Q40-1 -> #REF!
B43: Tasa de Crecimiento | D43: =D40*(1+$D$14) -> #REF! | E43: =IF(E$10>$G$14,D43*(1+E41),$G$14) -> 0.015 | F43: =IF(F$10>$G$14,E43*(1+F41),$G$14) -> 0.015 | G43: =IF(G$10>$G$14,F43*(1+G41),$G$14) -> 0.015 | H43: =IF(H$10>$G$14,G43*(1+H41),$G$14) -> 0.015 | I43: =IF(I$10>$G$14,H43*(1+I41),$G$14) -> 0.015 | J43: =IF(J$10>$G$14,I43*(1+J41),$G$14) -> 0.015 | K43: =IF(K$10>$G$14,J43*(1+K41),$G$14) -> 0.015 | L43: =IF(L$10>$G$14,K43*(1+L41),$G$14) -> 0.015 | ... R43: =IF(R$10>$G$14,Q43*(1+R41),$G$14) -> 0.015
B44: Proyección | C44: =C39 -> #REF! | D44: =C44*(1+D43) -> #REF! | E44: =D44*(1+E43) -> #REF! | F44: =E44*(1+F43) -> #REF! | G44: =F44*(1+G43) -> #REF! | H44: =G44*(1+H43) -> #REF! | I44: =H44*(1+I43) -> #REF! | J44: =I44*(1+J43) -> #REF! | K44: =J44*(1+K43) -> #REF! | ... R44: =Q44*(1+R43) -> #REF!
B47: Otros (Neto) | C47: =C$4 -> 2021 | D47: =D$4 -> 2022 | E47: =E$4 -> 2023 | F47: =F$4 -> 2024 | G47: =G$4 -> 2025 | H47: =H$4 -> 2026 | I47: =I$4 -> 2027 | J47: =J$4 -> 2028 | ... R47: =R$4 -> 2036
C48: =C$5 -> 5 | D48: =D$5 -> 6 | E48: =E$5 -> 7 | F48: =F$5 -> 8 | G48: =G$5 -> 9 | H48: =H$5 -> 10 | I48: =I$5 -> 11 | J48: =J$5 -> 12 | ... R48: =R$5 -> 20
B49: Proyección | C49: ='M. por conceptos'!G82 -> #REF! | D49: ='M. por conceptos'!H82 -> #REF! | E49: ='M. por conceptos'!I82 -> #REF! | F49: ='M. por conceptos'!J82 -> #REF! | G49: ='M. por conceptos'!K82 -> #REF! | H49: ='M. por conceptos'!L82 -> #REF! | I49: ='M. por conceptos'!M82 -> #REF! | J49: ='M. por conceptos'!N82 -> #REF! | ... R49: ='M. por conceptos'!V82 -> #REF!
B50: dProyección/dt | D50: =D49/C49-1 -> #REF! | E50: =E49/D49-1 -> #REF! | F50: =F49/E49-1 -> #REF! | G50: =G49/F49-1 -> #REF! | H50: =H49/G49-1 -> #REF! | I50: =I49/H49-1 -> #REF! | J50: =J49/I49-1 -> #REF! | K50: =K49/J49-1 -> #REF! | ... R50: =R49/Q49-1 -> #REF!
B51: d2Proyección/dt2 | E51: =E50/D50-1 -> #REF! | F51: =F50/E50-1 -> #REF! | G51: =G50/F50-1 -> #REF! | H51: =H50/G50-1 -> #REF! | I51: =I50/H50-1 -> #REF! | J51: =J50/I50-1 -> #REF! | K51: =K50/J50-1 -> #REF! | L51: =L50/K50-1 -> #REF! | ... R51: =R50/Q50-1 -> #REF!
B53: Tasa de Crecimiento | D53: =D10 -> #REF! | E53: =IF(E$10>$G$14,D53*(1+E51),$G$14) -> 0.015 | F53: =IF(F$10>$G$14,E53*(1+F51),$G$14) -> 0.015 | G53: =IF(G$10>$G$14,F53*(1+G51),$G$14) -> 0.015 | H53: =IF(H$10>$G$14,G53*(1+H51),$G$14) -> 0.015 | I53: =IF(I$10>$G$14,H53*(1+I51),$G$14) -> 0.015 | J53: =IF(J$10>$G$14,I53*(1+J51),$G$14) -> 0.015 | K53: =IF(K$10>$G$14,J53*(1+K51),$G$14) -> 0.015 | L53: =IF(L$10>$G$14,K53*(1+L51),$G$14) -> 0.015 | ... R53: =IF(R$10>$G$14,Q53*(1+R51),$G$14) -> 0.015
B54: Proyección | C54: =C49 -> #REF! | D54: =C54*(1+D53) -> #REF! | E54: =D54*(1+E53) -> #REF! | F54: =E54*(1+F53) -> #REF! | G54: =F54*(1+G53) -> #REF! | H54: =G54*(1+H53) -> #REF! | I54: =H54*(1+I53) -> #REF! | J54: =I54*(1+J53) -> #REF! | K54: =J54*(1+K53) -> #REF! | ... R54: =Q54*(1+R53) -> #REF!
B57: Depreciación | C57: =C$4 -> 2021 | D57: =D$4 -> 2022 | E57: =E$4 -> 2023 | F57: =F$4 -> 2024 | G57: =G$4 -> 2025 | H57: =H$4 -> 2026 | I57: =I$4 -> 2027 | J57: =J$4 -> 2028 | ... R57: =R$4 -> 2036
C58: =C$5 -> 5 | D58: =D$5 -> 6 | E58: =E$5 -> 7 | F58: =F$5 -> 8 | G58: =G$5 -> 9 | H58: =H$5 -> 10 | I58: =I$5 -> 11 | J58: =J$5 -> 12 | ... R58: =R$5 -> 20
B59: Proyección | C59: ='M. por conceptos'!G100 -> #REF! | D59: ='M. por conceptos'!H100 -> #REF! | E59: ='M. por conceptos'!I100 -> #REF! | F59: ='M. por conceptos'!J100 -> #REF! | G59: ='M. por conceptos'!K100 -> #REF! | H59: ='M. por conceptos'!L100 -> #REF! | I59: ='M. por conceptos'!M100 -> #REF! | J59: ='M. por conceptos'!N100 -> #REF! | ... R59: ='M. por conceptos'!V100 -> #REF!
B60: dProyección/dt | D60: =D59/C59-1 -> #REF! | E60: =E59/D59-1 -> #REF! | F60: =F59/E59-1 -> #REF! | G60: =G59/F59-1 -> #REF! | H60: =H59/G59-1 -> #REF! | I60: =I59/H59-1 -> #REF! | J60: =J59/I59-1 -> #REF! | K60: =K59/J59-1 -> #REF! | ... R60: =R59/Q59-1 -> #REF!
B61: d2Proyección/dt2 | E61: =E60/D60-1 -> #REF! | F61: =F60/E60-1 -> #REF! | G61: =G60/F60-1 -> #REF! | H61: =H60/G60-1 -> #REF! | I61: =I60/H60-1 -> #REF! | J61: =J60/I60-1 -> #REF! | K61: =K60/J60-1 -> #REF! | L61: =L60/K60-1 -> #REF! | ... R61: =R60/Q60-1 -> #REF!
B63: Tasa de Crecimiento | D63: =D60*(1+$D$14) -> #REF! | E63: =IF(E$10>$G$14,D63*(1+E61),$G$14) -> 0.015 | F63: =IF(F$10>$G$14,E63*(1+F61),$G$14) -> 0.015 | G63: =IF(G$10>$G$14,F63*(1+G61),$G$14) -> 0.015 | H63: =IF(H$10>$G$14,G63*(1+H61),$G$14) -> 0.015 | I63: =IF(I$10>$G$14,H63*(1+I61),$G$14) -> 0.015 | J63: =IF(J$10>$G$14,I63*(1+J61),$G$14) -> 0.015 | K63: =IF(K$10>$G$14,J63*(1+K61),$G$14) -> 0.015 | L63: =IF(L$10>$G$14,K63*(1+L61),$G$14) -> 0.015 | ... R63: =IF(R$10>$G$14,Q63*(1+R61),$G$14) -> 0.015
B64: Proyección | C64: =C59 -> #REF! | D64: =C64*(1+D63) -> #REF! | E64: =D64*(1+E63) -> #REF! | F64: =E64*(1+F63) -> #REF! | G64: =F64*(1+G63) -> #REF! | H64: =G64*(1+H63) -> #REF! | I64: =H64*(1+I63) -> #REF! | J64: =I64*(1+J63) -> #REF! | K64: =J64*(1+K63) -> #REF! | ... R64: =Q64*(1+R63) -> #REF!
B67: CAPEX | C67: =C$4 -> 2021 | D67: =D$4 -> 2022 | E67: =E$4 -> 2023 | F67: =F$4 -> 2024 | G67: =G$4 -> 2025 | H67: =H$4 -> 2026 | I67: =I$4 -> 2027 | J67: =J$4 -> 2028 | ... R67: =R$4 -> 2036
C68: =C$5 -> 5 | D68: =D$5 -> 6 | E68: =E$5 -> 7 | F68: =F$5 -> 8 | G68: =G$5 -> 9 | H68: =H$5 -> 10 | I68: =I$5 -> 11 | J68: =J$5 -> 12 | ... R68: =R$5 -> 20
C69: ='M. por conceptos'!G120 -> #REF! | D69: ='M. por conceptos'!H121 -> #REF! | E69: ='M. por conceptos'!I121 -> #REF! | F69: ='M. por conceptos'!J121 -> #REF! | G69: ='M. por conceptos'!K121 -> #REF! | H69: ='M. por conceptos'!L121 -> #REF! | I69: ='M. por conceptos'!M121 -> #REF! | J69: ='M. por conceptos'!N121 -> #REF! | K69: ='M. por conceptos'!O121 -> #REF! | ... R69: ='M. por conceptos'!V121 -> #REF!
C70: =C69*C11 -> #REF! | D70: =D69*D11 -> #REF! | E70: =E69*E11 -> #REF! | F70: =F69*F11 -> #REF! | G70: =G69*G11 -> #REF! | H70: =H69*H11 -> #REF! | I70: =I69*I11 -> #REF! | J70: =J69*J11 -> #REF! | ... R70: =R69*R11 -> #REF!
B73: Capital de trabajo | C73: =C$4 -> 2021 | D73: =D$4 -> 2022 | E73: =E$4 -> 2023 | F73: =F$4 -> 2024 | G73: =G$4 -> 2025 | H73: =H$4 -> 2026 | I73: =I$4 -> 2027 | J73: =J$4 -> 2028 | ... R73: =R$4 -> 2036
C74: =C$5 -> 5 | D74: =D$5 -> 6 | E74: =E$5 -> 7 | F74: =F$5 -> 8 | G74: =G$5 -> 9 | H74: =H$5 -> 10 | I74: =I$5 -> 11 | J74: =J$5 -> 12 | ... R74: =R$5 -> 20
C75: ='M. por conceptos'!G142 -> #REF! | D75: ='M. por conceptos'!H142 -> #REF! | E75: ='M. por conceptos'!I142 -> #REF! | F75: ='M. por conceptos'!J142 -> #REF! | G75: ='M. por conceptos'!K142 -> #REF! | H75: ='M. por conceptos'!L142 -> #REF! | I75: ='M. por conceptos'!M142 -> #REF! | J75: ='M. por conceptos'!N142 -> #REF! | ... R75: ='M. por conceptos'!V142 -> #REF!
C76: =C75*C11 -> #REF! | D76: =D75*D11 -> #REF! | E76: =E75*E11 -> #REF! | F76: =F75*F11 -> #REF! | G76: =G75*G11 -> #REF! | H76: =H75*H11 -> #REF! | I76: =I75*I11 -> #REF! | J76: =J75*J11 -> #REF! | ... R76: =R75*R11 -> #REF!
D77: =D76-C76 -> #REF! | E77: =E76-D76 -> #REF! | F77: =F76-E76 -> #REF! | G77: =G76-F76 -> #REF! | H77: =H76-G76 -> #REF! | I77: =I76-H76 -> #REF! | J77: =J76-I76 -> #REF! | K77: =K76-J76 -> #REF! | ... R77: =R76-Q76 -> #REF!
D80: =D$4 -> 2022 | E80: =E$4 -> 2023 | F80: =F$4 -> 2024 | G80: =G$4 -> 2025 | H80: =H$4 -> 2026 | I80: =I$4 -> 2027 | J80: =J$4 -> 2028 | K80: =K$4 -> 2029 | ... R80: =R$4 -> 2036
D81: =D$5 -> 6 | E81: =E$5 -> 7 | F81: =F$5 -> 8 | G81: =G$5 -> 9 | H81: =H$5 -> 10 | I81: =I$5 -> 11 | J81: =J$5 -> 12 | K81: =K$5 -> 13 | ... R81: =R$5 -> 20
B82: Ingresos | D82: =D11 -> #REF! | E82: =E11 -> #REF! | F82: =F11 -> #REF! | G82: =G11 -> #REF! | H82: =H11 -> #REF! | I82: =I11 -> #REF! | J82: =J11 -> #REF! | K82: =K11 -> #REF! | ... R82: =R11 -> #REF!
B83: Costo de ventas | D83: =D24 -> #REF! | E83: =E24 -> #REF! | F83: =F24 -> #REF! | G83: =G24 -> #REF! | H83: =H24 -> #REF! | I83: =I24 -> #REF! | J83: =J24 -> #REF! | K83: =K24 -> #REF! | ... R83: =R24 -> #REF!
B84: GANANCIA BRUTA | D84: =D82-D83 -> #REF! | E84: =E82-E83 -> #REF! | F84: =F82-F83 -> #REF! | G84: =G82-G83 -> #REF! | H84: =H82-H83 -> #REF! | I84: =I82-I83 -> #REF! | J84: =J82-J83 -> #REF! | K84: =K82-K83 -> #REF! | ... R84: =R82-R83 -> #REF!
B85: Gastos de Ventas y Distribución | D85: =IFERROR(D34,0) -> 0 | E85: =IFERROR(E34,0) -> 0 | F85: =IFERROR(F34,0) -> 0 | G85: =IFERROR(G34,0) -> 0 | H85: =IFERROR(H34,0) -> 0 | I85: =IFERROR(I34,0) -> 0 | J85: =IFERROR(J34,0) -> 0 | K85: =IFERROR(K34,0) -> 0 | ... R85: =IFERROR(R34,0) -> 0
B86: Gastos de Administración | D86: =D44 -> #REF! | E86: =E44 -> #REF! | F86: =F44 -> #REF! | G86: =G44 -> #REF! | H86: =H44 -> #REF! | I86: =I44 -> #REF! | J86: =J44 -> #REF! | K86: =K44 -> #REF! | ... R86: =R44 -> #REF!
B87: Otros Neto | D87: =D54 -> #REF! | E87: =E54 -> #REF! | F87: =F54 -> #REF! | G87: =G54 -> #REF! | H87: =H54 -> #REF! | I87: =I54 -> #REF! | J87: =J54 -> #REF! | K87: =K54 -> #REF! | ... R87: =R54 -> #REF!
B88: UTILIDAD OPERATIVA ANTES DE IMPUESTOS | D88: =D84-D85-D86+D87 -> #REF! | E88: =E84-E85-E86+E87 -> #REF! | F88: =F84-F85-F86+F87 -> #REF! | G88: =G84-G85-G86+G87 -> #REF! | H88: =H84-H85-H86+H87 -> #REF! | I88: =I84-I85-I86+I87 -> #REF! | J88: =J84-J85-J86+J87 -> #REF! | K88: =K84-K85-K86+K87 -> #REF! | ... R88: =R84-R85-R86+R87 -> #REF!
B89: Impuestos | D89: =29.5%*D88 -> #REF! | E89: =29.5%*E88 -> #REF! | F89: =29.5%*F88 -> #REF! | G89: =29.5%*G88 -> #REF! | H89: =29.5%*H88 -> #REF! | I89: =29.5%*I88 -> #REF! | J89: =29.5%*J88 -> #REF! | K89: =29.5%*K88 -> #REF! | ... R89: =29.5%*R88 -> #REF!
B90: Depreciación y amortización | D90: =Sensibilidad!D64 -> #REF! | E90: =Sensibilidad!E64 -> #REF! | F90: =Sensibilidad!F64 -> #REF! | G90: =Sensibilidad!G64 -> #REF! | H90: =Sensibilidad!H64 -> #REF! | I90: =Sensibilidad!I64 -> #REF! | J90: =Sensibilidad!J64 -> #REF! | K90: =Sensibilidad!K64 -> #REF! | ... R90: =Sensibilidad!R64 -> #REF!
B91: UTILIDAD OP. DESPUÉS DE IMPUESTOS | D91: =D88-D89+D90 -> #REF! | E91: =E88-E89+E90 -> #REF! | F91: =F88-F89+F90 -> #REF! | G91: =G88-G89+G90 -> #REF! | H91: =H88-H89+H90 -> #REF! | I91: =I88-I89+I90 -> #REF! | J91: =J88-J89+J90 -> #REF! | K91: =K88-K89+K90 -> #REF! | ... R91: =R88-R89+R90 -> #REF!
B92: CAPEX | D92: =-D70 -> #REF! | E92: =-E70 -> #REF! | F92: =-F70 -> #REF! | G92: =-G70 -> #REF! | H92: =-H70 -> #REF! | I92: =-I70 -> #REF! | J92: =-J70 -> #REF! | K92: =-K70 -> #REF! | ... R92: =-R70 -> #REF!
B93: Inversiones en capital de trabajo | D93: =-D77 -> #REF! | E93: =-E77 -> #REF! | F93: =-F77 -> #REF! | G93: =-G77 -> #REF! | H93: =-H77 -> #REF! | I93: =-I77 -> #REF! | J93: =-J77 -> #REF! | K93: =-K77 -> #REF! | ... R93: =-R77 -> #REF!
B94: FLUJO DE CAJA ECONÓMICO | D94: =SUM(D91:D93) -> #REF! | E94: =SUM(E91:E93) -> #REF! | F94: =SUM(F91:F93) -> #REF! | G94: =SUM(G91:G93) -> #REF! | H94: =SUM(H91:H93) -> #REF! | I94: =SUM(I91:I93) -> #REF! | J94: =SUM(J91:J93) -> #REF! | K94: =SUM(K91:K93) -> #REF! | ... R94: =SUM(R91:R93) -> #REF!
B95: Valor Terminal | R95: =R94*(1+G14)/($M$100-G14) -> #REF!
B96: Flujo de caja económico + Valor terminal | D96: =D94 -> #REF! | E96: =E94 -> #REF! | F96: =F94 -> #REF! | G96: =G94 -> #REF! | H96: =H94 -> #REF! | I96: =I94 -> #REF! | J96: =J94 -> #REF! | K96: =K94 -> #REF! | ... Q96: =Q94 -> #REF! | R96: =R94+R95 -> #REF!
H99: Valora | I99: BVL | J99: Kallpa
E100: Valor Financiero del Flujo Económico | H100: =NPV(M100,D96:R96) -> 0 | L100: WACC | M100: =WACC!I44 -> 0.091
E101: Pasivo | H101: ='EE.FF Económicos'!$H$24 -> 5437375
E102: Valor del patrimonio | H102: =H100-H101 -> -5437375
E103: Valor por acción | H103: =H102/'Plantilla Usuario'!C5 -> -6.4181162 | I103: 6.05 | J103: 10.1
A108: Método Integrado
B110: Flujo de caja operativo | C110: =C$4 -> 2021 | D110: =D$4 -> 2022 | E110: =E$4 -> 2023 | F110: =F$4 -> 2024 | G110: =G$4 -> 2025 | H110: =H$4 -> 2026 | I110: =I$4 -> 2027 | J110: =J$4 -> 2028 | ... R110: =R$4 -> 2036
C111: =C$5 -> 5 | D111: =D$5 -> 6 | E111: =E$5 -> 7 | F111: =F$5 -> 8 | G111: =G$5 -> 9 | H111: =H$5 -> 10 | I111: =I$5 -> 11 | J111: =J$5 -> 12 | ... R111: =R$5 -> 20
B112: Proyección | C112: ='M. Integrado'!G11 -> #REF! | D112: ='M. Integrado'!H11 -> #REF! | E112: ='M. Integrado'!I11 -> #REF! | F112: ='M. Integrado'!J11 -> #REF! | G112: ='M. Integrado'!K11 -> #REF! | H112: ='M. Integrado'!L11 -> #REF! | I112: ='M. Integrado'!M11 -> #REF! | J112: ='M. Integrado'!N11 -> #REF! | ... R112: ='M. Integrado'!V11 -> #REF!
B113: dProyección/dt | D113: =D112/C112-1 -> #REF! | E113: =E112/D112-1 -> #REF! | F113: =F112/E112-1 -> #REF! | G113: =G112/F112-1 -> #REF! | H113: =H112/G112-1 -> #REF! | I113: =I112/H112-1 -> #REF! | J113: =J112/I112-1 -> #REF! | K113: =K112/J112-1 -> #REF! | ... R113: =R112/Q112-1 -> #REF!
B114: d2Proyección/dt2 | E114: =E113/D113-1 -> #REF! | F114: =F113/E113-1 -> #REF! | G114: =G113/F113-1 -> #REF! | H114: =H113/G113-1 -> #REF! | I114: =I113/H113-1 -> #REF! | J114: =J113/I113-1 -> #REF! | K114: =K113/J113-1 -> #REF! | L114: =L113/K113-1 -> #REF! | ... R114: =R113/Q113-1 -> #REF!
B116: Tasa de Crecimiento | D116: =D113*(1+$D$14) -> #REF! | E116: =D116*(1+E114) -> #REF! | F116: =E116*(1+F114) -> #REF! | G116: =F116*(1+G114) -> #REF! | H116: =G116*(1+H114) -> #REF! | I116: =H116*(1+I114) -> #REF! | J116: =I116*(1+J114) -> #REF! | K116: =J116*(1+K114) -> #REF! | L116: =K116*(1+L114) -> #REF! | ... R116: =Q116*(1+R114) -> #REF!
B117: Proyección | C117: =C112 -> #REF! | D117: =C117*(1+D116) -> #REF! | E117: =D117*(1+E116) -> #REF! | F117: =E117*(1+F116) -> #REF! | G117: =F117*(1+G116) -> #REF! | H117: =G117*(1+H116) -> #REF! | I117: =H117*(1+I116) -> #REF! | J117: =I117*(1+J116) -> #REF! | K117: =J117*(1+K116) -> #REF! | ... R117: =Q117*(1+R116) -> #REF!
B120: CAPEX | D120: =D92 -> #REF! | E120: =E92 -> #REF! | F120: =F92 -> #REF! | G120: =G92 -> #REF! | H120: =H92 -> #REF! | I120: =I92 -> #REF! | J120: =J92 -> #REF! | K120: =K92 -> #REF! | ... R120: =R92 -> #REF!
B121: Inversiones en capital de trabajo | D121: =D93 -> #REF! | E121: =E93 -> #REF! | F121: =F93 -> #REF! | G121: =G93 -> #REF! | H121: =H93 -> #REF! | I121: =I93 -> #REF! | J121: =J93 -> #REF! | K121: =K93 -> #REF! | ... R121: =R93 -> #REF!
B122: FLUJO DE CAJA ECONÓMICO | D122: =D117+D120+D121 -> #REF! | E122: =E117+E120+E121 -> #REF! | F122: =F117+F120+F121 -> #REF! | G122: =G117+G120+G121 -> #REF! | H122: =H117+H120+H121 -> #REF! | I122: =I117+I120+I121 -> #REF! | J122: =J117+J120+J121 -> #REF! | K122: =K117+K120+K121 -> #REF! | ... R122: =R117+R120+R121 -> #REF!
B123: Valor Terminal | R123: =R122*(1+G14)/($M$100-G14) -> #REF!
B124: Flujo de caja económico + Valor Terminal | D124: =D122 -> #REF! | E124: =E122 -> #REF! | F124: =F122 -> #REF! | G124: =G122 -> #REF! | H124: =H122 -> #REF! | I124: =I122 -> #REF! | J124: =J122 -> #REF! | K124: =K122 -> #REF! | ... Q124: =Q122 -> #REF! | R124: =R122+R123 -> #REF!
H129: Valora | I129: BVL | J129: Kallpa
E130: Valor Financiero del Flujo Económico | H130: =NPV(M100,D124:R124) -> 0
E131: Pasivo | H131: =H101 -> 5437375
E132: Valor del patrimonio | H132: =H130-H131 -> -5437375
E133: Valor por acción | H133: =H132/'Plantilla Usuario'!C5 -> -6.4181162 | I133: 6.05 | J133: 10.1

Sheet BVL
A1: Empresa | B1: ID | C1: N. de acciones | D1: Capitalización_Bursátil | E1: Valor_por_accion
A2: AENZA S.A.A. | B2: AENZAC1 | C2: 1196979979 | D2: 5.0273159e+08 | E2: =D2/C2 -> 0.42
A3: ALICORP S.A.A. | B3: ALICORC1 | C3: 847191731 | D3: 5.9727017e+09 | E3: =D3/C3 -> 7.05
A4: A.F.P. INTEGRA S.A. | B4: INTEGRC1 | C4: 554677 | D4: 55467700 | E4: =D4/C4 -> 100
A5: ADMINISTRADORA DEL COMERCIO S.A. | B5: ADCOMEC1 | C5: 68835948 | D5: 28911098 | E5: =D5/C5 -> 0.42
A6: AFP HABITAT S.A. | B6: HABITAC1 | C6: 41826232 | D6: 41826232 | E6: =D6/C6 -> 1
A7: AGRO INDUSTRIAL PARAMONGA S.A.A. | B7: PARAMOC1 | C7: 33270968 | D7: 349345164 | E7: =D7/C7 -> 10.5
A8: AGRO PUCALA S.A.A. | B8: PUCALAC1 | C8: 20882274 | D8: 6473504.9 | E8: =D8/C8 -> 0.31
A9: AGROINDUSTRIAL LAREDO S.A.A. | B9: LAREDOC1 | C9: 11563369 | D9: 2.1392233e+08 | E9: =D9/C9 -> 18.5
A10: AGROINDUSTRIAS AIB S.A. | B10: AIBC1 | C10: 102895336 | D10: 102895336 | E10: =D10/C10 -> 1
A11: AGROINDUSTRIAS SAN JACINTO SOCIEDAD ANONIMA ABIERTA (AGROINDUSTRIAS SAN JACINTO S.A.A.) | B11: SNJACIC1 | C11: 28452786 | D11: 213395895 | E11: =D11/C11 -> 7.5
A12: AGROKASA HOLDINGS S.A. | B12: AGROKAC1 | C12: 66475362 | D12: 4.5868e+08 | E12: =D12/C12 -> 6.9
A13: AGRÍCOLA CAYALTÍ S.A.A. | B13: CAYALTC1 | C13: 237958555 | D13: 1.7846892e+08 | E13: =D13/C13 -> 0.75
... A195: VOLVO FINANCIAL SERVICES EMPRESA DE CREDITOS S.A. | B195: VFSECAC1 | C195: 5250000 | D195: 5250000 | E195: =D195/C195 -> 1
